Workbook
Name Additives_Data: #REF!
Name Applications_Data: Applications!$A$1:$BD$500
Name Applicator_Data: #REF!
Name Crop_Data: #REF!
Name crop_year: #REF!
Name Farm_Data: #REF!
Name Field_Data: Customer_Data!$A$1:$P$115
Name operation_name: #REF!
Name Pest_Data: #REF!
Name Pesticide_Data: #REF!
Name Pesticide_List_Copy: #REF!
Name Pesticide_List_Criteria: #REF!
Name Pesticide_Type_Table: #REF!
Name PPE_Code_Table: #REF!
Name Variety_Data: #REF!

Sheet Main
A1: Time Out Lawncare LLC
A3: Operator: | B3: Time Out Lawncare LLC
A4: Year: | B4: 2024 | C4: 2025 | D4: 2026

Sheet Applications
A1: Customer Name | B1: Application Date | C1: Application Start Time | D1: Application End Time | E1: Applicator | F1: ID number | G1: Treatment Type | H1: Size of Area Treated | J1: Brand Name 1 | K1: Active Ingredients | L1: Rate per Acre | M1: Total Amount Applied (Oz) | N1: Brand Name 2 | O1: Active Ingredients | P1: Rate per Acre | Q1: Total Amount Applied (Oz) | R1: Brand Name 3 | S1: Active Ingredients | T1: Rate per Acre | U1: Total Amount Applied (Oz) | V1: Brand Name 4 | W1: Active Ingredients | X1: Rate per Acre | Y1: Total Amount Applied (Oz) | Z1: Brand Name 5 | AA1: Active Ingredients | AB1: Rate per Acre | AC1: Total Amount Applied (Oz) | AD1: Brand Name 6 | AE1: Active Ingredients | AF1: Rate per Acre | AG1: Total Amount Applied (Oz) | AH1: Additive | AI1: Rate per Acre | AJ1: Total Amount Applied (Oz) | AK1: Applic. Method | AL1: Applic. Equip. | AM1: Wind Dir. | AN1: Wind Speed | AO1: Temp. | AP1: Rel. Hum. | AQ1: Herbicide $/Unit of Product | AR1: Herbicide Cost | AS1: Herbicide Cost/Acre | AT1: Total Herbicide Cost | AU1: Total Herbicide Cost/Acre | AV1: Addit. 1 $/Unit of Product | AW1: Addit. 1 Cost | AX1: Addit. 1 Cost/Acre | AY1: Total Chemical Cost | AZ1: Total Chemical Cost/Acre | BA1: Total Applic. Cost | BB1: Total Applic. Cost/Acre | BC1: Total Cost | BD1: Total Cost/Acre
A2: Max Miller | B2: 45591 | C2: 0.5 | D2: =C2+0.0208333 -> 0.5208333 | E2: Matthew Stowers | F2: =IFERROR(VLOOKUP(E2,Data!A$2:B$5,2,TRUE), "") -> 48160 | G2: Fall (pre/post emerge) | H2: =IFERROR(VLOOKUP(A2,Customer_Data!$A$1:$P$114,8,TRUE),"") -> 3100 | J2: =IF($G2=("Fall (pre/post emerge)"),"Princep Liquid (100-526)", IF($G2=("Fertilize"),"Harrell's 34-0-5",IF($G2=("Spot Treat"),"Outrider (59639-223)",""))) -> Princep Liquid (100-526) | K2: Simazine | L2: 32 | M2: =L2*(H2/43560) -> 2.2773186 | N2: =IF($G2=("Fall (pre/post emerge)"),"Triplet SF (3-Way) 228-312",IF($G2=("Spring Preemerge (Jan)"),"Triplet SF (3-Way) 228-312",IF($G2=("Spring Preemerge (Apr)"),"Triplet SF (3-Way) 228-312",""))) -> Triplet SF (3-Way) 228-312 | O2: =VLOOKUP($N2,Herbicide_Data!$A$1:$L$61,9) -> 2,4-D, dimethylamine salt; Dicamba, dimethylamine salt;Mecoprop-p (MCPP-p), dimethylamine salt | P2: =VLOOKUP($N2,Herbicide_Data!$A$1:$L$61,12) -> 24 | Q2: =P2*($H2/43560) -> 1.707989 | R2: =IF($G2=("Fall (pre/post emerge)"),"Resolute 4Fl (100-1139)",IF($G2=("Spring Preemerge (Jan)"),"Resolute 4Fl (100-1139)",IF($G2=("Spring Preemerge (Apr)"),"Certinty Turf 59639-226",""))) -> Resolute 4Fl (100-1139) | S2: =VLOOKUP($R2,Herbicide_Data!$A$1:$L$61,9) -> Prodiamine | T2: =VLOOKUP($R2,Herbicide_Data!$A$1:$L$61,12) -> 16 | U2: =T2*($H2/43560) -> 1.1386593 | V2: =IF($G2 = ("Preemerge"),"MSM Turf 228-373") -> FALSE | W2: =VLOOKUP($V2,Herbicide_Data!$A$1:$L$17,9) -> #N/A | X2: =VLOOKUP($V2,Herbicide_Data!$A$1:$L$17,12) -> #N/A | Y2: =X2*($H2/43560) -> #N/A | AH2: =IF($G2 = ("Preemerge"),"Surfactant") -> FALSE | AI2: =VLOOKUP($AH2,Herbicide_Data!$A$1:$L$17,12) -> #N/A | AJ2: =AI2*($H2/43560) -> #N/A
A3: Dot Stuart | B3: 45591 | C3: 0.54166667 | D3: =C3+0.0208333 -> 0.56249997 | E3: Matthew Stowers | F3: =IFERROR(VLOOKUP(E3,Data!A$2:B$5,2,TRUE), "") -> 48160 | G3: Fall (pre/post emerge) | H3: =IFERROR(VLOOKUP(A3,Customer_Data!$A$1:$P$114,8,TRUE),"") -> 1800 | J3: =IF($G3=("Fall (pre/post emerge)"),"Princep Liquid (100-526)", IF($G3=("Fertilize"),"Harrell's 34-0-5",IF($G3=("Spot Treat"),"Outrider (59639-223)",""))) -> Princep Liquid (100-526) | K3: =(VLOOKUP($J3,Herbicide_Data!$A$1:$L$61,9,TRUE)) -> Simazine | L3: =VLOOKUP($J3,Herbicide_Data!$A$1:$L$61,12,TRUE) -> 32 | M3: =L3*(H3/43560) -> 1.322314 | N3: =IF($G3=("Fall (pre/post emerge)"),"Triplet SF (3-Way) 228-312",IF($G3=("Spring Preemerge (Jan)"),"Triplet SF (3-Way) 228-312",IF($G3=("Spring Preemerge (Apr)"),"Triplet SF (3-Way) 228-312",""))) -> Triplet SF (3-Way) 228-312 | O3: =VLOOKUP($N3,Herbicide_Data!$A$1:$L$61,9) -> 2,4-D, dimethylamine salt; Dicamba, dimethylamine salt;Mecoprop-p (MCPP-p), dimethylamine salt | P3: =VLOOKUP($N3,Herbicide_Data!$A$1:$L$61,12) -> 24 | Q3: =P3*($H3/43560) -> 0.99173554 | R3: =IF($G3=("Fall (pre/post emerge)"),"Resolute 4Fl (100-1139)",IF($G3=("Spring Preemerge (Jan)"),"Resolute 4Fl (100-1139)",IF($G3=("Spring Preemerge (Apr)"),"Certinty Turf 59639-226",""))) -> Resolute 4Fl (100-1139) | S3: =VLOOKUP($R3,Herbicide_Data!$A$1:$L$61,9) -> Prodiamine | T3: =VLOOKUP($R3,Herbicide_Data!$A$1:$L$61,12) -> 16 | U3: =T3*($H3/43560) -> 0.66115702 | V3: =IF($G3 = ("Preemerge"),"MSM Turf 228-373") -> FALSE | W3: =VLOOKUP($V3,Herbicide_Data!$A$1:$L$17,9) -> #N/A | X3: =VLOOKUP($V3,Herbicide_Data!$A$1:$L$17,12) -> #N/A | Y3: =X3*($H3/43560) -> #N/A | AH3: =IF($G3 = ("Preemerge"),"Surfactant") -> FALSE | AI3: =VLOOKUP($AH3,Herbicide_Data!$A$1:$L$17,12) -> #N/A | AJ3: =AI3*($H3/43560) -> #N/A
A4: Matt Runner | B4: 45591 | C4: 0.58333333 | D4: =C4+0.0208333 -> 0.60416663 | E4: Matthew Stowers | F4: =IFERROR(VLOOKUP(E4,Data!A$2:B$5,2,TRUE), "") -> 48160 | G4: Fall (pre/post emerge) | H4: =IFERROR(VLOOKUP(A4,Customer_Data!$A$1:$P$114,8,TRUE),"") -> 2000 | J4: =IF($G4=("Fall (pre/post emerge)"),"Princep Liquid (100-526)", IF($G4=("Fertilize"),"Harrell's 34-0-5",IF($G4=("Spot Treat"),"Outrider (59639-223)",""))) -> Princep Liquid (100-526) | K4: =(VLOOKUP($J4,Herbicide_Data!$A$1:$L$61,9,TRUE)) -> Simazine | L4: =VLOOKUP($J4,Herbicide_Data!$A$1:$L$61,12,TRUE) -> 32 | M4: =L4*(H4/43560) -> 1.4692378 | N4: =IF($G4=("Fall (pre/post emerge)"),"Triplet SF (3-Way) 228-312",IF($G4=("Spring Preemerge (Jan)"),"Triplet SF (3-Way) 228-312",IF($G4=("Spring Preemerge (Apr)"),"Triplet SF (3-Way) 228-312",""))) -> Triplet SF (3-Way) 228-312 | O4: =VLOOKUP($N4,Herbicide_Data!$A$1:$L$61,9) -> 2,4-D, dimethylamine salt; Dicamba, dimethylamine salt;Mecoprop-p (MCPP-p), dimethylamine salt | P4: =VLOOKUP($N4,Herbicide_Data!$A$1:$L$61,12) -> 24 | Q4: =P4*($H4/43560) -> 1.1019284 | R4: =IF($G4=("Fall (pre/post emerge)"),"Resolute 4Fl (100-1139)",IF($G4=("Spring Preemerge (Jan)"),"Resolute 4Fl (100-1139)",IF($G4=("Spring Preemerge (Apr)"),"Certinty Turf 59639-226",""))) -> Resolute 4Fl (100-1139) | S4: =VLOOKUP($R4,Herbicide_Data!$A$1:$L$61,9) -> Prodiamine | T4: =VLOOKUP($R4,Herbicide_Data!$A$1:$L$61,12) -> 16 | U4: =T4*($H4/43560) -> 0.73461892 | V4: =IF($G4 = ("Preemerge"),"MSM Turf 228-373") -> FALSE | W4: =VLOOKUP($V4,Herbicide_Data!$A$1:$L$17,9) -> #N/A | X4: =VLOOKUP($V4,Herbicide_Data!$A$1:$L$17,12) -> #N/A | Y4: =X4*($H4/43560) -> #N/A | AH4: =IF($G4 = ("Preemerge"),"Surfactant") -> FALSE | AI4: =VLOOKUP($AH4,Herbicide_Data!$A$1:$L$17,12) -> #N/A | AJ4: =AI4*($H4/43560) -> #N/A
A5: Luther Stowers | B5: 45591 | C5: 0.60416667 | D5: =C5+0.0208333 -> 0.62499997 | E5: Luther Stowers | F5: =IFERROR(VLOOKUP(E5,Data!A$2:B$5,2,TRUE), "") -> 48182 | G5: Fall (pre/post emerge) | H5: =IFERROR(VLOOKUP(A5,Customer_Data!$A$1:$P$114,8,TRUE),"") -> 5361 | J5: =IF($G5=("Fall (pre/post emerge)"),"Princep Liquid (100-526)", IF($G5=("Fertilize"),"Harrell's 34-0-5",IF($G5=("Spot Treat"),"Outrider (59639-223)",""))) -> Princep Liquid (100-526) | K5: =(VLOOKUP($J5,Herbicide_Data!$A$1:$L$61,9,TRUE)) -> Simazine | L5: =VLOOKUP($J5,Herbicide_Data!$A$1:$L$61,12,TRUE) -> 32 | M5: =L5*(H5/43560) -> 3.938292 | N5: =IF($G5=("Fall (pre/post emerge)"),"Triplet SF (3-Way) 228-312",IF($G5=("Spring Preemerge (Jan)"),"Triplet SF (3-Way) 228-312",IF($G5=("Spring Preemerge (Apr)"),"Triplet SF (3-Way) 228-312",""))) -> Triplet SF (3-Way) 228-312 | O5: =VLOOKUP($N5,Herbicide_Data!$A$1:$L$61,9) -> 2,4-D, dimethylamine salt; Dicamba, dimethylamine salt;Mecoprop-p (MCPP-p), dimethylamine salt | P5: =VLOOKUP($N5,Herbicide_Data!$A$1:$L$61,12) -> 24 | Q5: =P5*($H5/43560) -> 2.953719 | R5: =IF($G5=("Fall (pre/post emerge)"),"Resolute 4Fl (100-1139)",IF($G5=("Spring Preemerge (Jan)"),"Resolute 4Fl (100-1139)",IF($G5=("Spring Preemerge (Apr)"),"Certinty Turf 59639-226",""))) -> Resolute 4Fl (100-1139) | S5: =VLOOKUP($R5,Herbicide_Data!$A$1:$L$61,9) -> Prodiamine | T5: =VLOOKUP($R5,Herbicide_Data!$A$1:$L$61,12) -> 16 | U5: =T5*($H5/43560) -> 1.969146 | V5: =IF($G5 = ("Preemerge"),"MSM Turf 228-373") -> FALSE | W5: =VLOOKUP($V5,Herbicide_Data!$A$1:$L$17,9) -> #N/A | X5: =VLOOKUP($V5,Herbicide_Data!$A$1:$L$17,12) -> #N/A | Y5: =X5*($H5/43560) -> #N/A | AH5: =IF($G5 = ("Preemerge"),"Surfactant") -> FALSE | AI5: =VLOOKUP($AH5,Herbicide_Data!$A$1:$L$17,12) -> #N/A | AJ5: =AI5*($H5/43560) -> #N/A
A6: Bobby Fatheree | B6: 45592 | C6: 0.4375 | D6: =C6+0.0208333 -> 0.4583333 | E6: Matthew Stowers | F6: =IFERROR(VLOOKUP(E6,Data!A$2:B$5,2,TRUE), "") -> 48160 | G6: Fall (pre/post emerge) | H6: =IFERROR(VLOOKUP(A6,Customer_Data!$A$1:$P$114,8,TRUE),"") -> 8850 | J6: =IF($G6=("Fall (pre/post emerge)"),"Princep Liquid (100-526)", IF($G6=("Fertilize"),"Harrell's 34-0-5",IF($G6=("Spot Treat"),"Outrider (59639-223)",""))) -> Princep Liquid (100-526) | K6: =(VLOOKUP($J6,Herbicide_Data!$A$1:$L$61,9,TRUE)) -> Simazine | L6: =VLOOKUP($J6,Herbicide_Data!$A$1:$L$61,12,TRUE) -> 32 | M6: =L6*(H6/43560) -> 6.5013774 | N6: =IF($G6=("Fall (pre/post emerge)"),"Triplet SF (3-Way) 228-312",IF($G6=("Spring Preemerge (Jan)"),"Triplet SF (3-Way) 228-312",IF($G6=("Spring Preemerge (Apr)"),"Triplet SF (3-Way) 228-312",""))) -> Triplet SF (3-Way) 228-312 | O6: =VLOOKUP($N6,Herbicide_Data!$A$1:$L$61,9) -> 2,4-D, dimethylamine salt; Dicamba, dimethylamine salt;Mecoprop-p (MCPP-p), dimethylamine salt | P6: =VLOOKUP($N6,Herbicide_Data!$A$1:$L$61,12) -> 24 | Q6: =P6*($H6/43560) -> 4.8760331 | R6: =IF($G6=("Fall (pre/post emerge)"),"Resolute 4Fl (100-1139)",IF($G6=("Spring Preemerge (Jan)"),"Resolute 4Fl (100-1139)",IF($G6=("Spring Preemerge (Apr)"),"Certinty Turf 59639-226",""))) -> Resolute 4Fl (100-1139) | S6: =VLOOKUP($R6,Herbicide_Data!$A$1:$L$61,9) -> Prodiamine | T6: =VLOOKUP($R6,Herbicide_Data!$A$1:$L$61,12) -> 16 | U6: =T6*($H6/43560) -> 3.2506887 | V6: =IF($G6 = ("Preemerge"),"MSM Turf 228-373") -> FALSE | W6: =VLOOKUP($V6,Herbicide_Data!$A$1:$L$17,9) -> #N/A | X6: =VLOOKUP($V6,Herbicide_Data!$A$1:$L$17,12) -> #N/A | Y6: =X6*($H6/43560) -> #N/A | AH6: =IF($G6 = ("Preemerge"),"Surfactant") -> FALSE | AI6: =VLOOKUP($AH6,Herbicide_Data!$A$1:$L$17,12) -> #N/A | AJ6: =AI6*($H6/43560) -> #N/A
A7: Asa Barnes | B7: 45592 | C7: 0.45833333 | D7: =C7+0.0208333 -> 0.47916663 | E7: Matthew Stowers | F7: =IFERROR(VLOOKUP(E7,Data!A$2:B$5,2,TRUE), "") -> 48160 | G7: Fall (pre/post emerge) | H7: 6575 | J7: =IF($G7=("Fall (pre/post emerge)"),"Princep Liquid (100-526)", IF($G7=("Fertilize"),"Harrell's 34-0-5",IF($G7=("Spot Treat"),"Outrider (59639-223)",""))) -> Princep Liquid (100-526) | K7: =(VLOOKUP($J7,Herbicide_Data!$A$1:$L$61,9,TRUE)) -> Simazine | L7: =VLOOKUP($J7,Herbicide_Data!$A$1:$L$61,12,TRUE) -> 32 | M7: =L7*(H7/43560) -> 4.8301194 | N7: =IF($G7=("Fall (pre/post emerge)"),"Triplet SF (3-Way) 228-312",IF($G7=("Spring Preemerge (Jan)"),"Triplet SF (3-Way) 228-312",IF($G7=("Spring Preemerge (Apr)"),"Triplet SF (3-Way) 228-312",""))) -> Triplet SF (3-Way) 228-312 | O7: =VLOOKUP($N7,Herbicide_Data!$A$1:$L$61,9) -> 2,4-D, dimethylamine salt; Dicamba, dimethylamine salt;Mecoprop-p (MCPP-p), dimethylamine salt | P7: =VLOOKUP($N7,Herbicide_Data!$A$1:$L$61,12) -> 24 | Q7: =P7*($H7/43560) -> 3.6225895 | R7: =IF($G7=("Fall (pre/post emerge)"),"Resolute 4Fl (100-1139)",IF($G7=("Spring Preemerge (Jan)"),"Resolute 4Fl (100-1139)",IF($G7=("Spring Preemerge (Apr)"),"Certinty Turf 59639-226",""))) -> Resolute 4Fl (100-1139) | S7: =VLOOKUP($R7,Herbicide_Data!$A$1:$L$61,9) -> Prodiamine | T7: =VLOOKUP($R7,Herbicide_Data!$A$1:$L$61,12) -> 16 | U7: =T7*($H7/43560) -> 2.4150597 | V7: =IF($G7 = ("Preemerge"),"MSM Turf 228-373") -> FALSE | W7: =VLOOKUP($V7,Herbicide_Data!$A$1:$L$17,9) -> #N/A | X7: =VLOOKUP($V7,Herbicide_Data!$A$1:$L$17,12) -> #N/A | Y7: =X7*($H7/43560) -> #N/A | AH7: =IF($G7 = ("Preemerge"),"Surfactant") -> FALSE | AI7: =VLOOKUP($AH7,Herbicide_Data!$A$1:$L$17,12) -> #N/A | AJ7: =AI7*($H7/43560) -> #N/A
A8: David Fatheree | B8: 45592 | C8: 0.47916667 | D8: =C8+0.0208333 -> 0.49999997 | E8: Matthew Stowers | F8: =IFERROR(VLOOKUP(E8,Data!A$2:B$5,2,TRUE), "") -> 48160 | G8: Fall (pre/post emerge) | H8: =IFERROR(VLOOKUP(A8,Customer_Data!$A$1:$P$114,8,TRUE),"") -> 8910 | J8: =IF($G8=("Fall (pre/post emerge)"),"Princep Liquid (100-526)", IF($G8=("Fertilize"),"Harrell's 34-0-5",IF($G8=("Spot Treat"),"Outrider (59639-223)",""))) -> Princep Liquid (100-526) | K8: =(VLOOKUP($J8,Herbicide_Data!$A$1:$L$61,9,TRUE)) -> Simazine | L8: =VLOOKUP($J8,Herbicide_Data!$A$1:$L$61,12,TRUE) -> 32 | M8: =L8*(H8/43560) -> 6.5454545 | N8: =IF($G8=("Fall (pre/post emerge)"),"Triplet SF (3-Way) 228-312",IF($G8=("Spring Preemerge (Jan)"),"Triplet SF (3-Way) 228-312",IF($G8=("Spring Preemerge (Apr)"),"Triplet SF (3-Way) 228-312",""))) -> Triplet SF (3-Way) 228-312 | O8: =VLOOKUP($N8,Herbicide_Data!$A$1:$L$61,9) -> 2,4-D, dimethylamine salt; Dicamba, dimethylamine salt;Mecoprop-p (MCPP-p), dimethylamine salt | P8: =VLOOKUP($N8,Herbicide_Data!$A$1:$L$61,12) -> 24 | Q8: =P8*($H8/43560) -> 4.9090909 | R8: =IF($G8=("Fall (pre/post emerge)"),"Resolute 4Fl (100-1139)",IF($G8=("Spring Preemerge (Jan)"),"Resolute 4Fl (100-1139)",IF($G8=("Spring Preemerge (Apr)"),"Certinty Turf 59639-226",""))) -> Resolute 4Fl (100-1139) | S8: =VLOOKUP($R8,Herbicide_Data!$A$1:$L$61,9) -> Prodiamine | T8: =VLOOKUP($R8,Herbicide_Data!$A$1:$L$61,12) -> 16 | U8: =T8*($H8/43560) -> 3.2727273 | V8: =IF($G8 = ("Preemerge"),"MSM Turf 228-373") -> FALSE | W8: =VLOOKUP($V8,Herbicide_Data!$A$1:$L$17,9) -> #N/A | X8: =VLOOKUP($V8,Herbicide_Data!$A$1:$L$17,12) -> #N/A | Y8: =X8*($H8/43560) -> #N/A | AH8: =IF($G8 = ("Preemerge"),"Surfactant") -> FALSE | AI8: =VLOOKUP($AH8,Herbicide_Data!$A$1:$L$17,12) -> #N/A | AJ8: =AI8*($H8/43560) -> #N/A
A9: Matt Stowers | B9: 45592 | C9: 0.58333333 | D9: =C9+0.0208333 -> 0.60416663 | E9: Matthew Stowers | F9: =IFERROR(VLOOKUP(E9,Data!A$2:B$5,2,TRUE), "") -> 48160 | G9: Fall (pre/post emerge) | H9: =IFERROR(VLOOKUP(A9,Customer_Data!$A$1:$P$114,8,TRUE),"") -> 6568 | J9: =IF($G9=("Fall (pre/post emerge)"),"Princep Liquid (100-526)", IF($G9=("Fertilize"),"Harrell's 34-0-5",IF($G9=("Spot Treat"),"Outrider (59639-223)",""))) -> Princep Liquid (100-526) | K9: =(VLOOKUP($J9,Herbicide_Data!$A$1:$L$61,9,TRUE)) -> Simazine | L9: =VLOOKUP($J9,Herbicide_Data!$A$1:$L$61,12,TRUE) -> 32 | M9: =L9*(H9/43560) -> 4.824977 | N9: =IF($G9=("Fall (pre/post emerge)"),"Triplet SF (3-Way) 228-312",IF($G9=("Spring Preemerge (Jan)"),"Triplet SF (3-Way) 228-312",IF($G9=("Spring Preemerge (Apr)"),"Triplet SF (3-Way) 228-312",""))) -> Triplet SF (3-Way) 228-312 | O9: =VLOOKUP($N9,Herbicide_Data!$A$1:$L$61,9) -> 2,4-D, dimethylamine salt; Dicamba, dimethylamine salt;Mecoprop-p (MCPP-p), dimethylamine salt | P9: =VLOOKUP($N9,Herbicide_Data!$A$1:$L$61,12) -> 24 | Q9: =P9*($H9/43560) -> 3.6187328 | R9: =IF($G9=("Fall (pre/post emerge)"),"Resolute 4Fl (100-1139)",IF($G9=("Spring Preemerge (Jan)"),"Resolute 4Fl (100-1139)",IF($G9=("Spring Preemerge (Apr)"),"Certinty Turf 59639-226",""))) -> Resolute 4Fl (100-1139) | S9: =VLOOKUP($R9,Herbicide_Data!$A$1:$L$61,9) -> Prodiamine | T9: =VLOOKUP($R9,Herbicide_Data!$A$1:$L$61,12) -> 16 | U9: =T9*($H9/43560) -> 2.4124885 | V9: =IF($G9 = ("Preemerge"),"MSM Turf 228-373") -> FALSE | W9: =VLOOKUP($V9,Herbicide_Data!$A$1:$L$17,9) -> #N/A | X9: =VLOOKUP($V9,Herbicide_Data!$A$1:$L$17,12) -> #N/A | Y9: =X9*($H9/43560) -> #N/A | AH9: =IF($G9 = ("Preemerge"),"Surfactant") -> FALSE | AI9: =VLOOKUP($AH9,Herbicide_Data!$A$1:$L$17,12) -> #N/A | AJ9: =AI9*($H9/43560) -> #N/A
A10: Luther Holmes | B10: 45604 | C10: 0.58333333 | D10: =C10+0.0208333 -> 0.60416663 | E10: Luther Stowers | F10: =IFERROR(VLOOKUP(E10,Data!A$2:B$5,2,TRUE), "") -> 48182 | G10: Fall (pre/post emerge) | H10: =IFERROR(VLOOKUP(A10,Customer_Data!$A$1:$P$114,8,TRUE),"") -> 3687 | J10: =IF($G10=("Fall (pre/post emerge)"),"Princep Liquid (100-526)", IF($G10=("Fertilize"),"Harrell's 34-0-5",IF($G10=("Spot Treat"),"Outrider (59639-223)",""))) -> Princep Liquid (100-526) | K10: =(VLOOKUP($J10,Herbicide_Data!$A$1:$L$61,9,TRUE)) -> Simazine | L10: =VLOOKUP($J10,Herbicide_Data!$A$1:$L$61,12,TRUE) -> 32 | M10: =L10*(H10/43560) -> 2.7085399 | N10: =IF($G10=("Fall (pre/post emerge)"),"Triplet SF (3-Way) 228-312",IF($G10=("Spring Preemerge (Jan)"),"Triplet SF (3-Way) 228-312",IF($G10=("Spring Preemerge (Apr)"),"Triplet SF (3-Way) 228-312",""))) -> Triplet SF (3-Way) 228-312 | O10: =VLOOKUP($N10,Herbicide_Data!$A$1:$L$61,9) -> 2,4-D, dimethylamine salt; Dicamba, dimethylamine salt;Mecoprop-p (MCPP-p), dimethylamine salt | P10: =VLOOKUP($N10,Herbicide_Data!$A$1:$L$61,12) -> 24 | Q10: =P10*($H10/43560) -> 2.031405 | R10: =IF($G10=("Fall (pre/post emerge)"),"Resolute 4Fl (100-1139)",IF($G10=("Spring Preemerge (Jan)"),"Resolute 4Fl (100-1139)",IF($G10=("Spring Preemerge (Apr)"),"Certinty Turf 59639-226",""))) -> Resolute 4Fl (100-1139) | S10: =VLOOKUP($R10,Herbicide_Data!$A$1:$L$61,9) -> Prodiamine | T10: =VLOOKUP($R10,Herbicide_Data!$A$1:$L$61,12) -> 16 | U10: =T10*($H10/43560) -> 1.35427 | V10: =IF($G10 = ("Preemerge"),"MSM Turf 228-373") -> FALSE | W10: =VLOOKUP($V10,Herbicide_Data!$A$1:$L$17,9) -> #N/A | X10: =VLOOKUP($V10,Herbicide_Data!$A$1:$L$17,12) -> #N/A | Y10: =X10*($H10/43560) -> #N/A | AH10: =IF($G10 = ("Preemerge"),"Surfactant") -> FALSE | AI10: =VLOOKUP($AH10,Herbicide_Data!$A$1:$L$17,12) -> #N/A | AJ10: =AI10*($H10/43560) -> #N/A
A11: David Fatheree | B11: 45710 | C11: 0.41666667 | D11: =C11+0.0208333 -> 0.43749997 | E11: Matthew Stowers | F11: =IFERROR(VLOOKUP(E11,Data!A$2:B$5,2,TRUE), "") -> 48160 | G11: Spring Preemerge (Jan) | H11: =IFERROR(VLOOKUP(A11,Customer_Data!$A$1:$P$114,8,TRUE),"") -> 8910 | J11: =IF($G11=("Fall (pre/post emerge)"),"Princep Liquid (100-526)", IF($G11=("Fertilize"),"Harrell's 34-0-5",IF($G11=("Spot Treat"),"Outrider (59639-223)",""))) | K11: =(VLOOKUP($J11,Herbicide_Data!$A$1:$L$61,9,TRUE)) -> #N/A | L11: =VLOOKUP($J11,Herbicide_Data!$A$1:$L$61,12,TRUE) -> #N/A | M11: =L11*(H11/43560) -> #N/A | N11: =IF($G11=("Fall (pre/post emerge)"),"Triplet SF (3-Way) 228-312",IF($G11=("Spring Preemerge (Jan)"),"Triplet SF (3-Way) 228-312",IF($G11=("Spring Preemerge (Apr)"),"Triplet SF (3-Way) 228-312",""))) -> Triplet SF (3-Way) 228-312 | O11: =VLOOKUP($N11,Herbicide_Data!$A$1:$L$61,9) -> 2,4-D, dimethylamine salt; Dicamba, dimethylamine salt;Mecoprop-p (MCPP-p), dimethylamine salt | P11: =VLOOKUP($N11,Herbicide_Data!$A$1:$P$61,13) -> 24 | Q11: =P11*($H11/43560) -> 4.9090909 | R11: =IF($G11=("Fall (pre/post emerge)"),"Resolute 4Fl (100-1139)",IF($G11=("Spring Preemerge (Jan)"),"Resolute 4Fl (100-1139)",IF($G11=("Spring Preemerge (Apr)"),"Certinty Turf 59639-226",""))) -> Resolute 4Fl (100-1139) | S11: =VLOOKUP($R11,Herbicide_Data!$A$1:$L$61,9) -> Prodiamine | T11: =VLOOKUP($R11,Herbicide_Data!$A$1:$Q$61,13) -> 16 | U11: =T11*($H11/43560) -> 3.2727273 | V11: =IF($G11 = ("Preemerge"),"MSM Turf 228-373") -> FALSE | W11: =VLOOKUP($V11,Herbicide_Data!$A$1:$L$17,9) -> #N/A | X11: =VLOOKUP($V11,Herbicide_Data!$A$1:$L$17,12) -> #N/A | Y11: =X11*($H11/43560) -> #N/A | AH11: =IF($G11 = ("Spring Preemerge (Jan)"),"Surfactant") -> Surfactant | AI11: =VLOOKUP($AH11,Herbicide_Data!$A$1:$Q$61,13) -> 12.8 | AJ11: =AI11*($H11/43560) -> 2.6181818
A12: Riley Cooper | B12: 45710 | C12: 0.4375 | D12: =C12+0.0208333 -> 0.4583333 | E12: Matthew Stowers | F12: =IFERROR(VLOOKUP(E12,Data!A$2:B$5,2,TRUE), "") -> 48160 | G12: Spring Preemerge (Jan) | H12: =IFERROR(VLOOKUP(A12,Customer_Data!$A$1:$P$114,8,TRUE),"") -> 4150 | J12: =IF($G12=("Fall (pre/post emerge)"),"Princep Liquid (100-526)", IF($G12=("Fertilize"),"Harrell's 34-0-5",IF($G12=("Spot Treat"),"Outrider (59639-223)",""))) | K12: =(VLOOKUP($J12,Herbicide_Data!$A$1:$L$61,9,TRUE)) -> #N/A | L12: =VLOOKUP($J12,Herbicide_Data!$A$1:$L$61,12,TRUE) -> #N/A | M12: =L12*(H12/43560) -> #N/A | N12: =IF($G12=("Fall (pre/post emerge)"),"Triplet SF (3-Way) 228-312",IF($G12=("Spring Preemerge (Jan)"),"Triplet SF (3-Way) 228-312",IF($G12=("Spring Preemerge (Apr)"),"Triplet SF (3-Way) 228-312",""))) -> Triplet SF (3-Way) 228-312 | O12: =VLOOKUP($N12,Herbicide_Data!$A$1:$L$61,9) -> 2,4-D, dimethylamine salt; Dicamba, dimethylamine salt;Mecoprop-p (MCPP-p), dimethylamine salt | P12: =VLOOKUP($N12,Herbicide_Data!$A$1:$P$61,13) -> 24 | Q12: =P12*($H12/43560) -> 2.2865014 | R12: =IF($G12=("Fall (pre/post emerge)"),"Resolute 4Fl (100-1139)",IF($G12=("Spring Preemerge (Jan)"),"Resolute 4Fl (100-1139)",IF($G12=("Spring Preemerge (Apr)"),"Certinty Turf 59639-226",""))) -> Resolute 4Fl (100-1139) | S12: =VLOOKUP($R12,Herbicide_Data!$A$1:$L$61,9) -> Prodiamine | T12: =VLOOKUP($R12,Herbicide_Data!$A$1:$Q$61,13) -> 16 | U12: =T12*($H12/43560) -> 1.5243343 | V12: =IF($G12 = ("Preemerge"),"MSM Turf 228-373") -> FALSE | W12: =VLOOKUP($V12,Herbicide_Data!$A$1:$L$17,9) -> #N/A | X12: =VLOOKUP($V12,Herbicide_Data!$A$1:$L$17,12) -> #N/A | Y12: =X12*($H12/43560) -> #N/A | AH12: =IF($G12 = ("Spring Preemerge (Jan)"),"Surfactant") -> Surfactant | AI12: =VLOOKUP($AH12,Herbicide_Data!$A$1:$Q$61,13) -> 12.8 | AJ12: =AI12*($H12/43560) -> 1.2194674
A13: Thomas Wilson | B13: 45710 | C13: 0.45833333 | D13: =C13+0.0208333 -> 0.47916663 | E13: Matthew Stowers | F13: =IFERROR(VLOOKUP(E13,Data!A$2:B$5,2,TRUE), "") -> 48160 | G13: Spring Preemerge (Jan) | H13: =IFERROR(VLOOKUP(A13,Customer_Data!$A$1:$P$114,8,TRUE),"") -> 3875 | J13: =IF($G13=("Fall (pre/post emerge)"),"Princep Liquid (100-526)", IF($G13=("Fertilize"),"Harrell's 34-0-5",IF($G13=("Spot Treat"),"Outrider (59639-223)",""))) | K13: =(VLOOKUP($J13,Herbicide_Data!$A$1:$L$61,9,TRUE)) -> #N/A | L13: =VLOOKUP($J13,Herbicide_Data!$A$1:$L$61,12,TRUE) -> #N/A | M13: =L13*(H13/43560) -> #N/A | N13: =IF($G13=("Fall (pre/post emerge)"),"Triplet SF (3-Way) 228-312",IF($G13=("Spring Preemerge (Jan)"),"Triplet SF (3-Way) 228-312",IF($G13=("Spring Preemerge (Apr)"),"Triplet SF (3-Way) 228-312",""))) -> Triplet SF (3-Way) 228-312 | O13: =VLOOKUP($N13,Herbicide_Data!$A$1:$L$61,9) -> 2,4-D, dimethylamine salt; Dicamba, dimethylamine salt;Mecoprop-p (MCPP-p), dimethylamine salt | P13: =VLOOKUP($N13,Herbicide_Data!$A$1:$P$61,13) -> 24 | Q13: =P13*($H13/43560) -> 2.1349862 | R13: =IF($G13=("Fall (pre/post emerge)"),"Resolute 4Fl (100-1139)",IF($G13=("Spring Preemerge (Jan)"),"Resolute 4Fl (100-1139)",IF($G13=("Spring Preemerge (Apr)"),"Certinty Turf 59639-226",""))) -> Resolute 4Fl (100-1139) | S13: =VLOOKUP($R13,Herbicide_Data!$A$1:$L$61,9) -> Prodiamine | T13: =VLOOKUP($R13,Herbicide_Data!$A$1:$Q$61,13) -> 16 | U13: =T13*($H13/43560) -> 1.4233242 | V13: =IF($G13 = ("Preemerge"),"MSM Turf 228-373") -> FALSE | W13: =VLOOKUP($V13,Herbicide_Data!$A$1:$L$17,9) -> #N/A | X13: =VLOOKUP($V13,Herbicide_Data!$A$1:$L$17,12) -> #N/A | Y13: =X13*($H13/43560) -> #N/A | AH13: =IF($G13 = ("Spring Preemerge (Jan)"),"Surfactant") -> Surfactant | AI13: =VLOOKUP($AH13,Herbicide_Data!$A$1:$Q$61,13) -> 12.8 | AJ13: =AI13*($H13/43560) -> 1.1386593
A14: Max Miller | B14: 45710 | C14: 0.5 | D14: =C14+0.0208333 -> 0.5208333 | E14: Matthew Stowers | F14: =IFERROR(VLOOKUP(E14,Data!A$2:B$5,2,TRUE), "") -> 48160 | G14: Spring Preemerge (Jan) | H14: =IFERROR(VLOOKUP(A14,Customer_Data!$A$1:$P$114,8,TRUE),"") -> 3100 | J14: =IF($G14=("Fall (pre/post emerge)"),"Princep Liquid (100-526)", IF($G14=("Fertilize"),"Harrell's 34-0-5",IF($G14=("Spot Treat"),"Outrider (59639-223)",""))) | K14: =(VLOOKUP($J14,Herbicide_Data!$A$1:$L$61,9,TRUE)) -> #N/A | L14: =VLOOKUP($J14,Herbicide_Data!$A$1:$L$61,12,TRUE) -> #N/A | M14: =L14*(H14/43560) -> #N/A | N14: =IF($G14=("Fall (pre/post emerge)"),"Triplet SF (3-Way) 228-312",IF($G14=("Spring Preemerge (Jan)"),"Triplet SF (3-Way) 228-312",IF($G14=("Spring Preemerge (Apr)"),"Triplet SF (3-Way) 228-312",""))) -> Triplet SF (3-Way) 228-312 | O14: =VLOOKUP($N14,Herbicide_Data!$A$1:$L$61,9) -> 2,4-D, dimethylamine salt; Dicamba, dimethylamine salt;Mecoprop-p (MCPP-p), dimethylamine salt | P14: =VLOOKUP($N14,Herbicide_Data!$A$1:$P$61,13) -> 24 | Q14: =P14*($H14/43560) -> 1.707989 | R14: =IF($G14=("Fall (pre/post emerge)"),"Resolute 4Fl (100-1139)",IF($G14=("Spring Preemerge (Jan)"),"Resolute 4Fl (100-1139)",IF($G14=("Spring Preemerge (Apr)"),"Certinty Turf 59639-226",""))) -> Resolute 4Fl (100-1139) | S14: =VLOOKUP($R14,Herbicide_Data!$A$1:$L$61,9) -> Prodiamine | T14: =VLOOKUP($R14,Herbicide_Data!$A$1:$Q$61,13) -> 16 | U14: =T14*($H14/43560) -> 1.1386593 | V14: =IF($G14 = ("Preemerge"),"MSM Turf 228-373") -> FALSE | W14: =VLOOKUP($V14,Herbicide_Data!$A$1:$L$17,9) -> #N/A | X14: =VLOOKUP($V14,Herbicide_Data!$A$1:$L$17,12) -> #N/A | Y14: =X14*($H14/43560) -> #N/A | AH14: =IF($G14 = ("Spring Preemerge (Jan)"),"Surfactant") -> Surfactant | AI14: =VLOOKUP($AH14,Herbicide_Data!$A$1:$Q$61,13) -> 12.8 | AJ14: =AI14*($H14/43560) -> 0.91092746
A15: Luther Holmes | B15: 45710 | C15: 0.54166667 | D15: =C15+0.0208333 -> 0.56249997 | E15: Luther Stowers | F15: =IFERROR(VLOOKUP(E15,Data!A$2:B$5,2,TRUE), "") -> 48182 | G15: Spring Preemerge (Jan) | H15: =IFERROR(VLOOKUP(A15,Customer_Data!$A$1:$P$114,8,TRUE),"") -> 3687 | J15: =IF($G15=("Fall (pre/post emerge)"),"Princep Liquid (100-526)", IF($G15=("Fertilize"),"Harrell's 34-0-5",IF($G15=("Spot Treat"),"Outrider (59639-223)",""))) | K15: =(VLOOKUP($J15,Herbicide_Data!$A$1:$L$61,9,TRUE)) -> #N/A | L15: =VLOOKUP($J15,Herbicide_Data!$A$1:$L$61,12,TRUE) -> #N/A | M15: =L15*(H15/43560) -> #N/A | N15: =IF($G15=("Fall (pre/post emerge)"),"Triplet SF (3-Way) 228-312",IF($G15=("Spring Preemerge (Jan)"),"Triplet SF (3-Way) 228-312",IF($G15=("Spring Preemerge (Apr)"),"Triplet SF (3-Way) 228-312",""))) -> Triplet SF (3-Way) 228-312 | O15: =VLOOKUP($N15,Herbicide_Data!$A$1:$L$61,9) -> 2,4-D, dimethylamine salt; Dicamba, dimethylamine salt;Mecoprop-p (MCPP-p), dimethylamine salt | P15: =VLOOKUP($N15,Herbicide_Data!$A$1:$P$61,13) -> 24 | Q15: =P15*($H15/43560) -> 2.031405 | R15: =IF($G15=("Fall (pre/post emerge)"),"Resolute 4Fl (100-1139)",IF($G15=("Spring Preemerge (Jan)"),"Resolute 4Fl (100-1139)",IF($G15=("Spring Preemerge (Apr)"),"Certinty Turf 59639-226",""))) -> Resolute 4Fl (100-1139) | S15: =VLOOKUP($R15,Herbicide_Data!$A$1:$L$61,9) -> Prodiamine | T15: =VLOOKUP($R15,Herbicide_Data!$A$1:$Q$61,13) -> 16 | U15: =T15*($H15/43560) -> 1.35427 | V15: =IF($G15 = ("Preemerge"),"MSM Turf 228-373") -> FALSE | W15: =VLOOKUP($V15,Herbicide_Data!$A$1:$L$17,9) -> #N/A | X15: =VLOOKUP($V15,Herbicide_Data!$A$1:$L$17,12) -> #N/A | Y15: =X15*($H15/43560) -> #N/A | AH15: =IF($G15 = ("Spring Preemerge (Jan)"),"Surfactant") -> Surfactant | AI15: =VLOOKUP($AH15,Herbicide_Data!$A$1:$Q$61,13) -> 12.8 | AJ15: =AI15*($H15/43560) -> 1.083416
A16: Bo Whatley | B16: 45710 | C16: 0.5625 | D16: =C16+0.0208333 -> 0.5833333 | E16: Matthew Stowers | F16: =IFERROR(VLOOKUP(E16,Data!A$2:B$5,2,TRUE), "") -> 48160 | G16: Spring Preemerge (Jan) | H16: =IFERROR(VLOOKUP(A16,Customer_Data!$A$1:$P$114,8,TRUE),"") -> 2750 | J16: =IF($G16=("Fall (pre/post emerge)"),"Princep Liquid (100-526)", IF($G16=("Fertilize"),"Harrell's 34-0-5",IF($G16=("Spot Treat"),"Outrider (59639-223)",""))) | K16: =(VLOOKUP($J16,Herbicide_Data!$A$1:$L$61,9,TRUE)) -> #N/A | L16: =VLOOKUP($J16,Herbicide_Data!$A$1:$L$61,12,TRUE) -> #N/A | M16: =L16*(H16/43560) -> #N/A | N16: =IF($G16=("Fall (pre/post emerge)"),"Triplet SF (3-Way) 228-312",IF($G16=("Spring Preemerge (Jan)"),"Triplet SF (3-Way) 228-312",IF($G16=("Spring Preemerge (Apr)"),"Triplet SF (3-Way) 228-312",""))) -> Triplet SF (3-Way) 228-312 | O16: =VLOOKUP($N16,Herbicide_Data!$A$1:$L$61,9) -> 2,4-D, dimethylamine salt; Dicamba, dimethylamine salt;Mecoprop-p (MCPP-p), dimethylamine salt | P16: =VLOOKUP($N16,Herbicide_Data!$A$1:$P$61,13) -> 24 | Q16: =P16*($H16/43560) -> 1.5151515 | R16: =IF($G16=("Fall (pre/post emerge)"),"Resolute 4Fl (100-1139)",IF($G16=("Spring Preemerge (Jan)"),"Resolute 4Fl (100-1139)",IF($G16=("Spring Preemerge (Apr)"),"Certinty Turf 59639-226",""))) -> Resolute 4Fl (100-1139) | S16: =VLOOKUP($R16,Herbicide_Data!$A$1:$L$61,9) -> Prodiamine | T16: =VLOOKUP($R16,Herbicide_Data!$A$1:$Q$61,13) -> 16 | U16: =T16*($H16/43560) -> 1.010101 | V16: =IF($G16 = ("Preemerge"),"MSM Turf 228-373") -> FALSE | W16: =VLOOKUP($V16,Herbicide_Data!$A$1:$L$17,9) -> #N/A | X16: =VLOOKUP($V16,Herbicide_Data!$A$1:$L$17,12) -> #N/A | Y16: =X16*($H16/43560) -> #N/A | AH16: =IF($G16 = ("Spring Preemerge (Jan)"),"Surfactant") -> Surfactant | AI16: =VLOOKUP($AH16,Herbicide_Data!$A$1:$Q$61,13) -> 12.8 | AJ16: =AI16*($H16/43560) -> 0.80808081
A17: Matt Stowers | B17: 45710 | C17: 0.5625 | D17: =C17+0.0208333 -> 0.5833333 | E17: Matthew Stowers | F17: =IFERROR(VLOOKUP(E17,Data!A$2:B$5,2,TRUE), "") -> 48160 | G17: Spring Preemerge (Jan) | H17: =IFERROR(VLOOKUP(A17,Customer_Data!$A$1:$P$114,8,TRUE),"") -> 6568 | J17: =IF($G17=("Fall (pre/post emerge)"),"Princep Liquid (100-526)", IF($G17=("Fertilize"),"Harrell's 34-0-5",IF($G17=("Spot Treat"),"Outrider (59639-223)",""))) | K17: =(VLOOKUP($J17,Herbicide_Data!$A$1:$L$61,9,TRUE)) -> #N/A | L17: =VLOOKUP($J17,Herbicide_Data!$A$1:$L$61,12,TRUE) -> #N/A | M17: =L17*(H17/43560) -> #N/A | N17: =IF($G17=("Fall (pre/post emerge)"),"Triplet SF (3-Way) 228-312",IF($G17=("Spring Preemerge (Jan)"),"Triplet SF (3-Way) 228-312",IF($G17=("Spring Preemerge (Apr)"),"Triplet SF (3-Way) 228-312",""))) -> Triplet SF (3-Way) 228-312 | O17: =VLOOKUP($N17,Herbicide_Data!$A$1:$L$61,9) -> 2,4-D, dimethylamine salt; Dicamba, dimethylamine salt;Mecoprop-p (MCPP-p), dimethylamine salt | P17: =VLOOKUP($N17,Herbicide_Data!$A$1:$P$61,13) -> 24 | Q17: =P17*($H17/43560) -> 3.6187328 | R17: =IF($G17=("Fall (pre/post emerge)"),"Resolute 4Fl (100-1139)",IF($G17=("Spring Preemerge (Jan)"),"Resolute 4Fl (100-1139)",IF($G17=("Spring Preemerge (Apr)"),"Certinty Turf 59639-226",""))) -> Resolute 4Fl (100-1139) | S17: =VLOOKUP($R17,Herbicide_Data!$A$1:$L$61,9) -> Prodiamine | T17: =VLOOKUP($R17,Herbicide_Data!$A$1:$Q$61,13) -> 16 | U17: =T17*($H17/43560) -> 2.4124885 | V17: =IF($G17 = ("Preemerge"),"MSM Turf 228-373") -> FALSE | W17: =VLOOKUP($V17,Herbicide_Data!$A$1:$L$17,9) -> #N/A | X17: =VLOOKUP($V17,Herbicide_Data!$A$1:$L$17,12) -> #N/A | Y17: =X17*($H17/43560) -> #N/A | AH17: =IF($G17 = ("Spring Preemerge (Jan)"),"Surfactant") -> Surfactant | AI17: =VLOOKUP($AH17,Herbicide_Data!$A$1:$Q$61,13) -> 12.8 | AJ17: =AI17*($H17/43560) -> 1.9299908
A18: Matt Runner | B18: 45710 | C18: 0.58333333 | D18: =C18+0.0208333 -> 0.60416663 | E18: Matthew Stowers | F18: =IFERROR(VLOOKUP(E18,Data!A$2:B$5,2,TRUE), "") -> 48160 | G18: Spring Preemerge (Jan) | H18: =IFERROR(VLOOKUP(A18,Customer_Data!$A$1:$P$114,8,TRUE),"") -> 2000 | J18: =IF($G18=("Fall (pre/post emerge)"),"Princep Liquid (100-526)", IF($G18=("Fertilize"),"Harrell's 34-0-5",IF($G18=("Spot Treat"),"Outrider (59639-223)",""))) | K18: =(VLOOKUP($J18,Herbicide_Data!$A$1:$L$61,9,TRUE)) -> #N/A | L18: =VLOOKUP($J18,Herbicide_Data!$A$1:$L$61,12,TRUE) -> #N/A | M18: =L18*(H18/43560) -> #N/A | N18: =IF($G18=("Fall (pre/post emerge)"),"Triplet SF (3-Way) 228-312",IF($G18=("Spring Preemerge (Jan)"),"Triplet SF (3-Way) 228-312",IF($G18=("Spring Preemerge (Apr)"),"Triplet SF (3-Way) 228-312",""))) -> Triplet SF (3-Way) 228-312 | O18: =VLOOKUP($N18,Herbicide_Data!$A$1:$L$61,9) -> 2,4-D, dimethylamine salt; Dicamba, dimethylamine salt;Mecoprop-p (MCPP-p), dimethylamine salt | P18: =VLOOKUP($N18,Herbicide_Data!$A$1:$P$61,13) -> 24 | Q18: =P18*($H18/43560) -> 1.1019284 | R18: =IF($G18=("Fall (pre/post emerge)"),"Resolute 4Fl (100-1139)",IF($G18=("Spring Preemerge (Jan)"),"Resolute 4Fl (100-1139)",IF($G18=("Spring Preemerge (Apr)"),"Certinty Turf 59639-226",""))) -> Resolute 4Fl (100-1139) | S18: =VLOOKUP($R18,Herbicide_Data!$A$1:$L$61,9) -> Prodiamine | T18: =VLOOKUP($R18,Herbicide_Data!$A$1:$Q$61,13) -> 16 | U18: =T18*($H18/43560) -> 0.73461892 | V18: =IF($G18 = ("Preemerge"),"MSM Turf 228-373") -> FALSE | W18: =VLOOKUP($V18,Herbicide_Data!$A$1:$L$17,9) -> #N/A | X18: =VLOOKUP($V18,Herbicide_Data!$A$1:$L$17,12) -> #N/A | Y18: =X18*($H18/43560) -> #N/A | AH18: =IF($G18 = ("Spring Preemerge (Jan)"),"Surfactant") -> Surfactant | AI18: =VLOOKUP($AH18,Herbicide_Data!$A$1:$Q$61,13) -> 12.8 | AJ18: =AI18*($H18/43560) -> 0.58769513
A19: Asa Barnes | B19: 45710 | C19: =IF(ISBLANK($A19),"",NOW()-TODAY()) -> 0.63285475 | D19: =C19+0.0208333 -> 0.65368805 | E19: Matthew Stowers | F19: =IFERROR(VLOOKUP(E19,Data!A$2:B$5,2,TRUE), "") -> 48160 | G19: Spring Preemerge (Jan) | H19: 6575 | J19: =IF($G19=("Fall (pre/post emerge)"),"Princep Liquid (100-526)", IF($G19=("Fertilize"),"Harrell's 34-0-5",IF($G19=("Spot Treat"),"Outrider (59639-223)",""))) | K19: =(VLOOKUP($J19,Herbicide_Data!$A$1:$L$61,9,TRUE)) -> #N/A | L19: =VLOOKUP($J19,Herbicide_Data!$A$1:$L$61,12,TRUE) -> #N/A | M19: =L19*(H19/43560) -> #N/A | N19: =IF($G19=("Fall (pre/post emerge)"),"Triplet SF (3-Way) 228-312",IF($G19=("Spring Preemerge (Jan)"),"Triplet SF (3-Way) 228-312",IF($G19=("Spring Preemerge (Apr)"),"Triplet SF (3-Way) 228-312",""))) -> Triplet SF (3-Way) 228-312 | O19: =VLOOKUP($N19,Herbicide_Data!$A$1:$L$61,9) -> 2,4-D, dimethylamine salt; Dicamba, dimethylamine salt;Mecoprop-p (MCPP-p), dimethylamine salt | P19: =VLOOKUP($N19,Herbicide_Data!$A$1:$P$61,13) -> 24 | Q19: =P19*($H19/43560) -> 3.6225895 | R19: =IF($G19=("Fall (pre/post emerge)"),"Resolute 4Fl (100-1139)",IF($G19=("Spring Preemerge (Jan)"),"Resolute 4Fl (100-1139)",IF($G19=("Spring Preemerge (Apr)"),"Certinty Turf 59639-226",""))) -> Resolute 4Fl (100-1139) | S19: =VLOOKUP($R19,Herbicide_Data!$A$1:$L$61,9) -> Prodiamine | T19: =VLOOKUP($R19,Herbicide_Data!$A$1:$Q$61,13) -> 16 | U19: =T19*($H19/43560) -> 2.4150597 | V19: =IF($G19 = ("Preemerge"),"MSM Turf 228-373") -> FALSE | W19: =VLOOKUP($V19,Herbicide_Data!$A$1:$L$17,9) -> #N/A | X19: =VLOOKUP($V19,Herbicide_Data!$A$1:$L$17,12) -> #N/A | Y19: =X19*($H19/43560) -> #N/A | AH19: =IF($G19 = ("Spring Preemerge (Jan)"),"Surfactant") -> Surfactant | AI19: =VLOOKUP($AH19,Herbicide_Data!$A$1:$Q$61,13) -> 12.8 | AJ19: =AI19*($H19/43560) -> 1.9320478
A20: Brandon Bergold | B20: 45710 | C20: 0.60416667 | D20: =C20+0.0208333 -> 0.62499997 | E20: Matthew Stowers | F20: =IFERROR(VLOOKUP(E20,Data!A$2:B$5,2,TRUE), "") -> 48160 | G20: Spring Preemerge (Jan) | H20: =IFERROR(VLOOKUP(A20,Customer_Data!$A$1:$P$114,8,TRUE),"") -> 5670 | J20: =IF($G20=("Fall (pre/post emerge)"),"Princep Liquid (100-526)", IF($G20=("Fertilize"),"Harrell's 34-0-5",IF($G20=("Spot Treat"),"Outrider (59639-223)",""))) | K20: =(VLOOKUP($J20,Herbicide_Data!$A$1:$L$61,9,TRUE)) -> #N/A | L20: =VLOOKUP($J20,Herbicide_Data!$A$1:$L$61,12,TRUE) -> #N/A | M20: =L20*(H20/43560) -> #N/A | N20: =IF($G20=("Fall (pre/post emerge)"),"Triplet SF (3-Way) 228-312",IF($G20=("Spring Preemerge (Jan)"),"Triplet SF (3-Way) 228-312",IF($G20=("Spring Preemerge (Apr)"),"Triplet SF (3-Way) 228-312",""))) -> Triplet SF (3-Way) 228-312 | O20: =VLOOKUP($N20,Herbicide_Data!$A$1:$L$61,9) -> 2,4-D, dimethylamine salt; Dicamba, dimethylamine salt;Mecoprop-p (MCPP-p), dimethylamine salt | P20: =VLOOKUP($N20,Herbicide_Data!$A$1:$P$61,13) -> 24 | Q20: =P20*($H20/43560) -> 3.1239669 | R20: =IF($G20=("Fall (pre/post emerge)"),"Resolute 4Fl (100-1139)",IF($G20=("Spring Preemerge (Jan)"),"Resolute 4Fl (100-1139)",IF($G20=("Spring Preemerge (Apr)"),"Certinty Turf 59639-226",""))) -> Resolute 4Fl (100-1139) | S20: =VLOOKUP($R20,Herbicide_Data!$A$1:$L$61,9) -> Prodiamine | T20: =VLOOKUP($R20,Herbicide_Data!$A$1:$Q$61,13) -> 16 | U20: =T20*($H20/43560) -> 2.0826446 | V20: =IF($G20 = ("Preemerge"),"MSM Turf 228-373") -> FALSE | W20: =VLOOKUP($V20,Herbicide_Data!$A$1:$L$17,9) -> #N/A | X20: =VLOOKUP($V20,Herbicide_Data!$A$1:$L$17,12) -> #N/A | Y20: =X20*($H20/43560) -> #N/A | AH20: =IF($G20 = ("Spring Preemerge (Jan)"),"Surfactant") -> Surfactant | AI20: =VLOOKUP($AH20,Herbicide_Data!$A$1:$Q$61,13) -> 12.8 | AJ20: =AI20*($H20/43560) -> 1.6661157
A21: Dot Stuart | B21: 45710 | C21: 0.625 | D21: =C21+0.0208333 -> 0.6458333 | E21: Matthew Stowers | F21: =IFERROR(VLOOKUP(E21,Data!A$2:B$5,2,TRUE), "") -> 48160 | G21: Spring Preemerge (Jan) | H21: =IFERROR(VLOOKUP(A21,Customer_Data!$A$1:$P$114,8,TRUE),"") -> 1800 | J21: =IF($G21=("Fall (pre/post emerge)"),"Princep Liquid (100-526)", IF($G21=("Fertilize"),"Harrell's 34-0-5",IF($G21=("Spot Treat"),"Outrider (59639-223)",""))) | K21: =(VLOOKUP($J21,Herbicide_Data!$A$1:$L$61,9,TRUE)) -> #N/A | L21: =VLOOKUP($J21,Herbicide_Data!$A$1:$L$61,12,TRUE) -> #N/A | M21: =L21*(H21/43560) -> #N/A | N21: =IF($G21=("Fall (pre/post emerge)"),"Triplet SF (3-Way) 228-312",IF($G21=("Spring Preemerge (Jan)"),"Triplet SF (3-Way) 228-312",IF($G21=("Spring Preemerge (Apr)"),"Triplet SF (3-Way) 228-312",""))) -> Triplet SF (3-Way) 228-312 | O21: =VLOOKUP($N21,Herbicide_Data!$A$1:$L$61,9) -> 2,4-D, dimethylamine salt; Dicamba, dimethylamine salt;Mecoprop-p (MCPP-p), dimethylamine salt | P21: =VLOOKUP($N21,Herbicide_Data!$A$1:$P$61,13) -> 24 | Q21: =P21*($H21/43560) -> 0.99173554 | R21: =IF($G21=("Fall (pre/post emerge)"),"Resolute 4Fl (100-1139)",IF($G21=("Spring Preemerge (Jan)"),"Resolute 4Fl (100-1139)",IF($G21=("Spring Preemerge (Apr)"),"Certinty Turf 59639-226",""))) -> Resolute 4Fl (100-1139) | S21: =VLOOKUP($R21,Herbicide_Data!$A$1:$L$61,9) -> Prodiamine | T21: =VLOOKUP($R21,Herbicide_Data!$A$1:$Q$61,13) -> 16 | U21: =T21*($H21/43560) -> 0.66115702 | V21: =IF($G21 = ("Preemerge"),"MSM Turf 228-373") -> FALSE | W21: =VLOOKUP($V21,Herbicide_Data!$A$1:$L$17,9) -> #N/A | X21: =VLOOKUP($V21,Herbicide_Data!$A$1:$L$17,12) -> #N/A | Y21: =X21*($H21/43560) -> #N/A | AH21: =IF($G21 = ("Spring Preemerge (Jan)"),"Surfactant") -> Surfactant | AI21: =VLOOKUP($AH21,Herbicide_Data!$A$1:$Q$61,13) -> 12.8 | AJ21: =AI21*($H21/43560) -> 0.52892562
A22: Elliot Smith | B22: 45710 | C22: 0.625 | D22: =C22+0.0208333 -> 0.6458333 | E22: Matthew Stowers | F22: =IFERROR(VLOOKUP(E22,Data!A$2:B$5,2,TRUE), "") -> 48160 | G22: Spring Preemerge (Jan) | H22: =IFERROR(VLOOKUP(A22,Customer_Data!$A$1:$P$114,8,TRUE),"") -> 13500 | J22: =IF($G22=("Fall (pre/post emerge)"),"Princep Liquid (100-526)", IF($G22=("Fertilize"),"Harrell's 34-0-5",IF($G22=("Spot Treat"),"Outrider (59639-223)",""))) | K22: =(VLOOKUP($J22,Herbicide_Data!$A$1:$L$61,9,TRUE)) -> #N/A | L22: =VLOOKUP($J22,Herbicide_Data!$A$1:$L$61,12,TRUE) -> #N/A | M22: =L22*(H22/43560) -> #N/A | N22: =IF($G22=("Fall (pre/post emerge)"),"Triplet SF (3-Way) 228-312",IF($G22=("Spring Preemerge (Jan)"),"Triplet SF (3-Way) 228-312",IF($G22=("Spring Preemerge (Apr)"),"Triplet SF (3-Way) 228-312",""))) -> Triplet SF (3-Way) 228-312 | O22: =VLOOKUP($N22,Herbicide_Data!$A$1:$L$61,9) -> 2,4-D, dimethylamine salt; Dicamba, dimethylamine salt;Mecoprop-p (MCPP-p), dimethylamine salt | P22: =VLOOKUP($N22,Herbicide_Data!$A$1:$P$61,13) -> 24 | Q22: =P22*($H22/43560) -> 7.4380165 | R22: =IF($G22=("Fall (pre/post emerge)"),"Resolute 4Fl (100-1139)",IF($G22=("Spring Preemerge (Jan)"),"Resolute 4Fl (100-1139)",IF($G22=("Spring Preemerge (Apr)"),"Certinty Turf 59639-226",""))) -> Resolute 4Fl (100-1139) | S22: =VLOOKUP($R22,Herbicide_Data!$A$1:$L$61,9) -> Prodiamine | T22: =VLOOKUP($R22,Herbicide_Data!$A$1:$Q$61,13) -> 16 | U22: =T22*($H22/43560) -> 4.9586777 | V22: =IF($G22 = ("Preemerge"),"MSM Turf 228-373") -> FALSE | W22: =VLOOKUP($V22,Herbicide_Data!$A$1:$L$17,9) -> #N/A | X22: =VLOOKUP($V22,Herbicide_Data!$A$1:$L$17,12) -> #N/A | Y22: =X22*($H22/43560) -> #N/A | AH22: =IF($G22 = ("Spring Preemerge (Jan)"),"Surfactant") -> Surfactant | AI22: =VLOOKUP($AH22,Herbicide_Data!$A$1:$Q$61,13) -> 12.8 | AJ22: =AI22*($H22/43560) -> 3.9669421
A23: Luther Stowers | B23: 45710 | C23: 0.64583333 | D23: =C23+0.0208333 -> 0.66666663 | E23: Luther Stowers | F23: =IFERROR(VLOOKUP(E23,Data!A$2:B$5,2,TRUE), "") -> 48182 | G23: Spring Preemerge (Jan) | H23: =IFERROR(VLOOKUP(A23,Customer_Data!$A$1:$P$114,8,TRUE),"") -> 5361 | J23: =IF($G23=("Fall (pre/post emerge)"),"Princep Liquid (100-526)", IF($G23=("Fertilize"),"Harrell's 34-0-5",IF($G23=("Spot Treat"),"Outrider (59639-223)",""))) | K23: =(VLOOKUP($J23,Herbicide_Data!$A$1:$L$61,9,TRUE)) -> #N/A | L23: =VLOOKUP($J23,Herbicide_Data!$A$1:$L$61,12,TRUE) -> #N/A | M23: =L23*(H23/43560) -> #N/A | N23: =IF($G23=("Fall (pre/post emerge)"),"Triplet SF (3-Way) 228-312",IF($G23=("Spring Preemerge (Jan)"),"Triplet SF (3-Way) 228-312",IF($G23=("Spring Preemerge (Apr)"),"Triplet SF (3-Way) 228-312",""))) -> Triplet SF (3-Way) 228-312 | O23: =VLOOKUP($N23,Herbicide_Data!$A$1:$L$61,9) -> 2,4-D, dimethylamine salt; Dicamba, dimethylamine salt;Mecoprop-p (MCPP-p), dimethylamine salt | P23: =VLOOKUP($N23,Herbicide_Data!$A$1:$P$61,13) -> 24 | Q23: =P23*($H23/43560) -> 2.953719 | R23: =IF($G23=("Fall (pre/post emerge)"),"Resolute 4Fl (100-1139)",IF($G23=("Spring Preemerge (Jan)"),"Resolute 4Fl (100-1139)",IF($G23=("Spring Preemerge (Apr)"),"Certinty Turf 59639-226",""))) -> Resolute 4Fl (100-1139) | S23: =VLOOKUP($R23,Herbicide_Data!$A$1:$L$61,9) -> Prodiamine | T23: =VLOOKUP($R23,Herbicide_Data!$A$1:$Q$61,13) -> 16 | U23: =T23*($H23/43560) -> 1.969146 | V23: =IF($G23 = ("Preemerge"),"MSM Turf 228-373") -> FALSE | W23: =VLOOKUP($V23,Herbicide_Data!$A$1:$L$17,9) -> #N/A | X23: =VLOOKUP($V23,Herbicide_Data!$A$1:$L$17,12) -> #N/A | Y23: =X23*($H23/43560) -> #N/A | AH23: =IF($G23 = ("Spring Preemerge (Jan)"),"Surfactant") -> Surfactant | AI23: =VLOOKUP($AH23,Herbicide_Data!$A$1:$Q$61,13) -> 12.8 | AJ23: =AI23*($H23/43560) -> 1.5753168
A24: Max Brian | B24: 45726 | C24: 0.72916667 | D24: =C24+0.0208333 -> 0.74999997 | E24: Matthew Stowers | F24: =IFERROR(VLOOKUP(E24,Data!A$2:B$5,2,TRUE), "") -> 48160 | G24: Spring Preemerge (Jan) | H24: =IFERROR(VLOOKUP(A24,Customer_Data!$A$1:$P$114,8,TRUE),"") -> 4670 | J24: =IF($G24=("Fall (pre/post emerge)"),"Princep Liquid (100-526)", IF($G24=("Fertilize"),"Harrell's 34-0-5",IF($G24=("Spot Treat"),"Outrider (59639-223)",""))) | K24: =(VLOOKUP($J24,Herbicide_Data!$A$1:$L$61,9,TRUE)) -> #N/A | L24: =VLOOKUP($J24,Herbicide_Data!$A$1:$L$61,12,TRUE) -> #N/A | M24: =L24*(H24/43560) -> #N/A | N24: =IF($G24=("Fall (pre/post emerge)"),"Triplet SF (3-Way) 228-312",IF($G24=("Spring Preemerge (Jan)"),"Triplet SF (3-Way) 228-312",IF($G24=("Spring Preemerge (Apr)"),"Triplet SF (3-Way) 228-312",""))) -> Triplet SF (3-Way) 228-312 | O24: =VLOOKUP($N24,Herbicide_Data!$A$1:$L$61,9) -> 2,4-D, dimethylamine salt; Dicamba, dimethylamine salt;Mecoprop-p (MCPP-p), dimethylamine salt | P24: =VLOOKUP($N24,Herbicide_Data!$A$1:$P$61,13) -> 24 | Q24: =P24*($H24/43560) -> 2.5730028 | R24: =IF($G24=("Fall (pre/post emerge)"),"Resolute 4Fl (100-1139)",IF($G24=("Spring Preemerge (Jan)"),"Resolute 4Fl (100-1139)",IF($G24=("Spring Preemerge (Apr)"),"Certinty Turf 59639-226",""))) -> Resolute 4Fl (100-1139) | S24: =VLOOKUP($R24,Herbicide_Data!$A$1:$L$61,9) -> Prodiamine | T24: =VLOOKUP($R24,Herbicide_Data!$A$1:$Q$61,13) -> 16 | U24: =T24*($H24/43560) -> 1.7153352 | V24: =IF($G24 = ("Preemerge"),"MSM Turf 228-373") -> FALSE | W24: =VLOOKUP($V24,Herbicide_Data!$A$1:$L$17,9) -> #N/A | X24: =VLOOKUP($V24,Herbicide_Data!$A$1:$L$17,12) -> #N/A | Y24: =X24*($H24/43560) -> #N/A | AH24: =IF($G24 = ("Spring Preemerge (Jan)"),"Surfactant") -> Surfactant | AI24: =VLOOKUP($AH24,Herbicide_Data!$A$1:$Q$61,13) -> 12.8 | AJ24: =AI24*($H24/43560) -> 1.3722681
A25: Troy Stokes | B25: 45726 | C25: 0.75 | D25: =C25+0.0208333 -> 0.7708333 | E25: Matthew Stowers | F25: =IFERROR(VLOOKUP(E25,Data!A$2:B$5,2,TRUE), "") -> 48160 | G25: Spring Preemerge (Jan) | H25: =IFERROR(VLOOKUP(A25,Customer_Data!$A$1:$P$114,8,TRUE),"") -> 9000 | J25: =IF($G25=("Fall (pre/post emerge)"),"Princep Liquid (100-526)", IF($G25=("Fertilize"),"Harrell's 34-0-5",IF($G25=("Spot Treat"),"Outrider (59639-223)",""))) | K25: =(VLOOKUP($J25,Herbicide_Data!$A$1:$L$61,9,TRUE)) -> #N/A | L25: =VLOOKUP($J25,Herbicide_Data!$A$1:$L$61,12,TRUE) -> #N/A | M25: =L25*(H25/43560) -> #N/A | N25: =IF($G25=("Fall (pre/post emerge)"),"Triplet SF (3-Way) 228-312",IF($G25=("Spring Preemerge (Jan)"),"Triplet SF (3-Way) 228-312",IF($G25=("Spring Preemerge (Apr)"),"Triplet SF (3-Way) 228-312",""))) -> Triplet SF (3-Way) 228-312 | O25: =VLOOKUP($N25,Herbicide_Data!$A$1:$L$61,9) -> 2,4-D, dimethylamine salt; Dicamba, dimethylamine salt;Mecoprop-p (MCPP-p), dimethylamine salt | P25: =VLOOKUP($N25,Herbicide_Data!$A$1:$P$61,13) -> 24 | Q25: =P25*($H25/43560) -> 4.9586777 | R25: =IF($G25=("Fall (pre/post emerge)"),"Resolute 4Fl (100-1139)",IF($G25=("Spring Preemerge (Jan)"),"Resolute 4Fl (100-1139)",IF($G25=("Spring Preemerge (Apr)"),"Certinty Turf 59639-226",""))) -> Resolute 4Fl (100-1139) | S25: =VLOOKUP($R25,Herbicide_Data!$A$1:$L$61,9) -> Prodiamine | T25: =VLOOKUP($R25,Herbicide_Data!$A$1:$Q$61,13) -> 16 | U25: =T25*($H25/43560) -> 3.3057851 | V25: =IF($G25 = ("Preemerge"),"MSM Turf 228-373") -> FALSE | W25: =VLOOKUP($V25,Herbicide_Data!$A$1:$L$17,9) -> #N/A | X25: =VLOOKUP($V25,Herbicide_Data!$A$1:$L$17,12) -> #N/A | Y25: =X25*($H25/43560) -> #N/A | AH25: =IF($G25 = ("Spring Preemerge (Jan)"),"Surfactant") -> Surfactant | AI25: =VLOOKUP($AH25,Herbicide_Data!$A$1:$Q$61,13) -> 12.8 | AJ25: =AI25*($H25/43560) -> 2.6446281
A26: Riley Bennett | B26: 45726 | C26: 0.77083333 | D26: =C26+0.0208333 -> 0.79166663 | E26: Matthew Stowers | F26: =IFERROR(VLOOKUP(E26,Data!A$2:B$5,2,TRUE), "") -> 48160 | G26: Spring Preemerge (Jan) | H26: =IFERROR(VLOOKUP(A26,Customer_Data!$A$1:$P$114,8,TRUE),"") -> 7500 | J26: =IF($G26=("Fall (pre/post emerge)"),"Princep Liquid (100-526)", IF($G26=("Fertilize"),"Harrell's 34-0-5",IF($G26=("Spot Treat"),"Outrider (59639-223)",""))) | K26: =(VLOOKUP($J26,Herbicide_Data!$A$1:$L$61,9,TRUE)) -> #N/A | L26: =VLOOKUP($J26,Herbicide_Data!$A$1:$L$61,12,TRUE) -> #N/A | M26: =L26*(H26/43560) -> #N/A | N26: =IF($G26=("Fall (pre/post emerge)"),"Triplet SF (3-Way) 228-312",IF($G26=("Spring Preemerge (Jan)"),"Triplet SF (3-Way) 228-312",IF($G26=("Spring Preemerge (Apr)"),"Triplet SF (3-Way) 228-312",""))) -> Triplet SF (3-Way) 228-312 | O26: =VLOOKUP($N26,Herbicide_Data!$A$1:$L$61,9) -> 2,4-D, dimethylamine salt; Dicamba, dimethylamine salt;Mecoprop-p (MCPP-p), dimethylamine salt | P26: =VLOOKUP($N26,Herbicide_Data!$A$1:$P$61,13) -> 24 | Q26: =P26*($H26/43560) -> 4.1322314 | R26: =IF($G26=("Fall (pre/post emerge)"),"Resolute 4Fl (100-1139)",IF($G26=("Spring Preemerge (Jan)"),"Resolute 4Fl (100-1139)",IF($G26=("Spring Preemerge (Apr)"),"Certinty Turf 59639-226",""))) -> Resolute 4Fl (100-1139) | S26: =VLOOKUP($R26,Herbicide_Data!$A$1:$L$61,9) -> Prodiamine | T26: =VLOOKUP($R26,Herbicide_Data!$A$1:$Q$61,13) -> 16 | U26: =T26*($H26/43560) -> 2.7548209 | V26: =IF($G26 = ("Preemerge"),"MSM Turf 228-373") -> FALSE | W26: =VLOOKUP($V26,Herbicide_Data!$A$1:$L$17,9) -> #N/A | X26: =VLOOKUP($V26,Herbicide_Data!$A$1:$L$17,12) -> #N/A | Y26: =X26*($H26/43560) -> #N/A | AH26: =IF($G26 = ("Spring Preemerge (Jan)"),"Surfactant") -> Surfactant | AI26: =VLOOKUP($AH26,Herbicide_Data!$A$1:$Q$61,13) -> 12.8 | AJ26: =AI26*($H26/43560) -> 2.2038567
A27: Danny Cooper | B27: 45727 | C27: 0.75 | D27: =C27+0.0208333 -> 0.7708333 | E27: Matthew Stowers | F27: =IFERROR(VLOOKUP(E27,Data!A$2:B$5,2,TRUE), "") -> 48160 | G27: Spring Preemerge (Jan) | H27: =IFERROR(VLOOKUP(A27,Customer_Data!$A$1:$P$114,8,TRUE),"") -> 7000 | J27: =IF($G27=("Fall (pre/post emerge)"),"Princep Liquid (100-526)", IF($G27=("Fertilize"),"Harrell's 34-0-5",IF($G27=("Spot Treat"),"Outrider (59639-223)",""))) | K27: =(VLOOKUP($J27,Herbicide_Data!$A$1:$L$61,9,TRUE)) -> #N/A | L27: =VLOOKUP($J27,Herbicide_Data!$A$1:$L$61,12,TRUE) -> #N/A | M27: =L27*(H27/43560) -> #N/A | N27: =IF($G27=("Fall (pre/post emerge)"),"Triplet SF (3-Way) 228-312",IF($G27=("Spring Preemerge (Jan)"),"Triplet SF (3-Way) 228-312",IF($G27=("Spring Preemerge (Apr)"),"Triplet SF (3-Way) 228-312",""))) -> Triplet SF (3-Way) 228-312 | O27: =VLOOKUP($N27,Herbicide_Data!$A$1:$L$61,9) -> 2,4-D, dimethylamine salt; Dicamba, dimethylamine salt;Mecoprop-p (MCPP-p), dimethylamine salt | P27: =VLOOKUP($N27,Herbicide_Data!$A$1:$P$61,13) -> 24 | Q27: =P27*($H27/43560) -> 3.8567493 | R27: =IF($G27=("Fall (pre/post emerge)"),"Resolute 4Fl (100-1139)",IF($G27=("Spring Preemerge (Jan)"),"Resolute 4Fl (100-1139)",IF($G27=("Spring Preemerge (Apr)"),"Certinty Turf 59639-226",""))) -> Resolute 4Fl (100-1139) | S27: =VLOOKUP($R27,Herbicide_Data!$A$1:$L$61,9) -> Prodiamine | T27: =VLOOKUP($R27,Herbicide_Data!$A$1:$Q$61,13) -> 16 | U27: =T27*($H27/43560) -> 2.5711662 | V27: =IF($G27 = ("Preemerge"),"MSM Turf 228-373") -> FALSE | W27: =VLOOKUP($V27,Herbicide_Data!$A$1:$L$17,9) -> #N/A | X27: =VLOOKUP($V27,Herbicide_Data!$A$1:$L$17,12) -> #N/A | Y27: =X27*($H27/43560) -> #N/A | AH27: =IF($G27 = ("Spring Preemerge (Jan)"),"Surfactant") -> Surfactant | AI27: =VLOOKUP($AH27,Herbicide_Data!$A$1:$Q$61,13) -> 12.8 | AJ27: =AI27*($H27/43560) -> 2.056933
A28: Seth Simmons | B28: 45735 | C28: 0.72916667 | D28: =C28+0.0208333 -> 0.74999997 | E28: Matthew Stowers | F28: =IFERROR(VLOOKUP(E28,Data!A$2:B$5,2,TRUE), "") -> 48160 | G28: Spring Preemerge (Jan) | H28: =IFERROR(VLOOKUP(A28,Customer_Data!$A$1:$P$114,8,TRUE),"") -> 6500 | J28: =IF($G28=("Fall (pre/post emerge)"),"Princep Liquid (100-526)", IF($G28=("Fertilize"),"Harrell's 34-0-5",IF($G28=("Spot Treat"),"Outrider (59639-223)",""))) | K28: =(VLOOKUP($J28,Herbicide_Data!$A$1:$L$61,9,TRUE)) -> #N/A | L28: =VLOOKUP($J28,Herbicide_Data!$A$1:$L$61,12,TRUE) -> #N/A | M28: =L28*(H28/43560) -> #N/A | N28: =IF($G28=("Fall (pre/post emerge)"),"Triplet SF (3-Way) 228-312",IF($G28=("Spring Preemerge (Jan)"),"Triplet SF (3-Way) 228-312",IF($G28=("Spring Preemerge (Apr)"),"Triplet SF (3-Way) 228-312",""))) -> Triplet SF (3-Way) 228-312 | O28: =VLOOKUP($N28,Herbicide_Data!$A$1:$L$61,9) -> 2,4-D, dimethylamine salt; Dicamba, dimethylamine salt;Mecoprop-p (MCPP-p), dimethylamine salt | P28: =VLOOKUP($N28,Herbicide_Data!$A$1:$P$61,13) -> 24 | Q28: =P28*($H28/43560) -> 3.5812672 | R28: =IF($G28=("Fall (pre/post emerge)"),"Resolute 4Fl (100-1139)",IF($G28=("Spring Preemerge (Jan)"),"Resolute 4Fl (100-1139)",IF($G28=("Spring Preemerge (Apr)"),"Certinty Turf 59639-226",""))) -> Resolute 4Fl (100-1139) | S28: =VLOOKUP($R28,Herbicide_Data!$A$1:$L$61,9) -> Prodiamine | T28: =VLOOKUP($R28,Herbicide_Data!$A$1:$Q$61,13) -> 16 | U28: =T28*($H28/43560) -> 2.3875115 | V28: =IF($G28 = ("Preemerge"),"MSM Turf 228-373") -> FALSE | W28: =VLOOKUP($V28,Herbicide_Data!$A$1:$L$17,9) -> #N/A | X28: =VLOOKUP($V28,Herbicide_Data!$A$1:$L$17,12) -> #N/A | Y28: =X28*($H28/43560) -> #N/A | AH28: =IF($G28 = ("Spring Preemerge (Jan)"),"Surfactant") -> Surfactant | AI28: =VLOOKUP($AH28,Herbicide_Data!$A$1:$Q$61,13) -> 12.8 | AJ28: =AI28*($H28/43560) -> 1.9100092
A29: Steve Edwards | B29: 45735 | C29: 0.75 | D29: =C29+0.0208333 -> 0.7708333 | E29: Matthew Stowers | F29: =IFERROR(VLOOKUP(E29,Data!A$2:B$5,2,TRUE), "") -> 48160 | G29: Spring Preemerge (Jan) | H29: =IFERROR(VLOOKUP(A29,Customer_Data!$A$1:$P$114,8,TRUE),"") -> 9000 | J29: =IF($G29=("Fall (pre/post emerge)"),"Princep Liquid (100-526)", IF($G29=("Fertilize"),"Harrell's 34-0-5",IF($G29=("Spot Treat"),"Outrider (59639-223)",""))) | K29: =(VLOOKUP($J29,Herbicide_Data!$A$1:$L$61,9,TRUE)) -> #N/A | L29: =VLOOKUP($J29,Herbicide_Data!$A$1:$L$61,12,TRUE) -> #N/A | M29: =L29*(H29/43560) -> #N/A | N29: =IF($G29=("Fall (pre/post emerge)"),"Triplet SF (3-Way) 228-312",IF($G29=("Spring Preemerge (Jan)"),"Triplet SF (3-Way) 228-312",IF($G29=("Spring Preemerge (Apr)"),"Triplet SF (3-Way) 228-312",""))) -> Triplet SF (3-Way) 228-312 | O29: =VLOOKUP($N29,Herbicide_Data!$A$1:$L$61,9) -> 2,4-D, dimethylamine salt; Dicamba, dimethylamine salt;Mecoprop-p (MCPP-p), dimethylamine salt | P29: =VLOOKUP($N29,Herbicide_Data!$A$1:$P$61,13) -> 24 | Q29: =P29*($H29/43560) -> 4.9586777 | R29: =IF($G29=("Fall (pre/post emerge)"),"Resolute 4Fl (100-1139)",IF($G29=("Spring Preemerge (Jan)"),"Resolute 4Fl (100-1139)",IF($G29=("Spring Preemerge (Apr)"),"Certinty Turf 59639-226",""))) -> Resolute 4Fl (100-1139) | S29: =VLOOKUP($R29,Herbicide_Data!$A$1:$L$61,9) -> Prodiamine | T29: =VLOOKUP($R29,Herbicide_Data!$A$1:$Q$61,13) -> 16 | U29: =T29*($H29/43560) -> 3.3057851 | V29: =IF($G29 = ("Preemerge"),"MSM Turf 228-373") -> FALSE | W29: =VLOOKUP($V29,Herbicide_Data!$A$1:$L$17,9) -> #N/A | X29: =VLOOKUP($V29,Herbicide_Data!$A$1:$L$17,12) -> #N/A | Y29: =X29*($H29/43560) -> #N/A | AH29: =IF($G29 = ("Spring Preemerge (Jan)"),"Surfactant") -> Surfactant | AI29: =VLOOKUP($AH29,Herbicide_Data!$A$1:$Q$61,13) -> 12.8 | AJ29: =AI29*($H29/43560) -> 2.6446281
A30: Gay Grantham | B30: 45735 | C30: 0.79166667 | D30: =C30+0.0208333 -> 0.81249997 | E30: Matthew Stowers | F30: =IFERROR(VLOOKUP(E30,Data!A$2:B$5,2,TRUE), "") -> 48160 | G30: Spring Preemerge (Jan) | H30: =IFERROR(VLOOKUP(A30,Customer_Data!$A$1:$P$114,8,TRUE),"") -> 5900 | J30: =IF($G30=("Fall (pre/post emerge)"),"Princep Liquid (100-526)", IF($G30=("Fertilize"),"Harrell's 34-0-5",IF($G30=("Spot Treat"),"Outrider (59639-223)",""))) | K30: =(VLOOKUP($J30,Herbicide_Data!$A$1:$L$61,9,TRUE)) -> #N/A | L30: =VLOOKUP($J30,Herbicide_Data!$A$1:$L$61,12,TRUE) -> #N/A | M30: =L30*(H30/43560) -> #N/A | N30: =IF($G30=("Fall (pre/post emerge)"),"Triplet SF (3-Way) 228-312",IF($G30=("Spring Preemerge (Jan)"),"Triplet SF (3-Way) 228-312",IF($G30=("Spring Preemerge (Apr)"),"Triplet SF (3-Way) 228-312",""))) -> Triplet SF (3-Way) 228-312 | O30: =VLOOKUP($N30,Herbicide_Data!$A$1:$L$61,9) -> 2,4-D, dimethylamine salt; Dicamba, dimethylamine salt;Mecoprop-p (MCPP-p), dimethylamine salt | P30: =VLOOKUP($N30,Herbicide_Data!$A$1:$P$61,13) -> 24 | Q30: =P30*($H30/43560) -> 3.2506887 | R30: =IF($G30=("Fall (pre/post emerge)"),"Resolute 4Fl (100-1139)",IF($G30=("Spring Preemerge (Jan)"),"Resolute 4Fl (100-1139)",IF($G30=("Spring Preemerge (Apr)"),"Certinty Turf 59639-226",""))) -> Resolute 4Fl (100-1139) | S30: =VLOOKUP($R30,Herbicide_Data!$A$1:$L$61,9) -> Prodiamine | T30: =VLOOKUP($R30,Herbicide_Data!$A$1:$Q$61,13) -> 16 | U30: =T30*($H30/43560) -> 2.1671258 | V30: =IF($G30 = ("Preemerge"),"MSM Turf 228-373") -> FALSE | W30: =VLOOKUP($V30,Herbicide_Data!$A$1:$L$17,9) -> #N/A | X30: =VLOOKUP($V30,Herbicide_Data!$A$1:$L$17,12) -> #N/A | Y30: =X30*($H30/43560) -> #N/A | AH30: =IF($G30 = ("Spring Preemerge (Jan)"),"Surfactant") -> Surfactant | AI30: =VLOOKUP($AH30,Herbicide_Data!$A$1:$Q$61,13) -> 12.8 | AJ30: =AI30*($H30/43560) -> 1.7337006
A31: Max Brian | B31: 45765 | C31: 0.625 | D31: =C31+0.0208333 -> 0.6458333 | E31: Matthew Stowers | F31: =IFERROR(VLOOKUP(E31,Data!A$2:B$5,2,TRUE), "") -> 48160 | G31: Spring Preemerge (Apr) | H31: =IFERROR(VLOOKUP(A31,Customer_Data!$A$1:$P$114,8,TRUE),"") -> 4670 | J31: =IF($G31=("Fall (pre/post emerge)"),"Princep Liquid (100-526)", IF($G31=("Fertilize"),"Harrell's 34-0-5",IF($G31=("Spot Treat"),"Outrider (59639-223)",""))) | K31: =(VLOOKUP($J31,Herbicide_Data!$A$1:$L$61,9,TRUE)) -> #N/A | L31: =VLOOKUP($J31,Herbicide_Data!$A$1:$L$61,12,TRUE) -> #N/A | M31: =L31*(H31/43560) -> #N/A | N31: =IF($G31=("Fall (pre/post emerge)"),"Triplet SF (3-Way) 228-312",IF($G31=("Spring Preemerge (Jan)"),"Triplet SF (3-Way) 228-312",IF($G31=("Spring Preemerge (Apr)"),"Triplet SF (3-Way) 228-312",""))) -> Triplet SF (3-Way) 228-312 | O31: =VLOOKUP($N31,Herbicide_Data!$A$1:$L$61,9) -> 2,4-D, dimethylamine salt; Dicamba, dimethylamine salt;Mecoprop-p (MCPP-p), dimethylamine salt | P31: =VLOOKUP($N31,Herbicide_Data!$A$1:$P$61,13) -> 24 | Q31: =P31*($H31/43560) -> 2.5730028 | R31: =IF($G31=("Fall (pre/post emerge)"),"Resolute 4Fl (100-1139)",IF($G31=("Spring Preemerge (Jan)"),"Resolute 4Fl (100-1139)",IF($G31=("Spring Preemerge (Apr)"),"Certinty Turf 59639-226",""))) -> Certinty Turf 59639-226 | S31: =VLOOKUP($R31,Herbicide_Data!$A$1:$L$61,9) -> Sulfosulfuron | T31: =VLOOKUP($R31,Herbicide_Data!$A$1:$Q$61,13) -> 0 | U31: =T31*($H31/43560) -> 0 | V31: =IF($G31 = ("Preemerge"),"MSM Turf 228-373") -> FALSE | W31: =VLOOKUP($V31,Herbicide_Data!$A$1:$L$17,9) -> #N/A | X31: =VLOOKUP($V31,Herbicide_Data!$A$1:$L$17,12) -> #N/A | Y31: =X31*($H31/43560) -> #N/A | AH31: =IF($G31=("Spring Preemerge (Jan)"),"Surfactant",IF($G31=("Spring Preemerge (Apr)"),"Surfactant","")) -> Surfactant | AI31: =VLOOKUP($AH31,Herbicide_Data!$A$1:$Q$61,13) -> 12.8 | AJ31: =AI31*($H31/43560) -> 1.3722681
A32: Troy Stokes | B32: 45765 | C32: 0.66666667 | D32: =C32+0.0208333 -> 0.68749997 | E32: Matthew Stowers | F32: =IFERROR(VLOOKUP(E32,Data!A$2:B$5,2,TRUE), "") -> 48160 | G32: Spring Preemerge (Apr) | H32: =IFERROR(VLOOKUP(A32,Customer_Data!$A$1:$P$114,8,TRUE),"") -> 9000 | J32: =IF($G32=("Fall (pre/post emerge)"),"Princep Liquid (100-526)", IF($G32=("Fertilize"),"Harrell's 34-0-5",IF($G32=("Spot Treat"),"Outrider (59639-223)",""))) | K32: =(VLOOKUP($J32,Herbicide_Data!$A$1:$L$61,9,TRUE)) -> #N/A | L32: =VLOOKUP($J32,Herbicide_Data!$A$1:$L$61,12,TRUE) -> #N/A | M32: =L32*(H32/43560) -> #N/A | N32: =IF($G32=("Fall (pre/post emerge)"),"Triplet SF (3-Way) 228-312",IF($G32=("Spring Preemerge (Jan)"),"Triplet SF (3-Way) 228-312",IF($G32=("Spring Preemerge (Apr)"),"Triplet SF (3-Way) 228-312",""))) -> Triplet SF (3-Way) 228-312 | O32: =VLOOKUP($N32,Herbicide_Data!$A$1:$L$61,9) -> 2,4-D, dimethylamine salt; Dicamba, dimethylamine salt;Mecoprop-p (MCPP-p), dimethylamine salt | P32: =VLOOKUP($N32,Herbicide_Data!$A$1:$P$61,13) -> 24 | Q32: =P32*($H32/43560) -> 4.9586777 | R32: =IF($G32=("Fall (pre/post emerge)"),"Resolute 4Fl (100-1139)",IF($G32=("Spring Preemerge (Jan)"),"Resolute 4Fl (100-1139)",IF($G32=("Spring Preemerge (Apr)"),"Certinty Turf 59639-226",""))) -> Certinty Turf 59639-226 | S32: =VLOOKUP($R32,Herbicide_Data!$A$1:$L$61,9) -> Sulfosulfuron | T32: =VLOOKUP($R32,Herbicide_Data!$A$1:$Q$61,13) -> 0 | U32: =T32*($H32/43560) -> 0 | V32: =IF($G32 = ("Preemerge"),"MSM Turf 228-373") -> FALSE | W32: =VLOOKUP($V32,Herbicide_Data!$A$1:$L$17,9) -> #N/A | X32: =VLOOKUP($V32,Herbicide_Data!$A$1:$L$17,12) -> #N/A | Y32: =X32*($H32/43560) -> #N/A | AH32: =IF($G32=("Spring Preemerge (Jan)"),"Surfactant",IF($G32=("Spring Preemerge (Apr)"),"Surfactant","")) -> Surfactant | AI32: =VLOOKUP($AH32,Herbicide_Data!$A$1:$Q$61,13) -> 12.8 | AJ32: =AI32*($H32/43560) -> 2.6446281
A33: David Fatheree | B33: 45765 | C33: 0.6875 | D33: =C33+0.0208333 -> 0.7083333 | E33: Matthew Stowers | F33: =IFERROR(VLOOKUP(E33,Data!A$2:B$5,2,TRUE), "") -> 48160 | G33: Spring Preemerge (Apr) | H33: =IFERROR(VLOOKUP(A33,Customer_Data!$A$1:$P$114,8,TRUE),"") -> 8910 | J33: =IF($G33=("Fall (pre/post emerge)"),"Princep Liquid (100-526)", IF($G33=("Fertilize"),"Harrell's 34-0-5",IF($G33=("Spot Treat"),"Outrider (59639-223)",""))) | K33: =(VLOOKUP($J33,Herbicide_Data!$A$1:$L$61,9,TRUE)) -> #N/A | L33: =VLOOKUP($J33,Herbicide_Data!$A$1:$L$61,12,TRUE) -> #N/A | M33: =L33*(H33/43560) -> #N/A | N33: =IF($G33=("Fall (pre/post emerge)"),"Triplet SF (3-Way) 228-312",IF($G33=("Spring Preemerge (Jan)"),"Triplet SF (3-Way) 228-312",IF($G33=("Spring Preemerge (Apr)"),"Triplet SF (3-Way) 228-312",""))) -> Triplet SF (3-Way) 228-312 | O33: =VLOOKUP($N33,Herbicide_Data!$A$1:$L$61,9) -> 2,4-D, dimethylamine salt; Dicamba, dimethylamine salt;Mecoprop-p (MCPP-p), dimethylamine salt | P33: =VLOOKUP($N33,Herbicide_Data!$A$1:$P$61,13) -> 24 | Q33: =P33*($H33/43560) -> 4.9090909 | R33: =IF($G33=("Fall (pre/post emerge)"),"Resolute 4Fl (100-1139)",IF($G33=("Spring Preemerge (Jan)"),"Resolute 4Fl (100-1139)",IF($G33=("Spring Preemerge (Apr)"),"Certinty Turf 59639-226",""))) -> Certinty Turf 59639-226 | S33: =VLOOKUP($R33,Herbicide_Data!$A$1:$L$61,9) -> Sulfosulfuron | T33: =VLOOKUP($R33,Herbicide_Data!$A$1:$Q$61,13) -> 0 | U33: =T33*($H33/43560) -> 0 | V33: =IF($G33 = ("Preemerge"),"MSM Turf 228-373") -> FALSE | W33: =VLOOKUP($V33,Herbicide_Data!$A$1:$L$17,9) -> #N/A | X33: =VLOOKUP($V33,Herbicide_Data!$A$1:$L$17,12) -> #N/A | Y33: =X33*($H33/43560) -> #N/A | AH33: =IF($G33=("Spring Preemerge (Jan)"),"Surfactant",IF($G33=("Spring Preemerge (Apr)"),"Surfactant","")) -> Surfactant | AI33: =VLOOKUP($AH33,Herbicide_Data!$A$1:$Q$61,13) -> 12.8 | AJ33: =AI33*($H33/43560) -> 2.6181818
A34: Max Miller | B34: 45765 | C34: 0.70833333 | D34: =C34+0.0208333 -> 0.72916663 | E34: Matthew Stowers | F34: =IFERROR(VLOOKUP(E34,Data!A$2:B$5,2,TRUE), "") -> 48160 | G34: Spring Preemerge (Apr) | H34: =IFERROR(VLOOKUP(A34,Customer_Data!$A$1:$P$114,8,TRUE),"") -> 3100 | J34: =IF($G34=("Fall (pre/post emerge)"),"Princep Liquid (100-526)", IF($G34=("Fertilize"),"Harrell's 34-0-5",IF($G34=("Spot Treat"),"Outrider (59639-223)",""))) | K34: =(VLOOKUP($J34,Herbicide_Data!$A$1:$L$61,9,TRUE)) -> #N/A | L34: =VLOOKUP($J34,Herbicide_Data!$A$1:$L$61,12,TRUE) -> #N/A | M34: =L34*(H34/43560) -> #N/A | N34: =IF($G34=("Fall (pre/post emerge)"),"Triplet SF (3-Way) 228-312",IF($G34=("Spring Preemerge (Jan)"),"Triplet SF (3-Way) 228-312",IF($G34=("Spring Preemerge (Apr)"),"Triplet SF (3-Way) 228-312",""))) -> Triplet SF (3-Way) 228-312 | O34: =VLOOKUP($N34,Herbicide_Data!$A$1:$L$61,9) -> 2,4-D, dimethylamine salt; Dicamba, dimethylamine salt;Mecoprop-p (MCPP-p), dimethylamine salt | P34: =VLOOKUP($N34,Herbicide_Data!$A$1:$P$61,13) -> 24 | Q34: =P34*($H34/43560) -> 1.707989 | R34: =IF($G34=("Fall (pre/post emerge)"),"Resolute 4Fl (100-1139)",IF($G34=("Spring Preemerge (Jan)"),"Resolute 4Fl (100-1139)",IF($G34=("Spring Preemerge (Apr)"),"Certinty Turf 59639-226",""))) -> Certinty Turf 59639-226 | S34: =VLOOKUP($R34,Herbicide_Data!$A$1:$L$61,9) -> Sulfosulfuron | T34: =VLOOKUP($R34,Herbicide_Data!$A$1:$Q$61,13) -> 0 | U34: =T34*($H34/43560) -> 0 | V34: =IF($G34 = ("Preemerge"),"MSM Turf 228-373") -> FALSE | W34: =VLOOKUP($V34,Herbicide_Data!$A$1:$L$17,9) -> #N/A | X34: =VLOOKUP($V34,Herbicide_Data!$A$1:$L$17,12) -> #N/A | Y34: =X34*($H34/43560) -> #N/A | AH34: =IF($G34=("Spring Preemerge (Jan)"),"Surfactant",IF($G34=("Spring Preemerge (Apr)"),"Surfactant","")) -> Surfactant | AI34: =VLOOKUP($AH34,Herbicide_Data!$A$1:$Q$61,13) -> 12.8 | AJ34: =AI34*($H34/43560) -> 0.91092746
A35: Browning Bergold | B35: 45765 | C35: 0.70833333 | D35: =C35+0.0208333 -> 0.72916663 | E35: Matthew Stowers | F35: =IFERROR(VLOOKUP(E35,Data!A$2:B$5,2,TRUE), "") -> 48160 | G35: Spring Preemerge (Apr) | H35: =IFERROR(VLOOKUP(A35,Customer_Data!$A$1:$P$114,8,TRUE),"") -> 6400 | J35: =IF($G35=("Fall (pre/post emerge)"),"Princep Liquid (100-526)", IF($G35=("Fertilize"),"Harrell's 34-0-5",IF($G35=("Spot Treat"),"Outrider (59639-223)",""))) | K35: =(VLOOKUP($J35,Herbicide_Data!$A$1:$L$61,9,TRUE)) -> #N/A | L35: =VLOOKUP($J35,Herbicide_Data!$A$1:$L$61,12,TRUE) -> #N/A | M35: =L35*(H35/43560) -> #N/A | N35: =IF($G35=("Fall (pre/post emerge)"),"Triplet SF (3-Way) 228-312",IF($G35=("Spring Preemerge (Jan)"),"Triplet SF (3-Way) 228-312",IF($G35=("Spring Preemerge (Apr)"),"Triplet SF (3-Way) 228-312",""))) -> Triplet SF (3-Way) 228-312 | O35: =VLOOKUP($N35,Herbicide_Data!$A$1:$L$61,9) -> 2,4-D, dimethylamine salt; Dicamba, dimethylamine salt;Mecoprop-p (MCPP-p), dimethylamine salt | P35: =VLOOKUP($N35,Herbicide_Data!$A$1:$P$61,13) -> 24 | Q35: =P35*($H35/43560) -> 3.5261708 | R35: =IF($G35=("Fall (pre/post emerge)"),"Resolute 4Fl (100-1139)",IF($G35=("Spring Preemerge (Jan)"),"Resolute 4Fl (100-1139)",IF($G35=("Spring Preemerge (Apr)"),"Certinty Turf 59639-226",""))) -> Certinty Turf 59639-226 | S35: =VLOOKUP($R35,Herbicide_Data!$A$1:$L$61,9) -> Sulfosulfuron | T35: =VLOOKUP($R35,Herbicide_Data!$A$1:$Q$61,13) -> 0 | U35: =T35*($H35/43560) -> 0 | V35: =IF($G35 = ("Preemerge"),"MSM Turf 228-373") -> FALSE | W35: =VLOOKUP($V35,Herbicide_Data!$A$1:$L$17,9) -> #N/A | X35: =VLOOKUP($V35,Herbicide_Data!$A$1:$L$17,12) -> #N/A | Y35: =X35*($H35/43560) -> #N/A | AH35: =IF($G35=("Spring Preemerge (Jan)"),"Surfactant",IF($G35=("Spring Preemerge (Apr)"),"Surfactant","")) -> Surfactant | AI35: =VLOOKUP($AH35,Herbicide_Data!$A$1:$Q$61,13) -> 12.8 | AJ35: =AI35*($H35/43560) -> 1.8806244
A36: Dot Stuart | B36: 45765 | C36: 0.72916667 | D36: =C36+0.0208333 -> 0.74999997 | E36: Matthew Stowers | F36: =IFERROR(VLOOKUP(E36,Data!A$2:B$5,2,TRUE), "") -> 48160 | G36: Spring Preemerge (Apr) | H36: =IFERROR(VLOOKUP(A36,Customer_Data!$A$1:$P$114,8,TRUE),"") -> 1800 | J36: =IF($G36=("Fall (pre/post emerge)"),"Princep Liquid (100-526)", IF($G36=("Fertilize"),"Harrell's 34-0-5",IF($G36=("Spot Treat"),"Outrider (59639-223)",""))) | K36: =(VLOOKUP($J36,Herbicide_Data!$A$1:$L$61,9,TRUE)) -> #N/A | L36: =VLOOKUP($J36,Herbicide_Data!$A$1:$L$61,12,TRUE) -> #N/A | M36: =L36*(H36/43560) -> #N/A | N36: =IF($G36=("Fall (pre/post emerge)"),"Triplet SF (3-Way) 228-312",IF($G36=("Spring Preemerge (Jan)"),"Triplet SF (3-Way) 228-312",IF($G36=("Spring Preemerge (Apr)"),"Triplet SF (3-Way) 228-312",""))) -> Triplet SF (3-Way) 228-312 | O36: =VLOOKUP($N36,Herbicide_Data!$A$1:$L$61,9) -> 2,4-D, dimethylamine salt; Dicamba, dimethylamine salt;Mecoprop-p (MCPP-p), dimethylamine salt | P36: =VLOOKUP($N36,Herbicide_Data!$A$1:$P$61,13) -> 24 | Q36: =P36*($H36/43560) -> 0.99173554 | R36: =IF($G36=("Fall (pre/post emerge)"),"Resolute 4Fl (100-1139)",IF($G36=("Spring Preemerge (Jan)"),"Resolute 4Fl (100-1139)",IF($G36=("Spring Preemerge (Apr)"),"Certinty Turf 59639-226",""))) -> Certinty Turf 59639-226 | S36: =VLOOKUP($R36,Herbicide_Data!$A$1:$L$61,9) -> Sulfosulfuron | T36: =VLOOKUP($R36,Herbicide_Data!$A$1:$Q$61,13) -> 0 | U36: =T36*($H36/43560) -> 0 | V36: =IF($G36 = ("Preemerge"),"MSM Turf 228-373") -> FALSE | W36: =VLOOKUP($V36,Herbicide_Data!$A$1:$L$17,9) -> #N/A | X36: =VLOOKUP($V36,Herbicide_Data!$A$1:$L$17,12) -> #N/A | Y36: =X36*($H36/43560) -> #N/A | AH36: =IF($G36=("Spring Preemerge (Jan)"),"Surfactant",IF($G36=("Spring Preemerge (Apr)"),"Surfactant","")) -> Surfactant | AI36: =VLOOKUP($AH36,Herbicide_Data!$A$1:$Q$61,13) -> 12.8 | AJ36: =AI36*($H36/43560) -> 0.52892562
A37: Jordan Bane | B37: 45765 | C37: 0.72916667 | D37: =C37+0.0208333 -> 0.74999997 | E37: Matthew Stowers | F37: =IFERROR(VLOOKUP(E37,Data!A$2:B$5,2,TRUE), "") -> 48160 | G37: Spring Preemerge (Apr) | H37: =IFERROR(VLOOKUP(A37,Customer_Data!$A$1:$P$114,8,TRUE),"") -> 4200 | J37: =IF($G37=("Fall (pre/post emerge)"),"Princep Liquid (100-526)", IF($G37=("Fertilize"),"Harrell's 34-0-5",IF($G37=("Spot Treat"),"Outrider (59639-223)",""))) | K37: =(VLOOKUP($J37,Herbicide_Data!$A$1:$L$61,9,TRUE)) -> #N/A | L37: =VLOOKUP($J37,Herbicide_Data!$A$1:$L$61,12,TRUE) -> #N/A | M37: =L37*(H37/43560) -> #N/A | N37: =IF($G37=("Fall (pre/post emerge)"),"Triplet SF (3-Way) 228-312",IF($G37=("Spring Preemerge (Jan)"),"Triplet SF (3-Way) 228-312",IF($G37=("Spring Preemerge (Apr)"),"Triplet SF (3-Way) 228-312",""))) -> Triplet SF (3-Way) 228-312 | O37: =VLOOKUP($N37,Herbicide_Data!$A$1:$L$61,9) -> 2,4-D, dimethylamine salt; Dicamba, dimethylamine salt;Mecoprop-p (MCPP-p), dimethylamine salt | P37: =VLOOKUP($N37,Herbicide_Data!$A$1:$P$61,13) -> 24 | Q37: =P37*($H37/43560) -> 2.3140496 | R37: =IF($G37=("Fall (pre/post emerge)"),"Resolute 4Fl (100-1139)",IF($G37=("Spring Preemerge (Jan)"),"Resolute 4Fl (100-1139)",IF($G37=("Spring Preemerge (Apr)"),"Certinty Turf 59639-226",""))) -> Certinty Turf 59639-226 | S37: =VLOOKUP($R37,Herbicide_Data!$A$1:$L$61,9) -> Sulfosulfuron | T37: =VLOOKUP($R37,Herbicide_Data!$A$1:$Q$61,13) -> 0 | U37: =T37*($H37/43560) -> 0 | V37: =IF($G37 = ("Preemerge"),"MSM Turf 228-373") -> FALSE | W37: =VLOOKUP($V37,Herbicide_Data!$A$1:$L$17,9) -> #N/A | X37: =VLOOKUP($V37,Herbicide_Data!$A$1:$L$17,12) -> #N/A | Y37: =X37*($H37/43560) -> #N/A | AH37: =IF($G37=("Spring Preemerge (Jan)"),"Surfactant",IF($G37=("Spring Preemerge (Apr)"),"Surfactant","")) -> Surfactant | AI37: =VLOOKUP($AH37,Herbicide_Data!$A$1:$Q$61,13) -> 12.8 | AJ37: =AI37*($H37/43560) -> 1.2341598
A38: Matt Runner | B38: 45765 | C38: 0.75 | D38: =C38+0.0208333 -> 0.7708333 | E38: Matthew Stowers | F38: =IFERROR(VLOOKUP(E38,Data!A$2:B$5,2,TRUE), "") -> 48160 | G38: Spring Preemerge (Apr) | H38: =IFERROR(VLOOKUP(A38,Customer_Data!$A$1:$P$114,8,TRUE),"") -> 2000 | J38: =IF($G38=("Fall (pre/post emerge)"),"Princep Liquid (100-526)", IF($G38=("Fertilize"),"Harrell's 34-0-5",IF($G38=("Spot Treat"),"Outrider (59639-223)",""))) | K38: =(VLOOKUP($J38,Herbicide_Data!$A$1:$L$61,9,TRUE)) -> #N/A | L38: =VLOOKUP($J38,Herbicide_Data!$A$1:$L$61,12,TRUE) -> #N/A | M38: =L38*(H38/43560) -> #N/A | N38: =IF($G38=("Fall (pre/post emerge)"),"Triplet SF (3-Way) 228-312",IF($G38=("Spring Preemerge (Jan)"),"Triplet SF (3-Way) 228-312",IF($G38=("Spring Preemerge (Apr)"),"Triplet SF (3-Way) 228-312",""))) -> Triplet SF (3-Way) 228-312 | O38: =VLOOKUP($N38,Herbicide_Data!$A$1:$L$61,9) -> 2,4-D, dimethylamine salt; Dicamba, dimethylamine salt;Mecoprop-p (MCPP-p), dimethylamine salt | P38: =VLOOKUP($N38,Herbicide_Data!$A$1:$P$61,13) -> 24 | Q38: =P38*($H38/43560) -> 1.1019284 | R38: =IF($G38=("Fall (pre/post emerge)"),"Resolute 4Fl (100-1139)",IF($G38=("Spring Preemerge (Jan)"),"Resolute 4Fl (100-1139)",IF($G38=("Spring Preemerge (Apr)"),"Certinty Turf 59639-226",""))) -> Certinty Turf 59639-226 | S38: =VLOOKUP($R38,Herbicide_Data!$A$1:$L$61,9) -> Sulfosulfuron | T38: =VLOOKUP($R38,Herbicide_Data!$A$1:$Q$61,13) -> 0 | U38: =T38*($H38/43560) -> 0 | V38: =IF($G38 = ("Preemerge"),"MSM Turf 228-373") -> FALSE | W38: =VLOOKUP($V38,Herbicide_Data!$A$1:$L$17,9) -> #N/A | X38: =VLOOKUP($V38,Herbicide_Data!$A$1:$L$17,12) -> #N/A | Y38: =X38*($H38/43560) -> #N/A | AH38: =IF($G38=("Spring Preemerge (Jan)"),"Surfactant",IF($G38=("Spring Preemerge (Apr)"),"Surfactant","")) -> Surfactant | AI38: =VLOOKUP($AH38,Herbicide_Data!$A$1:$Q$61,13) -> 12.8 | AJ38: =AI38*($H38/43560) -> 0.58769513
A39: Gay Grantham | B39: 45766 | C39: =IF(ISBLANK($A39),"",NOW()-TODAY()) -> 0.63285475 | D39: =C39+0.0208333 -> 0.65368805 | E39: Matthew Stowers | F39: =IFERROR(VLOOKUP(E39,Data!A$2:B$5,2,TRUE), "") -> 48160 | G39: Spring Preemerge (Apr) | H39: =IFERROR(VLOOKUP(A39,Customer_Data!$A$1:$P$114,8,TRUE),"") -> 5900 | J39: =IF($G39=("Fall (pre/post emerge)"),"Princep Liquid (100-526)", IF($G39=("Fertilize"),"Harrell's 34-0-5",IF($G39=("Spot Treat"),"Outrider (59639-223)",""))) | K39: =(VLOOKUP($J39,Herbicide_Data!$A$1:$L$61,9,TRUE)) -> #N/A | L39: =VLOOKUP($J39,Herbicide_Data!$A$1:$L$61,12,TRUE) -> #N/A | M39: =L39*(H39/43560) -> #N/A | N39: =IF($G39=("Fall (pre/post emerge)"),"Triplet SF (3-Way) 228-312",IF($G39=("Spring Preemerge (Jan)"),"Triplet SF (3-Way) 228-312",IF($G39=("Spring Preemerge (Apr)"),"Triplet SF (3-Way) 228-312",""))) -> Triplet SF (3-Way) 228-312 | O39: =VLOOKUP($N39,Herbicide_Data!$A$1:$L$61,9) -> 2,4-D, dimethylamine salt; Dicamba, dimethylamine salt;Mecoprop-p (MCPP-p), dimethylamine salt | P39: =VLOOKUP($N39,Herbicide_Data!$A$1:$P$61,13) -> 24 | Q39: =P39*($H39/43560) -> 3.2506887 | R39: =IF($G39=("Fall (pre/post emerge)"),"Resolute 4Fl (100-1139)",IF($G39=("Spring Preemerge (Jan)"),"Resolute 4Fl (100-1139)",IF($G39=("Spring Preemerge (Apr)"),"Certinty Turf 59639-226",""))) -> Certinty Turf 59639-226 | S39: =VLOOKUP($R39,Herbicide_Data!$A$1:$L$61,9) -> Sulfosulfuron | T39: =VLOOKUP($R39,Herbicide_Data!$A$1:$Q$61,13) -> 0 | U39: =T39*($H39/43560) -> 0 | V39: =IF($G39 = ("Preemerge"),"MSM Turf 228-373") -> FALSE | W39: =VLOOKUP($V39,Herbicide_Data!$A$1:$L$17,9) -> #N/A | X39: =VLOOKUP($V39,Herbicide_Data!$A$1:$L$17,12) -> #N/A | Y39: =X39*($H39/43560) -> #N/A | AH39: =IF($G39=("Spring Preemerge (Jan)"),"Surfactant",IF($G39=("Spring Preemerge (Apr)"),"Surfactant","")) -> Surfactant | AI39: =VLOOKUP($AH39,Herbicide_Data!$A$1:$Q$61,13) -> 12.8 | AJ39: =AI39*($H39/43560) -> 1.7337006
A40: Riley Bennett | B40: 45767 | C40: 0.625 | D40: =C40+0.0208333 -> 0.6458333 | E40: Matthew Stowers | F40: =IFERROR(VLOOKUP(E40,Data!A$2:B$5,2,TRUE), "") -> 48160 | G40: Spring Preemerge (Apr) | H40: =IFERROR(VLOOKUP(A40,Customer_Data!$A$1:$P$114,8,TRUE),"") -> 7500 | J40: =IF($G40=("Fall (pre/post emerge)"),"Princep Liquid (100-526)", IF($G40=("Fertilize"),"Harrell's 34-0-5",IF($G40=("Spot Treat"),"Outrider (59639-223)",""))) | K40: =(VLOOKUP($J40,Herbicide_Data!$A$1:$L$61,9,TRUE)) -> #N/A | L40: =VLOOKUP($J40,Herbicide_Data!$A$1:$L$61,12,TRUE) -> #N/A | M40: =L40*(H40/43560) -> #N/A | N40: =IF($G40=("Fall (pre/post emerge)"),"Triplet SF (3-Way) 228-312",IF($G40=("Spring Preemerge (Jan)"),"Triplet SF (3-Way) 228-312",IF($G40=("Spring Preemerge (Apr)"),"Triplet SF (3-Way) 228-312",""))) -> Triplet SF (3-Way) 228-312 | O40: =VLOOKUP($N40,Herbicide_Data!$A$1:$L$61,9) -> 2,4-D, dimethylamine salt; Dicamba, dimethylamine salt;Mecoprop-p (MCPP-p), dimethylamine salt | P40: =VLOOKUP($N40,Herbicide_Data!$A$1:$P$61,13) -> 24 | Q40: =P40*($H40/43560) -> 4.1322314 | R40: =IF($G40=("Fall (pre/post emerge)"),"Resolute 4Fl (100-1139)",IF($G40=("Spring Preemerge (Jan)"),"Resolute 4Fl (100-1139)",IF($G40=("Spring Preemerge (Apr)"),"Certinty Turf 59639-226",""))) -> Certinty Turf 59639-226 | S40: =VLOOKUP($R40,Herbicide_Data!$A$1:$L$61,9) -> Sulfosulfuron | T40: =VLOOKUP($R40,Herbicide_Data!$A$1:$Q$61,13) -> 0 | U40: =T40*($H40/43560) -> 0 | V40: =IF($G40 = ("Preemerge"),"MSM Turf 228-373") -> FALSE | W40: =VLOOKUP($V40,Herbicide_Data!$A$1:$L$17,9) -> #N/A | X40: =VLOOKUP($V40,Herbicide_Data!$A$1:$L$17,12) -> #N/A | Y40: =X40*($H40/43560) -> #N/A | AH40: =IF($G40=("Spring Preemerge (Jan)"),"Surfactant",IF($G40=("Spring Preemerge (Apr)"),"Surfactant","")) -> Surfactant | AI40: =VLOOKUP($AH40,Herbicide_Data!$A$1:$Q$61,13) -> 12.8 | AJ40: =AI40*($H40/43560) -> 2.2038567
A41: Gene Henderson | B41: 45767 | C41: 0.64583333 | D41: =C41+0.0208333 -> 0.66666663 | E41: Matthew Stowers | F41: =IFERROR(VLOOKUP(E41,Data!A$2:B$5,2,TRUE), "") -> 48160 | G41: Spring Preemerge (Apr) | H41: =IFERROR(VLOOKUP(A41,Customer_Data!$A$1:$P$114,8,TRUE),"") -> 11000 | J41: =IF($G41=("Fall (pre/post emerge)"),"Princep Liquid (100-526)", IF($G41=("Fertilize"),"Harrell's 34-0-5",IF($G41=("Spot Treat"),"Outrider (59639-223)",""))) | K41: =(VLOOKUP($J41,Herbicide_Data!$A$1:$L$61,9,TRUE)) -> #N/A | L41: =VLOOKUP($J41,Herbicide_Data!$A$1:$L$61,12,TRUE) -> #N/A | M41: =L41*(H41/43560) -> #N/A | N41: =IF($G41=("Fall (pre/post emerge)"),"Triplet SF (3-Way) 228-312",IF($G41=("Spring Preemerge (Jan)"),"Triplet SF (3-Way) 228-312",IF($G41=("Spring Preemerge (Apr)"),"Triplet SF (3-Way) 228-312",""))) -> Triplet SF (3-Way) 228-312 | O41: =VLOOKUP($N41,Herbicide_Data!$A$1:$L$61,9) -> 2,4-D, dimethylamine salt; Dicamba, dimethylamine salt;Mecoprop-p (MCPP-p), dimethylamine salt | P41: =VLOOKUP($N41,Herbicide_Data!$A$1:$P$61,13) -> 24 | Q41: =P41*($H41/43560) -> 6.0606061 | R41: =IF($G41=("Fall (pre/post emerge)"),"Resolute 4Fl (100-1139)",IF($G41=("Spring Preemerge (Jan)"),"Resolute 4Fl (100-1139)",IF($G41=("Spring Preemerge (Apr)"),"Certinty Turf 59639-226",""))) -> Certinty Turf 59639-226 | S41: =VLOOKUP($R41,Herbicide_Data!$A$1:$L$61,9) -> Sulfosulfuron | T41: =VLOOKUP($R41,Herbicide_Data!$A$1:$Q$61,13) -> 0 | U41: =T41*($H41/43560) -> 0 | V41: =IF($G41 = ("Preemerge"),"MSM Turf 228-373") -> FALSE | W41: =VLOOKUP($V41,Herbicide_Data!$A$1:$L$17,9) -> #N/A | X41: =VLOOKUP($V41,Herbicide_Data!$A$1:$L$17,12) -> #N/A | Y41: =X41*($H41/43560) -> #N/A | AH41: =IF($G41=("Spring Preemerge (Jan)"),"Surfactant",IF($G41=("Spring Preemerge (Apr)"),"Surfactant","")) -> Surfactant | AI41: =VLOOKUP($AH41,Herbicide_Data!$A$1:$Q$61,13) -> 12.8 | AJ41: =AI41*($H41/43560) -> 3.2323232
A42: Elliot Smith | B42: 45773 | C42: 0.41666667 | D42: =C42+0.0208333 -> 0.43749997 | E42: Matthew Stowers | F42: =IFERROR(VLOOKUP(E42,Data!A$2:B$5,2,TRUE), "") -> 48160 | G42: Spring Preemerge (Apr) | H42: =IFERROR(VLOOKUP(A42,Customer_Data!$A$1:$P$114,8,TRUE),"") -> 13500 | J42: =IF($G42=("Fall (pre/post emerge)"),"Princep Liquid (100-526)", IF($G42=("Fertilize"),"Harrell's 34-0-5",IF($G42=("Spot Treat"),"Outrider (59639-223)",""))) | K42: =(VLOOKUP($J42,Herbicide_Data!$A$1:$L$61,9,TRUE)) -> #N/A | L42: =VLOOKUP($J42,Herbicide_Data!$A$1:$L$61,12,TRUE) -> #N/A | M42: =L42*(H42/43560) -> #N/A | N42: =IF($G42=("Fall (pre/post emerge)"),"Triplet SF (3-Way) 228-312",IF($G42=("Spring Preemerge (Jan)"),"Triplet SF (3-Way) 228-312",IF($G42=("Spring Preemerge (Apr)"),"Triplet SF (3-Way) 228-312",""))) -> Triplet SF (3-Way) 228-312 | O42: =VLOOKUP($N42,Herbicide_Data!$A$1:$L$61,9) -> 2,4-D, dimethylamine salt; Dicamba, dimethylamine salt;Mecoprop-p (MCPP-p), dimethylamine salt | P42: =VLOOKUP($N42,Herbicide_Data!$A$1:$P$61,13) -> 24 | Q42: =P42*($H42/43560) -> 7.4380165 | R42: =IF($G42=("Fall (pre/post emerge)"),"Resolute 4Fl (100-1139)",IF($G42=("Spring Preemerge (Jan)"),"Resolute 4Fl (100-1139)",IF($G42=("Spring Preemerge (Apr)"),"Certinty Turf 59639-226",""))) -> Certinty Turf 59639-226 | S42: =VLOOKUP($R42,Herbicide_Data!$A$1:$L$61,9) -> Sulfosulfuron | T42: =VLOOKUP($R42,Herbicide_Data!$A$1:$Q$61,13) -> 0 | U42: =T42*($H42/43560) -> 0 | V42: =IF($G42 = ("Preemerge"),"MSM Turf 228-373") -> FALSE | W42: =VLOOKUP($V42,Herbicide_Data!$A$1:$L$17,9) -> #N/A | X42: =VLOOKUP($V42,Herbicide_Data!$A$1:$L$17,12) -> #N/A | Y42: =X42*($H42/43560) -> #N/A | AH42: =IF($G42=("Spring Preemerge (Jan)"),"Surfactant",IF($G42=("Spring Preemerge (Apr)"),"Surfactant","")) -> Surfactant | AI42: =VLOOKUP($AH42,Herbicide_Data!$A$1:$Q$61,13) -> 12.8 | AJ42: =AI42*($H42/43560) -> 3.9669421
A43: Bo Whatley | B43: 45773 | C43: =IF(ISBLANK($A43),"",NOW()-TODAY()) -> 0.63285475 | D43: =C43+0.0208333 -> 0.65368805 | E43: Matthew Stowers | F43: =IFERROR(VLOOKUP(E43,Data!A$2:B$5,2,TRUE), "") -> 48160 | G43: Spring Preemerge (Apr) | H43: =IFERROR(VLOOKUP(A43,Customer_Data!$A$1:$P$114,8,TRUE),"") -> 2750 | J43: =IF($G43=("Fall (pre/post emerge)"),"Princep Liquid (100-526)", IF($G43=("Fertilize"),"Harrell's 34-0-5",IF($G43=("Spot Treat"),"Outrider (59639-223)",""))) | K43: =(VLOOKUP($J43,Herbicide_Data!$A$1:$L$61,9,TRUE)) -> #N/A | L43: =VLOOKUP($J43,Herbicide_Data!$A$1:$L$61,12,TRUE) -> #N/A | M43: =L43*(H43/43560) -> #N/A | N43: =IF($G43=("Fall (pre/post emerge)"),"Triplet SF (3-Way) 228-312",IF($G43=("Spring Preemerge (Jan)"),"Triplet SF (3-Way) 228-312",IF($G43=("Spring Preemerge (Apr)"),"Triplet SF (3-Way) 228-312",""))) -> Triplet SF (3-Way) 228-312 | O43: =VLOOKUP($N43,Herbicide_Data!$A$1:$L$61,9) -> 2,4-D, dimethylamine salt; Dicamba, dimethylamine salt;Mecoprop-p (MCPP-p), dimethylamine salt | P43: =VLOOKUP($N43,Herbicide_Data!$A$1:$P$61,13) -> 24 | Q43: =P43*($H43/43560) -> 1.5151515 | R43: =IF($G43=("Fall (pre/post emerge)"),"Resolute 4Fl (100-1139)",IF($G43=("Spring Preemerge (Jan)"),"Resolute 4Fl (100-1139)",IF($G43=("Spring Preemerge (Apr)"),"Certinty Turf 59639-226",""))) -> Certinty Turf 59639-226 | S43: =VLOOKUP($R43,Herbicide_Data!$A$1:$L$61,9) -> Sulfosulfuron | T43: =VLOOKUP($R43,Herbicide_Data!$A$1:$Q$61,13) -> 0 | U43: =T43*($H43/43560) -> 0 | V43: =IF($G43 = ("Preemerge"),"MSM Turf 228-373") -> FALSE | W43: =VLOOKUP($V43,Herbicide_Data!$A$1:$L$17,9) -> #N/A | X43: =VLOOKUP($V43,Herbicide_Data!$A$1:$L$17,12) -> #N/A | Y43: =X43*($H43/43560) -> #N/A | AH43: =IF($G43=("Spring Preemerge (Jan)"),"Surfactant",IF($G43=("Spring Preemerge (Apr)"),"Surfactant","")) -> Surfactant | AI43: =VLOOKUP($AH43,Herbicide_Data!$A$1:$Q$61,13) -> 12.8 | AJ43: =AI43*($H43/43560) -> 0.80808081
A44: Luther Holmes | B44: 45774 | C44: 0.5 | D44: =C44+0.0208333 -> 0.5208333 | E44: Matthew Stowers | F44: =IFERROR(VLOOKUP(E44,Data!A$2:B$5,2,TRUE), "") -> 48160 | G44: Spring Preemerge (Apr) | H44: =IFERROR(VLOOKUP(A44,Customer_Data!$A$1:$P$114,8,TRUE),"") -> 3687 | J44: =IF($G44=("Fall (pre/post emerge)"),"Princep Liquid (100-526)", IF($G44=("Fertilize"),"Harrell's 34-0-5",IF($G44=("Spot Treat"),"Outrider (59639-223)",""))) | K44: =(VLOOKUP($J44,Herbicide_Data!$A$1:$L$61,9,TRUE)) -> #N/A | L44: =VLOOKUP($J44,Herbicide_Data!$A$1:$L$61,12,TRUE) -> #N/A | M44: =L44*(H44/43560) -> #N/A | N44: =IF($G44=("Fall (pre/post emerge)"),"Triplet SF (3-Way) 228-312",IF($G44=("Spring Preemerge (Jan)"),"Triplet SF (3-Way) 228-312",IF($G44=("Spring Preemerge (Apr)"),"Triplet SF (3-Way) 228-312",""))) -> Triplet SF (3-Way) 228-312 | O44: =VLOOKUP($N44,Herbicide_Data!$A$1:$L$61,9) -> 2,4-D, dimethylamine salt; Dicamba, dimethylamine salt;Mecoprop-p (MCPP-p), dimethylamine salt | P44: =VLOOKUP($N44,Herbicide_Data!$A$1:$P$61,13) -> 24 | Q44: =P44*($H44/43560) -> 2.031405 | R44: =IF($G44=("Fall (pre/post emerge)"),"Resolute 4Fl (100-1139)",IF($G44=("Spring Preemerge (Jan)"),"Resolute 4Fl (100-1139)",IF($G44=("Spring Preemerge (Apr)"),"Certinty Turf 59639-226",""))) -> Certinty Turf 59639-226 | S44: =VLOOKUP($R44,Herbicide_Data!$A$1:$L$61,9) -> Sulfosulfuron | T44: =VLOOKUP($R44,Herbicide_Data!$A$1:$Q$61,13) -> 0 | U44: =T44*($H44/43560) -> 0 | V44: =IF($G44 = ("Preemerge"),"MSM Turf 228-373") -> FALSE | W44: =VLOOKUP($V44,Herbicide_Data!$A$1:$L$17,9) -> #N/A | X44: =VLOOKUP($V44,Herbicide_Data!$A$1:$L$17,12) -> #N/A | Y44: =X44*($H44/43560) -> #N/A | AH44: =IF($G44=("Spring Preemerge (Jan)"),"Surfactant",IF($G44=("Spring Preemerge (Apr)"),"Surfactant","")) -> Surfactant | AI44: =VLOOKUP($AH44,Herbicide_Data!$A$1:$Q$61,13) -> 12.8 | AJ44: =AI44*($H44/43560) -> 1.083416
A45: Riley Cooper | B45: 45775 | C45: 0.70833333 | D45: =C45+0.0208333 -> 0.72916663 | E45: Matthew Stowers | F45: =IFERROR(VLOOKUP(E45,Data!A$2:B$5,2,TRUE), "") -> 48160 | G45: Spring Preemerge (Apr) | H45: =IFERROR(VLOOKUP(A45,Customer_Data!$A$1:$P$114,8,TRUE),"") -> 4150 | J45: =IF($G45=("Fall (pre/post emerge)"),"Princep Liquid (100-526)", IF($G45=("Fertilize"),"Harrell's 34-0-5",IF($G45=("Spot Treat"),"Outrider (59639-223)",""))) | K45: =(VLOOKUP($J45,Herbicide_Data!$A$1:$L$61,9,TRUE)) -> #N/A | L45: =VLOOKUP($J45,Herbicide_Data!$A$1:$L$61,12,TRUE) -> #N/A | M45: =L45*(H45/43560) -> #N/A | N45: =IF($G45=("Fall (pre/post emerge)"),"Triplet SF (3-Way) 228-312",IF($G45=("Spring Preemerge (Jan)"),"Triplet SF (3-Way) 228-312",IF($G45=("Spring Preemerge (Apr)"),"Triplet SF (3-Way) 228-312",""))) -> Triplet SF (3-Way) 228-312 | O45: =VLOOKUP($N45,Herbicide_Data!$A$1:$L$61,9) -> 2,4-D, dimethylamine salt; Dicamba, dimethylamine salt;Mecoprop-p (MCPP-p), dimethylamine salt | P45: =VLOOKUP($N45,Herbicide_Data!$A$1:$P$61,13) -> 24 | Q45: =P45*($H45/43560) -> 2.2865014 | R45: =IF($G45=("Fall (pre/post emerge)"),"Resolute 4Fl (100-1139)",IF($G45=("Spring Preemerge (Jan)"),"Resolute 4Fl (100-1139)",IF($G45=("Spring Preemerge (Apr)"),"Certinty Turf 59639-226",""))) -> Certinty Turf 59639-226 | S45: =VLOOKUP($R45,Herbicide_Data!$A$1:$L$61,9) -> Sulfosulfuron | T45: =VLOOKUP($R45,Herbicide_Data!$A$1:$Q$61,13) -> 0 | U45: =T45*($H45/43560) -> 0 | V45: =IF($G45 = ("Preemerge"),"MSM Turf 228-373") -> FALSE | W45: =VLOOKUP($V45,Herbicide_Data!$A$1:$L$17,9) -> #N/A | X45: =VLOOKUP($V45,Herbicide_Data!$A$1:$L$17,12) -> #N/A | Y45: =X45*($H45/43560) -> #N/A | AH45: =IF($G45=("Spring Preemerge (Jan)"),"Surfactant",IF($G45=("Spring Preemerge (Apr)"),"Surfactant","")) -> Surfactant | AI45: =VLOOKUP($AH45,Herbicide_Data!$A$1:$Q$61,13) -> 12.8 | AJ45: =AI45*($H45/43560) -> 1.2194674
A46: Thomas Wilson | B46: 45775 | C46: 0.72916667 | D46: =C46+0.0208333 -> 0.74999997 | E46: Matthew Stowers | F46: =IFERROR(VLOOKUP(E46,Data!A$2:B$5,2,TRUE), "") -> 48160 | G46: Spring Preemerge (Apr) | H46: =IFERROR(VLOOKUP(A46,Customer_Data!$A$1:$P$114,8,TRUE),"") -> 3875 | J46: =IF($G46=("Fall (pre/post emerge)"),"Princep Liquid (100-526)", IF($G46=("Fertilize"),"Harrell's 34-0-5",IF($G46=("Spot Treat"),"Outrider (59639-223)",""))) | K46: =(VLOOKUP($J46,Herbicide_Data!$A$1:$L$61,9,TRUE)) -> #N/A | L46: =VLOOKUP($J46,Herbicide_Data!$A$1:$L$61,12,TRUE) -> #N/A | M46: =L46*(H46/43560) -> #N/A | N46: =IF($G46=("Fall (pre/post emerge)"),"Triplet SF (3-Way) 228-312",IF($G46=("Spring Preemerge (Jan)"),"Triplet SF (3-Way) 228-312",IF($G46=("Spring Preemerge (Apr)"),"Triplet SF (3-Way) 228-312",""))) -> Triplet SF (3-Way) 228-312 | O46: =VLOOKUP($N46,Herbicide_Data!$A$1:$L$61,9) -> 2,4-D, dimethylamine salt; Dicamba, dimethylamine salt;Mecoprop-p (MCPP-p), dimethylamine salt | P46: =VLOOKUP($N46,Herbicide_Data!$A$1:$P$61,13) -> 24 | Q46: =P46*($H46/43560) -> 2.1349862 | R46: =IF($G46=("Fall (pre/post emerge)"),"Resolute 4Fl (100-1139)",IF($G46=("Spring Preemerge (Jan)"),"Resolute 4Fl (100-1139)",IF($G46=("Spring Preemerge (Apr)"),"Certinty Turf 59639-226",""))) -> Certinty Turf 59639-226 | S46: =VLOOKUP($R46,Herbicide_Data!$A$1:$L$61,9) -> Sulfosulfuron | T46: =VLOOKUP($R46,Herbicide_Data!$A$1:$Q$61,13) -> 0 | U46: =T46*($H46/43560) -> 0 | V46: =IF($G46 = ("Preemerge"),"MSM Turf 228-373") -> FALSE | W46: =VLOOKUP($V46,Herbicide_Data!$A$1:$L$17,9) -> #N/A | X46: =VLOOKUP($V46,Herbicide_Data!$A$1:$L$17,12) -> #N/A | Y46: =X46*($H46/43560) -> #N/A | AH46: =IF($G46=("Spring Preemerge (Jan)"),"Surfactant",IF($G46=("Spring Preemerge (Apr)"),"Surfactant","")) -> Surfactant | AI46: =VLOOKUP($AH46,Herbicide_Data!$A$1:$Q$61,13) -> 12.8 | AJ46: =AI46*($H46/43560) -> 1.1386593
A47: Danny Cooper | B47: 45775 | C47: 0.75 | D47: =C47+0.0208333 -> 0.7708333 | E47: Matthew Stowers | F47: =IFERROR(VLOOKUP(E47,Data!A$2:B$5,2,TRUE), "") -> 48160 | G47: Spring Preemerge (Apr) | H47: =IFERROR(VLOOKUP(A47,Customer_Data!$A$1:$P$114,8,TRUE),"") -> 7000 | J47: =IF($G47=("Fall (pre/post emerge)"),"Princep Liquid (100-526)", IF($G47=("Fertilize"),"Harrell's 34-0-5",IF($G47=("Spot Treat"),"Outrider (59639-223)",""))) | K47: =(VLOOKUP($J47,Herbicide_Data!$A$1:$L$61,9,TRUE)) -> #N/A | L47: =VLOOKUP($J47,Herbicide_Data!$A$1:$L$61,12,TRUE) -> #N/A | M47: =L47*(H47/43560) -> #N/A | N47: =IF($G47=("Fall (pre/post emerge)"),"Triplet SF (3-Way) 228-312",IF($G47=("Spring Preemerge (Jan)"),"Triplet SF (3-Way) 228-312",IF($G47=("Spring Preemerge (Apr)"),"Triplet SF (3-Way) 228-312",""))) -> Triplet SF (3-Way) 228-312 | O47: =VLOOKUP($N47,Herbicide_Data!$A$1:$L$61,9) -> 2,4-D, dimethylamine salt; Dicamba, dimethylamine salt;Mecoprop-p (MCPP-p), dimethylamine salt | P47: =VLOOKUP($N47,Herbicide_Data!$A$1:$P$61,13) -> 24 | Q47: =P47*($H47/43560) -> 3.8567493 | R47: =IF($G47=("Fall (pre/post emerge)"),"Resolute 4Fl (100-1139)",IF($G47=("Spring Preemerge (Jan)"),"Resolute 4Fl (100-1139)",IF($G47=("Spring Preemerge (Apr)"),"Certinty Turf 59639-226",""))) -> Certinty Turf 59639-226 | S47: =VLOOKUP($R47,Herbicide_Data!$A$1:$L$61,9) -> Sulfosulfuron | T47: =VLOOKUP($R47,Herbicide_Data!$A$1:$Q$61,13) -> 0 | U47: =T47*($H47/43560) -> 0 | V47: =IF($G47 = ("Preemerge"),"MSM Turf 228-373") -> FALSE | W47: =VLOOKUP($V47,Herbicide_Data!$A$1:$L$17,9) -> #N/A | X47: =VLOOKUP($V47,Herbicide_Data!$A$1:$L$17,12) -> #N/A | Y47: =X47*($H47/43560) -> #N/A | AH47: =IF($G47=("Spring Preemerge (Jan)"),"Surfactant",IF($G47=("Spring Preemerge (Apr)"),"Surfactant","")) -> Surfactant | AI47: =VLOOKUP($AH47,Herbicide_Data!$A$1:$Q$61,13) -> 12.8 | AJ47: =AI47*($H47/43560) -> 2.056933
A48: Steve Edwards | B48: 45775 | C48: 0.77083333 | D48: =C48+0.0208333 -> 0.79166663 | E48: Matthew Stowers | F48: =IFERROR(VLOOKUP(E48,Data!A$2:B$5,2,TRUE), "") -> 48160 | G48: Spring Preemerge (Apr) | H48: =IFERROR(VLOOKUP(A48,Customer_Data!$A$1:$P$114,8,TRUE),"") -> 9000 | J48: =IF($G48=("Fall (pre/post emerge)"),"Princep Liquid (100-526)", IF($G48=("Fertilize"),"Harrell's 34-0-5",IF($G48=("Spot Treat"),"Outrider (59639-223)",""))) | K48: =(VLOOKUP($J48,Herbicide_Data!$A$1:$L$61,9,TRUE)) -> #N/A | L48: =VLOOKUP($J48,Herbicide_Data!$A$1:$L$61,12,TRUE) -> #N/A | M48: =L48*(H48/43560) -> #N/A | N48: =IF($G48=("Fall (pre/post emerge)"),"Triplet SF (3-Way) 228-312",IF($G48=("Spring Preemerge (Jan)"),"Triplet SF (3-Way) 228-312",IF($G48=("Spring Preemerge (Apr)"),"Triplet SF (3-Way) 228-312",""))) -> Triplet SF (3-Way) 228-312 | O48: =VLOOKUP($N48,Herbicide_Data!$A$1:$L$61,9) -> 2,4-D, dimethylamine salt; Dicamba, dimethylamine salt;Mecoprop-p (MCPP-p), dimethylamine salt | P48: =VLOOKUP($N48,Herbicide_Data!$A$1:$P$61,13) -> 24 | Q48: =P48*($H48/43560) -> 4.9586777 | R48: =IF($G48=("Fall (pre/post emerge)"),"Resolute 4Fl (100-1139)",IF($G48=("Spring Preemerge (Jan)"),"Resolute 4Fl (100-1139)",IF($G48=("Spring Preemerge (Apr)"),"Certinty Turf 59639-226",""))) -> Certinty Turf 59639-226 | S48: =VLOOKUP($R48,Herbicide_Data!$A$1:$L$61,9) -> Sulfosulfuron | T48: =VLOOKUP($R48,Herbicide_Data!$A$1:$Q$61,13) -> 0 | U48: =T48*($H48/43560) -> 0 | V48: =IF($G48 = ("Preemerge"),"MSM Turf 228-373") -> FALSE | W48: =VLOOKUP($V48,Herbicide_Data!$A$1:$L$17,9) -> #N/A | X48: =VLOOKUP($V48,Herbicide_Data!$A$1:$L$17,12) -> #N/A | Y48: =X48*($H48/43560) -> #N/A | AH48: =IF($G48=("Spring Preemerge (Jan)"),"Surfactant",IF($G48=("Spring Preemerge (Apr)"),"Surfactant","")) -> Surfactant | AI48: =VLOOKUP($AH48,Herbicide_Data!$A$1:$Q$61,13) -> 12.8 | AJ48: =AI48*($H48/43560) -> 2.6446281
A49: Seth Simmons | B49: 45775 | C49: 0.79166667 | D49: =C49+0.0208333 -> 0.81249997 | E49: Matthew Stowers | F49: =IFERROR(VLOOKUP(E49,Data!A$2:B$5,2,TRUE), "") -> 48160 | G49: Spring Preemerge (Apr) | H49: =IFERROR(VLOOKUP(A49,Customer_Data!$A$1:$P$114,8,TRUE),"") -> 6500 | J49: =IF($G49=("Fall (pre/post emerge)"),"Princep Liquid (100-526)", IF($G49=("Fertilize"),"Harrell's 34-0-5",IF($G49=("Spot Treat"),"Outrider (59639-223)",""))) | K49: =(VLOOKUP($J49,Herbicide_Data!$A$1:$L$61,9,TRUE)) -> #N/A | L49: =VLOOKUP($J49,Herbicide_Data!$A$1:$L$61,12,TRUE) -> #N/A | M49: =L49*(H49/43560) -> #N/A | N49: =IF($G49=("Fall (pre/post emerge)"),"Triplet SF (3-Way) 228-312",IF($G49=("Spring Preemerge (Jan)"),"Triplet SF (3-Way) 228-312",IF($G49=("Spring Preemerge (Apr)"),"Triplet SF (3-Way) 228-312",""))) -> Triplet SF (3-Way) 228-312 | O49: =VLOOKUP($N49,Herbicide_Data!$A$1:$L$61,9) -> 2,4-D, dimethylamine salt; Dicamba, dimethylamine salt;Mecoprop-p (MCPP-p), dimethylamine salt | P49: =VLOOKUP($N49,Herbicide_Data!$A$1:$P$61,13) -> 24 | Q49: =P49*($H49/43560) -> 3.5812672 | R49: =IF($G49=("Fall (pre/post emerge)"),"Resolute 4Fl (100-1139)",IF($G49=("Spring Preemerge (Jan)"),"Resolute 4Fl (100-1139)",IF($G49=("Spring Preemerge (Apr)"),"Certinty Turf 59639-226",""))) -> Certinty Turf 59639-226 | S49: =VLOOKUP($R49,Herbicide_Data!$A$1:$L$61,9) -> Sulfosulfuron | T49: =VLOOKUP($R49,Herbicide_Data!$A$1:$Q$61,13) -> 0 | U49: =T49*($H49/43560) -> 0 | V49: =IF($G49 = ("Preemerge"),"MSM Turf 228-373") -> FALSE | W49: =VLOOKUP($V49,Herbicide_Data!$A$1:$L$17,9) -> #N/A | X49: =VLOOKUP($V49,Herbicide_Data!$A$1:$L$17,12) -> #N/A | Y49: =X49*($H49/43560) -> #N/A | AH49: =IF($G49=("Spring Preemerge (Jan)"),"Surfactant",IF($G49=("Spring Preemerge (Apr)"),"Surfactant","")) -> Surfactant | AI49: =VLOOKUP($AH49,Herbicide_Data!$A$1:$Q$61,13) -> 12.8 | AJ49: =AI49*($H49/43560) -> 1.9100092
A50: Luther Stowers | B50: 45781 | C50: 0.54166667 | D50: =C50+0.0208333 -> 0.56249997 | E50: Luther Stowers | F50: =IFERROR(VLOOKUP(E50,Data!A$2:B$5,2,TRUE), "") -> 48182 | G50: Spring Preemerge (Apr) | H50: =IFERROR(VLOOKUP(A50,Customer_Data!$A$1:$P$114,8,TRUE),"") -> 5361 | J50: =IF($G50=("Fall (pre/post emerge)"),"Princep Liquid (100-526)", IF($G50=("Fertilize"),"Harrell's 34-0-5",IF($G50=("Spot Treat"),"Outrider (59639-223)",""))) | K50: =(VLOOKUP($J50,Herbicide_Data!$A$1:$L$61,9,TRUE)) -> #N/A | L50: =VLOOKUP($J50,Herbicide_Data!$A$1:$L$61,12,TRUE) -> #N/A | M50: =L50*(H50/43560) -> #N/A | N50: =IF($G50=("Fall (pre/post emerge)"),"Triplet SF (3-Way) 228-312",IF($G50=("Spring Preemerge (Jan)"),"Triplet SF (3-Way) 228-312",IF($G50=("Spring Preemerge (Apr)"),"Triplet SF (3-Way) 228-312",""))) -> Triplet SF (3-Way) 228-312 | O50: =VLOOKUP($N50,Herbicide_Data!$A$1:$L$61,9) -> 2,4-D, dimethylamine salt; Dicamba, dimethylamine salt;Mecoprop-p (MCPP-p), dimethylamine salt | P50: =VLOOKUP($N50,Herbicide_Data!$A$1:$P$61,13) -> 24 | Q50: =P50*($H50/43560) -> 2.953719 | R50: =IF($G50=("Fall (pre/post emerge)"),"Resolute 4Fl (100-1139)",IF($G50=("Spring Preemerge (Jan)"),"Resolute 4Fl (100-1139)",IF($G50=("Spring Preemerge (Apr)"),"Certinty Turf 59639-226",""))) -> Certinty Turf 59639-226 | S50: =VLOOKUP($R50,Herbicide_Data!$A$1:$L$61,9) -> Sulfosulfuron | T50: =VLOOKUP($R50,Herbicide_Data!$A$1:$Q$61,13) -> 0 | U50: =T50*($H50/43560) -> 0 | V50: =IF($G50 = ("Preemerge"),"MSM Turf 228-373") -> FALSE | W50: =VLOOKUP($V50,Herbicide_Data!$A$1:$L$17,9) -> #N/A | X50: =VLOOKUP($V50,Herbicide_Data!$A$1:$L$17,12) -> #N/A | Y50: =X50*($H50/43560) -> #N/A | AH50: =IF($G50=("Spring Preemerge (Jan)"),"Surfactant",IF($G50=("Spring Preemerge (Apr)"),"Surfactant","")) -> Surfactant | AI50: =VLOOKUP($AH50,Herbicide_Data!$A$1:$Q$61,13) -> 12.8 | AJ50: =AI50*($H50/43560) -> 1.5753168
A51: Max Miller | B51: 45801 | C51: =IF(ISBLANK($A51),"",NOW()-TODAY()) -> 0.63285475 | D51: =C51+0.0208333 -> 0.65368805 | E51: Matthew Stowers | F51: =IFERROR(VLOOKUP(E51,Data!A$2:B$5,2,TRUE), "") -> 48160 | G51: Fertilize | H51: =IFERROR(VLOOKUP(A51,Customer_Data!$A$1:$P$114,8,TRUE),"") -> 3100 | J51: =IF($G51=("Fall (pre/post emerge)"),"Princep Liquid (100-526)", IF($G51=("Fertilize"),"Harrell's 34-0-5",IF($G51=("Spot Treat"),"Outrider (59639-223)",""))) -> Harrell's 34-0-5 | K51: =(VLOOKUP($J51,Herbicide_Data!$A$1:$L$61,9,TRUE)) -> Nitrogen | L51: =VLOOKUP($J51,Herbicide_Data!$A$1:$L$61,12,TRUE) -> 2.94 | M51: =L51*(H51/43560) -> 0.20922865 | N51: =IF($G51=("Fall (pre/post emerge)"),"Triplet SF (3-Way) 228-312",IF($G51=("Spring Preemerge (Jan)"),"Triplet SF (3-Way) 228-312",IF($G51=("Spring Preemerge (Apr)"),"Triplet SF (3-Way) 228-312",""))) | O51: =VLOOKUP($N51,Herbicide_Data!$A$1:$L$61,9) -> #N/A | P51: =VLOOKUP($N51,Herbicide_Data!$A$1:$P$61,13) -> #N/A | Q51: =P51*($H51/43560) -> #N/A | R51: =IF($G51=("Fall (pre/post emerge)"),"Resolute 4Fl (100-1139)",IF($G51=("Spring Preemerge (Jan)"),"Resolute 4Fl (100-1139)",IF($G51=("Spring Preemerge (Apr)"),"Certinty Turf 59639-226",""))) | S51: =VLOOKUP($R51,Herbicide_Data!$A$1:$L$61,9) -> #N/A | T51: =VLOOKUP($R51,Herbicide_Data!$A$1:$Q$61,13) -> #N/A | U51: =T51*($H51/43560) -> #N/A | V51: =IF($G51 = ("Preemerge"),"MSM Turf 228-373") -> FALSE | W51: =VLOOKUP($V51,Herbicide_Data!$A$1:$L$17,9) -> #N/A | X51: =VLOOKUP($V51,Herbicide_Data!$A$1:$L$17,12) -> #N/A | Y51: =X51*($H51/43560) -> #N/A | AH51: =IF($G51=("Spring Preemerge (Jan)"),"Surfactant",IF($G51=("Spring Preemerge (Apr)"),"Surfactant","")) | AI51: =VLOOKUP($AH51,Herbicide_Data!$A$1:$Q$61,13) -> #N/A | AJ51: =AI51*($H51/43560) -> #N/A
A52: Max Miller | B52: 45871 | C52: 0.4375 | D52: =C52+0.0208333 -> 0.4583333 | E52: Matthew Stowers | F52: =IFERROR(VLOOKUP(E52,Data!A$2:B$5,2,TRUE), "") -> 48160 | G52: Fertilize | H52: =IFERROR(VLOOKUP(A52,Customer_Data!$A$1:$P$114,8,TRUE),"") -> 3100 | J52: =IF($G52=("Fall (pre/post emerge)"),"Princep Liquid (100-526)", IF($G52=("Fertilize"),"Harrell's 34-0-5",IF($G52=("Spot Treat"),"Outrider (59639-223)",""))) -> Harrell's 34-0-5 | K52: =(VLOOKUP($J52,Herbicide_Data!$A$1:$L$61,9,TRUE)) -> Nitrogen | L52: =VLOOKUP($J52,Herbicide_Data!$A$1:$L$61,12,TRUE) -> 2.94 | M52: =L52*(H52/43560) -> 0.20922865 | N52: =IF($G52=("Fall (pre/post emerge)"),"Triplet SF (3-Way) 228-312",IF($G52=("Spring Preemerge (Jan)"),"Triplet SF (3-Way) 228-312",IF($G52=("Spring Preemerge (Apr)"),"Triplet SF (3-Way) 228-312",""))) | O52: =VLOOKUP($N52,Herbicide_Data!$A$1:$L$61,9) -> #N/A | P52: =VLOOKUP($N52,Herbicide_Data!$A$1:$P$61,13) -> #N/A | Q52: =P52*($H52/43560) -> #N/A | R52: =IF($G52=("Fall (pre/post emerge)"),"Resolute 4Fl (100-1139)",IF($G52=("Spring Preemerge (Jan)"),"Resolute 4Fl (100-1139)",IF($G52=("Spring Preemerge (Apr)"),"Certinty Turf 59639-226",""))) | S52: =VLOOKUP($R52,Herbicide_Data!$A$1:$L$61,9) -> #N/A | T52: =VLOOKUP($R52,Herbicide_Data!$A$1:$Q$61,13) -> #N/A | U52: =T52*($H52/43560) -> #N/A | V52: =IF($G52 = ("Preemerge"),"MSM Turf 228-373") -> FALSE | W52: =VLOOKUP($V52,Herbicide_Data!$A$1:$L$17,9) -> #N/A | X52: =VLOOKUP($V52,Herbicide_Data!$A$1:$L$17,12) -> #N/A | Y52: =X52*($H52/43560) -> #N/A | AH52: =IF($G52=("Spring Preemerge (Jan)"),"Surfactant",IF($G52=("Spring Preemerge (Apr)"),"Surfactant","")) | AI52: =VLOOKUP($AH52,Herbicide_Data!$A$1:$Q$61,13) -> #N/A | AJ52: =AI52*($H52/43560) -> #N/A
A53: Max Miller | B53: 45956 | C53: =IF(ISBLANK($A53),"",NOW()-TODAY()) -> 0.63285475 | D53: =C53+0.0208333 -> 0.65368805 | E53: Matthew Stowers | F53: =IFERROR(VLOOKUP(E53,Data!A$2:B$5,2,TRUE), "") -> 48160 | G53: Fall (pre/post emerge) | H53: =IFERROR(VLOOKUP(A53,Customer_Data!$A$1:$P$114,8,TRUE),"") -> 3100 | J53: =IF($G53=("Fall (pre/post emerge)"),"Princep Liquid (100-526)", IF($G53=("Fertilize"),"Harrell's 34-0-5",IF($G53=("Spot Treat"),"Outrider (59639-223)",""))) -> Princep Liquid (100-526) | K53: =(VLOOKUP($J53,Herbicide_Data!$A$1:$L$61,9,TRUE)) -> Simazine | L53: =VLOOKUP($J53,Herbicide_Data!$A$1:$L$61,12,TRUE) -> 32 | M53: =L53*(H53/43560) -> 2.2773186 | N53: =IF($G53=("Fall (pre/post emerge)"),"Triplet SF (3-Way) 228-312",IF($G53=("Spring Preemerge (Jan)"),"Triplet SF (3-Way) 228-312",IF($G53=("Spring Preemerge (Apr)"),"Triplet SF (3-Way) 228-312",""))) -> Triplet SF (3-Way) 228-312 | O53: =VLOOKUP($N53,Herbicide_Data!$A$1:$L$61,9) -> 2,4-D, dimethylamine salt; Dicamba, dimethylamine salt;Mecoprop-p (MCPP-p), dimethylamine salt | P53: =VLOOKUP($N53,Herbicide_Data!$A$1:$P$61,13) -> 24 | Q53: =P53*($H53/43560) -> 1.707989 | R53: =IF($G53=("Fall (pre/post emerge)"),"Resolute 4Fl (100-1139)",IF($G53=("Spring Preemerge (Jan)"),"Resolute 4Fl (100-1139)",IF($G53=("Spring Preemerge (Apr)"),"Certinty Turf 59639-226",""))) -> Resolute 4Fl (100-1139) | S53: =VLOOKUP($R53,Herbicide_Data!$A$1:$L$61,9) -> Prodiamine | T53: =VLOOKUP($R53,Herbicide_Data!$A$1:$Q$61,13) -> 16 | U53: =T53*($H53/43560) -> 1.1386593 | V53: =IF($G53 = ("Preemerge"),"MSM Turf 228-373") -> FALSE | W53: =VLOOKUP($V53,Herbicide_Data!$A$1:$L$17,9) -> #N/A | X53: =VLOOKUP($V53,Herbicide_Data!$A$1:$L$17,12) -> #N/A | Y53: =X53*($H53/43560) -> #N/A | AH53: =IF($G53=("Spring Preemerge (Jan)"),"Surfactant",IF($G53=("Spring Preemerge (Apr)"),"Surfactant","")) | AI53: =VLOOKUP($AH53,Herbicide_Data!$A$1:$Q$61,13) -> #N/A | AJ53: =AI53*($H53/43560) -> #N/A
A54: Dot Stuart | B54: 45801 | C54: =IF(ISBLANK($A54),"",NOW()-TODAY()) -> 0.63285475 | D54: =C54+0.0208333 -> 0.65368805 | E54: Luther Stowers | F54: =IFERROR(VLOOKUP(E54,Data!A$2:B$5,2,TRUE), "") -> 48182 | G54: Fertilize | H54: =IFERROR(VLOOKUP(A54,Customer_Data!$A$1:$P$114,8,TRUE),"") -> 1800 | J54: =IF($G54=("Fall (pre/post emerge)"),"Princep Liquid (100-526)", IF($G54=("Fertilize"),"Harrell's 34-0-5",IF($G54=("Spot Treat"),"Outrider (59639-223)",""))) -> Harrell's 34-0-5 | K54: =(VLOOKUP($J54,Herbicide_Data!$A$1:$L$61,9,TRUE)) -> Nitrogen | L54: =VLOOKUP($J54,Herbicide_Data!$A$1:$L$61,12,TRUE) -> 2.94 | M54: =L54*(H54/43560) -> 0.1214876 | N54: =IF($G54=("Fall (pre/post emerge)"),"Triplet SF (3-Way) 228-312",IF($G54=("Spring Preemerge (Jan)"),"Triplet SF (3-Way) 228-312",IF($G54=("Spring Preemerge (Apr)"),"Triplet SF (3-Way) 228-312",""))) | O54: =VLOOKUP($N54,Herbicide_Data!$A$1:$L$61,9) -> #N/A | P54: =VLOOKUP($N54,Herbicide_Data!$A$1:$P$61,13) -> #N/A | Q54: =P54*($H54/43560) -> #N/A | R54: =IF($G54=("Fall (pre/post emerge)"),"Resolute 4Fl (100-1139)",IF($G54=("Spring Preemerge (Jan)"),"Resolute 4Fl (100-1139)",IF($G54=("Spring Preemerge (Apr)"),"Certinty Turf 59639-226",""))) | S54: =VLOOKUP($R54,Herbicide_Data!$A$1:$L$61,9) -> #N/A | T54: =VLOOKUP($R54,Herbicide_Data!$A$1:$Q$61,13) -> #N/A | U54: =T54*($H54/43560) -> #N/A | V54: =IF($G54 = ("Preemerge"),"MSM Turf 228-373") -> FALSE | W54: =VLOOKUP($V54,Herbicide_Data!$A$1:$L$17,9) -> #N/A | X54: =VLOOKUP($V54,Herbicide_Data!$A$1:$L$17,12) -> #N/A | Y54: =X54*($H54/43560) -> #N/A | AH54: =IF($G54=("Spring Preemerge (Jan)"),"Surfactant",IF($G54=("Spring Preemerge (Apr)"),"Surfactant","")) | AI54: =VLOOKUP($AH54,Herbicide_Data!$A$1:$Q$61,13) -> #N/A | AJ54: =AI54*($H54/43560) -> #N/A
A55: Dot Stuart | B55: 45871 | C55: 0.5 | D55: =C55+0.0208333 -> 0.5208333 | E55: Matthew Stowers | F55: =IFERROR(VLOOKUP(E55,Data!A$2:B$5,2,TRUE), "") -> 48160 | G55: Fertilize | H55: =IFERROR(VLOOKUP(A55,Customer_Data!$A$1:$P$114,8,TRUE),"") -> 1800 | J55: =IF($G55=("Fall (pre/post emerge)"),"Princep Liquid (100-526)", IF($G55=("Fertilize"),"Harrell's 34-0-5",IF($G55=("Spot Treat"),"Outrider (59639-223)",""))) -> Harrell's 34-0-5 | K55: =(VLOOKUP($J55,Herbicide_Data!$A$1:$L$61,9,TRUE)) -> Nitrogen | L55: =VLOOKUP($J55,Herbicide_Data!$A$1:$L$61,12,TRUE) -> 2.94 | M55: =L55*(H55/43560) -> 0.1214876 | N55: =IF($G55=("Fall (pre/post emerge)"),"Triplet SF (3-Way) 228-312",IF($G55=("Spring Preemerge (Jan)"),"Triplet SF (3-Way) 228-312",IF($G55=("Spring Preemerge (Apr)"),"Triplet SF (3-Way) 228-312",""))) | O55: =VLOOKUP($N55,Herbicide_Data!$A$1:$L$61,9) -> #N/A | P55: =VLOOKUP($N55,Herbicide_Data!$A$1:$P$61,13) -> #N/A | Q55: =P55*($H55/43560) -> #N/A | R55: =IF($G55=("Fall (pre/post emerge)"),"Resolute 4Fl (100-1139)",IF($G55=("Spring Preemerge (Jan)"),"Resolute 4Fl (100-1139)",IF($G55=("Spring Preemerge (Apr)"),"Certinty Turf 59639-226",""))) | S55: =VLOOKUP($R55,Herbicide_Data!$A$1:$L$61,9) -> #N/A | T55: =VLOOKUP($R55,Herbicide_Data!$A$1:$Q$61,13) -> #N/A | U55: =T55*($H55/43560) -> #N/A | V55: =IF($G55 = ("Preemerge"),"MSM Turf 228-373") -> FALSE | W55: =VLOOKUP($V55,Herbicide_Data!$A$1:$L$17,9) -> #N/A | X55: =VLOOKUP($V55,Herbicide_Data!$A$1:$L$17,12) -> #N/A | Y55: =X55*($H55/43560) -> #N/A | AH55: =IF($G55=("Spring Preemerge (Jan)"),"Surfactant",IF($G55=("Spring Preemerge (Apr)"),"Surfactant","")) | AI55: =VLOOKUP($AH55,Herbicide_Data!$A$1:$Q$61,13) -> #N/A | AJ55: =AI55*($H55/43560) -> #N/A
A56: Dot Stuart | B56: 45948 | C56: 0.375 | D56: =C56+0.0208333 -> 0.3958333 | E56: Matthew Stowers | F56: =IFERROR(VLOOKUP(E56,Data!A$2:B$5,2,TRUE), "") -> 48160 | G56: Fall (pre/post emerge) | H56: =IFERROR(VLOOKUP(A56,Customer_Data!$A$1:$P$114,8,TRUE),"") -> 1800 | J56: =IF($G56=("Fall (pre/post emerge)"),"Princep Liquid (100-526)", IF($G56=("Fertilize"),"Harrell's 34-0-5",IF($G56=("Spot Treat"),"Outrider (59639-223)",""))) -> Princep Liquid (100-526) | K56: =(VLOOKUP($J56,Herbicide_Data!$A$1:$L$61,9,TRUE)) -> Simazine | L56: =VLOOKUP($J56,Herbicide_Data!$A$1:$L$61,12,TRUE) -> 32 | M56: =L56*(H56/43560) -> 1.322314 | N56: =IF($G56=("Fall (pre/post emerge)"),"Triplet SF (3-Way) 228-312",IF($G56=("Spring Preemerge (Jan)"),"Triplet SF (3-Way) 228-312",IF($G56=("Spring Preemerge (Apr)"),"Triplet SF (3-Way) 228-312",""))) -> Triplet SF (3-Way) 228-312 | O56: =VLOOKUP($N56,Herbicide_Data!$A$1:$L$61,9) -> 2,4-D, dimethylamine salt; Dicamba, dimethylamine salt;Mecoprop-p (MCPP-p), dimethylamine salt | P56: =VLOOKUP($N56,Herbicide_Data!$A$1:$P$61,13) -> 24 | Q56: =P56*($H56/43560) -> 0.99173554 | R56: =IF($G56=("Fall (pre/post emerge)"),"Resolute 4Fl (100-1139)",IF($G56=("Spring Preemerge (Jan)"),"Resolute 4Fl (100-1139)",IF($G56=("Spring Preemerge (Apr)"),"Certinty Turf 59639-226",""))) -> Resolute 4Fl (100-1139) | S56: =VLOOKUP($R56,Herbicide_Data!$A$1:$L$61,9) -> Prodiamine | T56: =VLOOKUP($R56,Herbicide_Data!$A$1:$Q$61,13) -> 16 | U56: =T56*($H56/43560) -> 0.66115702 | V56: =IF($G56 = ("Preemerge"),"MSM Turf 228-373") -> FALSE | W56: =VLOOKUP($V56,Herbicide_Data!$A$1:$L$17,9) -> #N/A | X56: =VLOOKUP($V56,Herbicide_Data!$A$1:$L$17,12) -> #N/A | Y56: =X56*($H56/43560) -> #N/A | AH56: =IF($G56=("Spring Preemerge (Jan)"),"Surfactant",IF($G56=("Spring Preemerge (Apr)"),"Surfactant","")) | AI56: =VLOOKUP($AH56,Herbicide_Data!$A$1:$Q$61,13) -> #N/A | AJ56: =AI56*($H56/43560) -> #N/A
A57: Luther Holmes | B57: 45801 | C57: =IF(ISBLANK($A57),"",NOW()-TODAY()) -> 0.63285475 | D57: =C57+0.0208333 -> 0.65368805 | E57: Luther Stowers | F57: =IFERROR(VLOOKUP(E57,Data!A$2:B$5,2,TRUE), "") -> 48182 | G57: Fertilize | H57: =IFERROR(VLOOKUP(A57,Customer_Data!$A$1:$P$114,8,TRUE),"") -> 3687 | J57: =IF($G57=("Fall (pre/post emerge)"),"Princep Liquid (100-526)", IF($G57=("Fertilize"),"Harrell's 34-0-5",IF($G57=("Spot Treat"),"Outrider (59639-223)",""))) -> Harrell's 34-0-5 | K57: =(VLOOKUP($J57,Herbicide_Data!$A$1:$L$61,9,TRUE)) -> Nitrogen | L57: =VLOOKUP($J57,Herbicide_Data!$A$1:$L$61,12,TRUE) -> 2.94 | M57: =L57*(H57/43560) -> 0.24884711 | N57: =IF($G57=("Fall (pre/post emerge)"),"Triplet SF (3-Way) 228-312",IF($G57=("Spring Preemerge (Jan)"),"Triplet SF (3-Way) 228-312",IF($G57=("Spring Preemerge (Apr)"),"Triplet SF (3-Way) 228-312",""))) | O57: =VLOOKUP($N57,Herbicide_Data!$A$1:$L$61,9) -> #N/A | P57: =VLOOKUP($N57,Herbicide_Data!$A$1:$P$61,13) -> #N/A | Q57: =P57*($H57/43560) -> #N/A | R57: =IF($G57=("Fall (pre/post emerge)"),"Resolute 4Fl (100-1139)",IF($G57=("Spring Preemerge (Jan)"),"Resolute 4Fl (100-1139)",IF($G57=("Spring Preemerge (Apr)"),"Certinty Turf 59639-226",""))) | S57: =VLOOKUP($R57,Herbicide_Data!$A$1:$L$61,9) -> #N/A | T57: =VLOOKUP($R57,Herbicide_Data!$A$1:$Q$61,13) -> #N/A | U57: =T57*($H57/43560) -> #N/A | V57: =IF($G57 = ("Preemerge"),"MSM Turf 228-373") -> FALSE | W57: =VLOOKUP($V57,Herbicide_Data!$A$1:$L$17,9) -> #N/A | X57: =VLOOKUP($V57,Herbicide_Data!$A$1:$L$17,12) -> #N/A | Y57: =X57*($H57/43560) -> #N/A | AH57: =IF($G57=("Spring Preemerge (Jan)"),"Surfactant",IF($G57=("Spring Preemerge (Apr)"),"Surfactant","")) | AI57: =VLOOKUP($AH57,Herbicide_Data!$A$1:$Q$61,13) -> #N/A | AJ57: =AI57*($H57/43560) -> #N/A
A58: Luther Holmes | B58: 45871 | C58: 0.66666667 | D58: =C58+0.0208333 -> 0.68749997 | E58: Luther Stowers | F58: =IFERROR(VLOOKUP(E58,Data!A$2:B$5,2,TRUE), "") -> 48182 | G58: Fertilize | H58: =IFERROR(VLOOKUP(A58,Customer_Data!$A$1:$P$114,8,TRUE),"") -> 3687 | J58: =IF($G58=("Fall (pre/post emerge)"),"Princep Liquid (100-526)", IF($G58=("Fertilize"),"Harrell's 34-0-5",IF($G58=("Spot Treat"),"Outrider (59639-223)",""))) -> Harrell's 34-0-5 | K58: =(VLOOKUP($J58,Herbicide_Data!$A$1:$L$61,9,TRUE)) -> Nitrogen | L58: =VLOOKUP($J58,Herbicide_Data!$A$1:$L$61,12,TRUE) -> 2.94 | M58: =L58*(H58/43560) -> 0.24884711 | N58: =IF($G58=("Fall (pre/post emerge)"),"Triplet SF (3-Way) 228-312",IF($G58=("Spring Preemerge (Jan)"),"Triplet SF (3-Way) 228-312",IF($G58=("Spring Preemerge (Apr)"),"Triplet SF (3-Way) 228-312",""))) | O58: =VLOOKUP($N58,Herbicide_Data!$A$1:$L$61,9) -> #N/A | P58: =VLOOKUP($N58,Herbicide_Data!$A$1:$P$61,13) -> #N/A | Q58: =P58*($H58/43560) -> #N/A | R58: =IF($G58=("Fall (pre/post emerge)"),"Resolute 4Fl (100-1139)",IF($G58=("Spring Preemerge (Jan)"),"Resolute 4Fl (100-1139)",IF($G58=("Spring Preemerge (Apr)"),"Certinty Turf 59639-226",""))) | S58: =VLOOKUP($R58,Herbicide_Data!$A$1:$L$61,9) -> #N/A | T58: =VLOOKUP($R58,Herbicide_Data!$A$1:$Q$61,13) -> #N/A | U58: =T58*($H58/43560) -> #N/A | V58: =IF($G58 = ("Preemerge"),"MSM Turf 228-373") -> FALSE | W58: =VLOOKUP($V58,Herbicide_Data!$A$1:$L$17,9) -> #N/A | X58: =VLOOKUP($V58,Herbicide_Data!$A$1:$L$17,12) -> #N/A | Y58: =X58*($H58/43560) -> #N/A | AH58: =IF($G58=("Spring Preemerge (Jan)"),"Surfactant",IF($G58=("Spring Preemerge (Apr)"),"Surfactant","")) | AI58: =VLOOKUP($AH58,Herbicide_Data!$A$1:$Q$61,13) -> #N/A | AJ58: =AI58*($H58/43560) -> #N/A
A59: Luther Holmes | B59: 45948 | C59: 0.33333333 | D59: =C59+0.0208333 -> 0.35416663 | E59: Matthew Stowers | F59: =IFERROR(VLOOKUP(E59,Data!A$2:B$5,2,TRUE), "") -> 48160 | G59: Fall (pre/post emerge) | H59: =IFERROR(VLOOKUP(A59,Customer_Data!$A$1:$P$114,8,TRUE),"") -> 3687 | J59: =IF($G59=("Fall (pre/post emerge)"),"Princep Liquid (100-526)", IF($G59=("Fertilize"),"Harrell's 34-0-5",IF($G59=("Spot Treat"),"Outrider (59639-223)",""))) -> Princep Liquid (100-526) | K59: =(VLOOKUP($J59,Herbicide_Data!$A$1:$L$61,9,TRUE)) -> Simazine | L59: =VLOOKUP($J59,Herbicide_Data!$A$1:$L$61,12,TRUE) -> 32 | M59: =L59*(H59/43560) -> 2.7085399 | N59: =IF($G59=("Fall (pre/post emerge)"),"Triplet SF (3-Way) 228-312",IF($G59=("Spring Preemerge (Jan)"),"Triplet SF (3-Way) 228-312",IF($G59=("Spring Preemerge (Apr)"),"Triplet SF (3-Way) 228-312",""))) -> Triplet SF (3-Way) 228-312 | O59: =VLOOKUP($N59,Herbicide_Data!$A$1:$L$61,9) -> 2,4-D, dimethylamine salt; Dicamba, dimethylamine salt;Mecoprop-p (MCPP-p), dimethylamine salt | P59: =VLOOKUP($N59,Herbicide_Data!$A$1:$P$61,13) -> 24 | Q59: =P59*($H59/43560) -> 2.031405 | R59: =IF($G59=("Fall (pre/post emerge)"),"Resolute 4Fl (100-1139)",IF($G59=("Spring Preemerge (Jan)"),"Resolute 4Fl (100-1139)",IF($G59=("Spring Preemerge (Apr)"),"Certinty Turf 59639-226",""))) -> Resolute 4Fl (100-1139) | S59: =VLOOKUP($R59,Herbicide_Data!$A$1:$L$61,9) -> Prodiamine | T59: =VLOOKUP($R59,Herbicide_Data!$A$1:$Q$61,13) -> 16 | U59: =T59*($H59/43560) -> 1.35427 | V59: =IF($G59 = ("Preemerge"),"MSM Turf 228-373") -> FALSE | W59: =VLOOKUP($V59,Herbicide_Data!$A$1:$L$17,9) -> #N/A | X59: =VLOOKUP($V59,Herbicide_Data!$A$1:$L$17,12) -> #N/A | Y59: =X59*($H59/43560) -> #N/A | AH59: =IF($G59=("Spring Preemerge (Jan)"),"Surfactant",IF($G59=("Spring Preemerge (Apr)"),"Surfactant","")) | AI59: =VLOOKUP($AH59,Herbicide_Data!$A$1:$Q$61,13) -> #N/A | AJ59: =AI59*($H59/43560) -> #N/A
A60: Matt Runner | B60: 45802 | C60: 0.41666667 | D60: =C60+0.0208333 -> 0.43749997 | E60: Matthew Stowers | F60: =IFERROR(VLOOKUP(E60,Data!A$2:B$5,2,TRUE), "") -> 48160 | G60: Fertilize | H60: =IFERROR(VLOOKUP(A60,Customer_Data!$A$1:$P$114,8,TRUE),"") -> 2000 | J60: =IF($G60=("Fall (pre/post emerge)"),"Princep Liquid (100-526)", IF($G60=("Fertilize"),"Harrell's 34-0-5",IF($G60=("Spot Treat"),"Outrider (59639-223)",""))) -> Harrell's 34-0-5 | K60: =(VLOOKUP($J60,Herbicide_Data!$A$1:$L$61,9,TRUE)) -> Nitrogen | L60: =VLOOKUP($J60,Herbicide_Data!$A$1:$L$61,12,TRUE) -> 2.94 | M60: =L60*(H60/43560) -> 0.13498623 | N60: =IF($G60=("Fall (pre/post emerge)"),"Triplet SF (3-Way) 228-312",IF($G60=("Spring Preemerge (Jan)"),"Triplet SF (3-Way) 228-312",IF($G60=("Spring Preemerge (Apr)"),"Triplet SF (3-Way) 228-312",""))) | O60: =VLOOKUP($N60,Herbicide_Data!$A$1:$L$61,9) -> #N/A | P60: =VLOOKUP($N60,Herbicide_Data!$A$1:$P$61,13) -> #N/A | Q60: =P60*($H60/43560) -> #N/A | R60: =IF($G60=("Fall (pre/post emerge)"),"Resolute 4Fl (100-1139)",IF($G60=("Spring Preemerge (Jan)"),"Resolute 4Fl (100-1139)",IF($G60=("Spring Preemerge (Apr)"),"Certinty Turf 59639-226",""))) | S60: =VLOOKUP($R60,Herbicide_Data!$A$1:$L$61,9) -> #N/A | T60: =VLOOKUP($R60,Herbicide_Data!$A$1:$Q$61,13) -> #N/A | U60: =T60*($H60/43560) -> #N/A | V60: =IF($G60 = ("Preemerge"),"MSM Turf 228-373") -> FALSE | W60: =VLOOKUP($V60,Herbicide_Data!$A$1:$L$17,9) -> #N/A | X60: =VLOOKUP($V60,Herbicide_Data!$A$1:$L$17,12) -> #N/A | Y60: =X60*($H60/43560) -> #N/A | AH60: =IF($G60=("Spring Preemerge (Jan)"),"Surfactant",IF($G60=("Spring Preemerge (Apr)"),"Surfactant","")) | AI60: =VLOOKUP($AH60,Herbicide_Data!$A$1:$Q$61,13) -> #N/A | AJ60: =AI60*($H60/43560) -> #N/A
A61: Matt Runner | B61: 45948 | C61: =IF(ISBLANK($A61),"",NOW()-TODAY()) -> 0.63285475 | D61: =C61+0.0208333 -> 0.65368805 | E61: Matthew Stowers | F61: =IFERROR(VLOOKUP(E61,Data!A$2:B$5,2,TRUE), "") -> 48160 | G61: Fall (pre/post emerge) | H61: =IFERROR(VLOOKUP(A61,Customer_Data!$A$1:$P$114,8,TRUE),"") -> 2000 | J61: =IF($G61=("Fall (pre/post emerge)"),"Princep Liquid (100-526)", IF($G61=("Fertilize"),"Harrell's 34-0-5",IF($G61=("Spot Treat"),"Outrider (59639-223)",""))) -> Princep Liquid (100-526) | K61: =(VLOOKUP($J61,Herbicide_Data!$A$1:$L$61,9,TRUE)) -> Simazine | L61: =VLOOKUP($J61,Herbicide_Data!$A$1:$L$61,12,TRUE) -> 32 | M61: =L61*(H61/43560) -> 1.4692378 | N61: =IF($G61=("Fall (pre/post emerge)"),"Triplet SF (3-Way) 228-312",IF($G61=("Spring Preemerge (Jan)"),"Triplet SF (3-Way) 228-312",IF($G61=("Spring Preemerge (Apr)"),"Triplet SF (3-Way) 228-312",""))) -> Triplet SF (3-Way) 228-312 | O61: =VLOOKUP($N61,Herbicide_Data!$A$1:$L$61,9) -> 2,4-D, dimethylamine salt; Dicamba, dimethylamine salt;Mecoprop-p (MCPP-p), dimethylamine salt | P61: =VLOOKUP($N61,Herbicide_Data!$A$1:$P$61,13) -> 24 | Q61: =P61*($H61/43560) -> 1.1019284 | R61: =IF($G61=("Fall (pre/post emerge)"),"Resolute 4Fl (100-1139)",IF($G61=("Spring Preemerge (Jan)"),"Resolute 4Fl (100-1139)",IF($G61=("Spring Preemerge (Apr)"),"Certinty Turf 59639-226",""))) -> Resolute 4Fl (100-1139) | S61: =VLOOKUP($R61,Herbicide_Data!$A$1:$L$61,9) -> Prodiamine | T61: =VLOOKUP($R61,Herbicide_Data!$A$1:$Q$61,13) -> 16 | U61: =T61*($H61/43560) -> 0.73461892 | V61: =IF($G61 = ("Preemerge"),"MSM Turf 228-373") -> FALSE | W61: =VLOOKUP($V61,Herbicide_Data!$A$1:$L$17,9) -> #N/A | X61: =VLOOKUP($V61,Herbicide_Data!$A$1:$L$17,12) -> #N/A | Y61: =X61*($H61/43560) -> #N/A | AH61: =IF($G61=("Spring Preemerge (Jan)"),"Surfactant",IF($G61=("Spring Preemerge (Apr)"),"Surfactant","")) | AI61: =VLOOKUP($AH61,Herbicide_Data!$A$1:$Q$61,13) -> #N/A | AJ61: =AI61*($H61/43560) -> #N/A
A62: David Fatheree | B62: 45801 | C62: 0.45833333 | D62: =C62+0.0208333 -> 0.47916663 | E62: Matthew Stowers | F62: =IFERROR(VLOOKUP(E62,Data!A$2:B$5,2,TRUE), "") -> 48160 | G62: Fertilize | H62: =IFERROR(VLOOKUP(A62,Customer_Data!$A$1:$P$114,8,TRUE),"") -> 8910 | J62: =IF($G62=("Fall (pre/post emerge)"),"Princep Liquid (100-526)", IF($G62=("Fertilize"),"Harrell's 34-0-5",IF($G62=("Spot Treat"),"Outrider (59639-223)",""))) -> Harrell's 34-0-5 | K62: =(VLOOKUP($J62,Herbicide_Data!$A$1:$L$61,9,TRUE)) -> Nitrogen | L62: =VLOOKUP($J62,Herbicide_Data!$A$1:$L$61,12,TRUE) -> 2.94 | M62: =L62*(H62/43560) -> 0.60136364 | N62: =IF($G62=("Fall (pre/post emerge)"),"Triplet SF (3-Way) 228-312",IF($G62=("Spring Preemerge (Jan)"),"Triplet SF (3-Way) 228-312",IF($G62=("Spring Preemerge (Apr)"),"Triplet SF (3-Way) 228-312",""))) | O62: =VLOOKUP($N62,Herbicide_Data!$A$1:$L$61,9) -> #N/A | P62: =VLOOKUP($N62,Herbicide_Data!$A$1:$P$61,13) -> #N/A | Q62: =P62*($H62/43560) -> #N/A | R62: =IF($G62=("Fall (pre/post emerge)"),"Resolute 4Fl (100-1139)",IF($G62=("Spring Preemerge (Jan)"),"Resolute 4Fl (100-1139)",IF($G62=("Spring Preemerge (Apr)"),"Certinty Turf 59639-226",""))) | S62: =VLOOKUP($R62,Herbicide_Data!$A$1:$L$61,9) -> #N/A | T62: =VLOOKUP($R62,Herbicide_Data!$A$1:$Q$61,13) -> #N/A | U62: =T62*($H62/43560) -> #N/A | V62: =IF($G62 = ("Preemerge"),"MSM Turf 228-373") -> FALSE | W62: =VLOOKUP($V62,Herbicide_Data!$A$1:$L$17,9) -> #N/A | X62: =VLOOKUP($V62,Herbicide_Data!$A$1:$L$17,12) -> #N/A | Y62: =X62*($H62/43560) -> #N/A | AH62: =IF($G62=("Spring Preemerge (Jan)"),"Surfactant",IF($G62=("Spring Preemerge (Apr)"),"Surfactant","")) | AI62: =VLOOKUP($AH62,Herbicide_Data!$A$1:$Q$61,13) -> #N/A | AJ62: =AI62*($H62/43560) -> #N/A
A63: David Fatheree | B63: 45948 | C63: 0.375 | D63: =C63+0.0208333 -> 0.3958333 | E63: Matthew Stowers | F63: =IFERROR(VLOOKUP(E63,Data!A$2:B$5,2,TRUE), "") -> 48160 | G63: Fall (pre/post emerge) | H63: =IFERROR(VLOOKUP(A63,Customer_Data!$A$1:$P$114,8,TRUE),"") -> 8910 | J63: =IF($G63=("Fall (pre/post emerge)"),"Princep Liquid (100-526)", IF($G63=("Fertilize"),"Harrell's 34-0-5",IF($G63=("Spot Treat"),"Outrider (59639-223)",""))) -> Princep Liquid (100-526) | K63: =(VLOOKUP($J63,Herbicide_Data!$A$1:$L$61,9,TRUE)) -> Simazine | L63: =VLOOKUP($J63,Herbicide_Data!$A$1:$L$61,12,TRUE) -> 32 | M63: =L63*(H63/43560) -> 6.5454545 | N63: =IF($G63=("Fall (pre/post emerge)"),"Triplet SF (3-Way) 228-312",IF($G63=("Spring Preemerge (Jan)"),"Triplet SF (3-Way) 228-312",IF($G63=("Spring Preemerge (Apr)"),"Triplet SF (3-Way) 228-312",""))) -> Triplet SF (3-Way) 228-312 | O63: =VLOOKUP($N63,Herbicide_Data!$A$1:$L$61,9) -> 2,4-D, dimethylamine salt; Dicamba, dimethylamine salt;Mecoprop-p (MCPP-p), dimethylamine salt | P63: =VLOOKUP($N63,Herbicide_Data!$A$1:$P$61,13) -> 24 | Q63: =P63*($H63/43560) -> 4.9090909 | R63: =IF($G63=("Fall (pre/post emerge)"),"Resolute 4Fl (100-1139)",IF($G63=("Spring Preemerge (Jan)"),"Resolute 4Fl (100-1139)",IF($G63=("Spring Preemerge (Apr)"),"Certinty Turf 59639-226",""))) -> Resolute 4Fl (100-1139) | S63: =VLOOKUP($R63,Herbicide_Data!$A$1:$L$61,9) -> Prodiamine | T63: =VLOOKUP($R63,Herbicide_Data!$A$1:$Q$61,13) -> 16 | U63: =T63*($H63/43560) -> 3.2727273 | V63: =IF($G63 = ("Preemerge"),"MSM Turf 228-373") -> FALSE | W63: =VLOOKUP($V63,Herbicide_Data!$A$1:$L$17,9) -> #N/A | X63: =VLOOKUP($V63,Herbicide_Data!$A$1:$L$17,12) -> #N/A | Y63: =X63*($H63/43560) -> #N/A | AH63: =IF($G63=("Spring Preemerge (Jan)"),"Surfactant",IF($G63=("Spring Preemerge (Apr)"),"Surfactant","")) | AI63: =VLOOKUP($AH63,Herbicide_Data!$A$1:$Q$61,13) -> #N/A | AJ63: =AI63*($H63/43560) -> #N/A
A64: Bo Whatley | B64: 45801 | C64: 0.625 | D64: =C64+0.0208333 -> 0.6458333 | E64: Matthew Stowers | F64: =IFERROR(VLOOKUP(E64,Data!A$2:B$5,2,TRUE), "") -> 48160 | G64: Fertilize | H64: =IFERROR(VLOOKUP(A64,Customer_Data!$A$1:$P$114,8,TRUE),"") -> 2750 | J64: =IF($G64=("Fall (pre/post emerge)"),"Princep Liquid (100-526)", IF($G64=("Fertilize"),"Harrell's 34-0-5",IF($G64=("Spot Treat"),"Outrider (59639-223)",""))) -> Harrell's 34-0-5 | K64: =(VLOOKUP($J64,Herbicide_Data!$A$1:$L$61,9,TRUE)) -> Nitrogen | L64: =VLOOKUP($J64,Herbicide_Data!$A$1:$L$61,12,TRUE) -> 2.94 | M64: =L64*(H64/43560) -> 0.18560606 | N64: =IF($G64=("Fall (pre/post emerge)"),"Triplet SF (3-Way) 228-312",IF($G64=("Spring Preemerge (Jan)"),"Triplet SF (3-Way) 228-312",IF($G64=("Spring Preemerge (Apr)"),"Triplet SF (3-Way) 228-312",""))) | O64: =VLOOKUP($N64,Herbicide_Data!$A$1:$L$61,9) -> #N/A | P64: =VLOOKUP($N64,Herbicide_Data!$A$1:$P$61,13) -> #N/A | Q64: =P64*($H64/43560) -> #N/A | R64: =IF($G64=("Fall (pre/post emerge)"),"Resolute 4Fl (100-1139)",IF($G64=("Spring Preemerge (Jan)"),"Resolute 4Fl (100-1139)",IF($G64=("Spring Preemerge (Apr)"),"Certinty Turf 59639-226",""))) | S64: =VLOOKUP($R64,Herbicide_Data!$A$1:$L$61,9) -> #N/A | T64: =VLOOKUP($R64,Herbicide_Data!$A$1:$Q$61,13) -> #N/A | U64: =T64*($H64/43560) -> #N/A | V64: =IF($G64 = ("Preemerge"),"MSM Turf 228-373") -> FALSE | W64: =VLOOKUP($V64,Herbicide_Data!$A$1:$L$17,9) -> #N/A | X64: =VLOOKUP($V64,Herbicide_Data!$A$1:$L$17,12) -> #N/A | Y64: =X64*($H64/43560) -> #N/A | AH64: =IF($G64=("Spring Preemerge (Jan)"),"Surfactant",IF($G64=("Spring Preemerge (Apr)"),"Surfactant","")) | AI64: =VLOOKUP($AH64,Herbicide_Data!$A$1:$Q$61,13) -> #N/A | AJ64: =AI64*($H64/43560) -> #N/A
A65: Bo Whatley | B65: 45948 | C65: 0.58333333 | D65: =C65+0.0208333 -> 0.60416663 | E65: Matthew Stowers | F65: =IFERROR(VLOOKUP(E65,Data!A$2:B$5,2,TRUE), "") -> 48160 | G65: Fall (pre/post emerge) | H65: =IFERROR(VLOOKUP(A65,Customer_Data!$A$1:$P$114,8,TRUE),"") -> 2750 | J65: =IF($G65=("Fall (pre/post emerge)"),"Princep Liquid (100-526)", IF($G65=("Fertilize"),"Harrell's 34-0-5",IF($G65=("Spot Treat"),"Outrider (59639-223)",""))) -> Princep Liquid (100-526) | K65: =(VLOOKUP($J65,Herbicide_Data!$A$1:$L$61,9,TRUE)) -> Simazine | L65: =VLOOKUP($J65,Herbicide_Data!$A$1:$L$61,12,TRUE) -> 32 | M65: =L65*(H65/43560) -> 2.020202 | N65: =IF($G65=("Fall (pre/post emerge)"),"Triplet SF (3-Way) 228-312",IF($G65=("Spring Preemerge (Jan)"),"Triplet SF (3-Way) 228-312",IF($G65=("Spring Preemerge (Apr)"),"Triplet SF (3-Way) 228-312",""))) -> Triplet SF (3-Way) 228-312 | O65: =VLOOKUP($N65,Herbicide_Data!$A$1:$L$61,9) -> 2,4-D, dimethylamine salt; Dicamba, dimethylamine salt;Mecoprop-p (MCPP-p), dimethylamine salt | P65: =VLOOKUP($N65,Herbicide_Data!$A$1:$P$61,13) -> 24 | Q65: =P65*($H65/43560) -> 1.5151515 | R65: =IF($G65=("Fall (pre/post emerge)"),"Resolute 4Fl (100-1139)",IF($G65=("Spring Preemerge (Jan)"),"Resolute 4Fl (100-1139)",IF($G65=("Spring Preemerge (Apr)"),"Certinty Turf 59639-226",""))) -> Resolute 4Fl (100-1139) | S65: =VLOOKUP($R65,Herbicide_Data!$A$1:$L$61,9) -> Prodiamine | T65: =VLOOKUP($R65,Herbicide_Data!$A$1:$Q$61,13) -> 16 | U65: =T65*($H65/43560) -> 1.010101 | V65: =IF($G65 = ("Preemerge"),"MSM Turf 228-373") -> FALSE | W65: =VLOOKUP($V65,Herbicide_Data!$A$1:$L$17,9) -> #N/A | X65: =VLOOKUP($V65,Herbicide_Data!$A$1:$L$17,12) -> #N/A | Y65: =X65*($H65/43560) -> #N/A | AH65: =IF($G65=("Spring Preemerge (Jan)"),"Surfactant",IF($G65=("Spring Preemerge (Apr)"),"Surfactant","")) | AI65: =VLOOKUP($AH65,Herbicide_Data!$A$1:$Q$61,13) -> #N/A | AJ65: =AI65*($H65/43560) -> #N/A
A66: Riley Bennett | B66: 45802 | C66: 0.41666667 | D66: =C66+0.0208333 -> 0.43749997 | E66: Matthew Stowers | F66: =IFERROR(VLOOKUP(E66,Data!A$2:B$5,2,TRUE), "") -> 48160 | G66: Fertilize | H66: =IFERROR(VLOOKUP(A66,Customer_Data!$A$1:$P$114,8,TRUE),"") -> 7500 | J66: =IF($G66=("Fall (pre/post emerge)"),"Princep Liquid (100-526)", IF($G66=("Fertilize"),"Harrell's 34-0-5",IF($G66=("Spot Treat"),"Outrider (59639-223)",""))) -> Harrell's 34-0-5 | K66: =(VLOOKUP($J66,Herbicide_Data!$A$1:$L$61,9,TRUE)) -> Nitrogen | L66: =VLOOKUP($J66,Herbicide_Data!$A$1:$L$61,12,TRUE) -> 2.94 | M66: =L66*(H66/43560) -> 0.50619835 | N66: =IF($G66=("Fall (pre/post emerge)"),"Triplet SF (3-Way) 228-312",IF($G66=("Spring Preemerge (Jan)"),"Triplet SF (3-Way) 228-312",IF($G66=("Spring Preemerge (Apr)"),"Triplet SF (3-Way) 228-312",""))) | O66: =VLOOKUP($N66,Herbicide_Data!$A$1:$L$61,9) -> #N/A | P66: =VLOOKUP($N66,Herbicide_Data!$A$1:$P$61,13) -> #N/A | Q66: =P66*($H66/43560) -> #N/A | R66: =IF($G66=("Fall (pre/post emerge)"),"Resolute 4Fl (100-1139)",IF($G66=("Spring Preemerge (Jan)"),"Resolute 4Fl (100-1139)",IF($G66=("Spring Preemerge (Apr)"),"Certinty Turf 59639-226",""))) | S66: =VLOOKUP($R66,Herbicide_Data!$A$1:$L$61,9) -> #N/A | T66: =VLOOKUP($R66,Herbicide_Data!$A$1:$Q$61,13) -> #N/A | U66: =T66*($H66/43560) -> #N/A | V66: =IF($G66 = ("Preemerge"),"MSM Turf 228-373") -> FALSE | W66: =VLOOKUP($V66,Herbicide_Data!$A$1:$L$17,9) -> #N/A | X66: =VLOOKUP($V66,Herbicide_Data!$A$1:$L$17,12) -> #N/A | Y66: =X66*($H66/43560) -> #N/A | AH66: =IF($G66=("Spring Preemerge (Jan)"),"Surfactant",IF($G66=("Spring Preemerge (Apr)"),"Surfactant","")) | AI66: =VLOOKUP($AH66,Herbicide_Data!$A$1:$Q$61,13) -> #N/A | AJ66: =AI66*($H66/43560) -> #N/A
A67: Riley Bennett | B67: 45948 | C67: 0.58333333 | D67: =C67+0.0208333 -> 0.60416663 | E67: Luther Stowers | F67: =IFERROR(VLOOKUP(E67,Data!A$2:B$5,2,TRUE), "") -> 48182 | G67: Fall (pre/post emerge) | H67: =IFERROR(VLOOKUP(A67,Customer_Data!$A$1:$P$114,8,TRUE),"") -> 7500 | J67: =IF($G67=("Fall (pre/post emerge)"),"Princep Liquid (100-526)", IF($G67=("Fertilize"),"Harrell's 34-0-5",IF($G67=("Spot Treat"),"Outrider (59639-223)",""))) -> Princep Liquid (100-526) | K67: =(VLOOKUP($J67,Herbicide_Data!$A$1:$L$61,9,TRUE)) -> Simazine | L67: =VLOOKUP($J67,Herbicide_Data!$A$1:$L$61,12,TRUE) -> 32 | M67: =L67*(H67/43560) -> 5.5096419 | N67: =IF($G67=("Fall (pre/post emerge)"),"Triplet SF (3-Way) 228-312",IF($G67=("Spring Preemerge (Jan)"),"Triplet SF (3-Way) 228-312",IF($G67=("Spring Preemerge (Apr)"),"Triplet SF (3-Way) 228-312",""))) -> Triplet SF (3-Way) 228-312 | O67: =VLOOKUP($N67,Herbicide_Data!$A$1:$L$61,9) -> 2,4-D, dimethylamine salt; Dicamba, dimethylamine salt;Mecoprop-p (MCPP-p), dimethylamine salt | P67: =VLOOKUP($N67,Herbicide_Data!$A$1:$P$61,13) -> 24 | Q67: =P67*($H67/43560) -> 4.1322314 | R67: =IF($G67=("Fall (pre/post emerge)"),"Resolute 4Fl (100-1139)",IF($G67=("Spring Preemerge (Jan)"),"Resolute 4Fl (100-1139)",IF($G67=("Spring Preemerge (Apr)"),"Certinty Turf 59639-226",""))) -> Resolute 4Fl (100-1139) | S67: =VLOOKUP($R67,Herbicide_Data!$A$1:$L$61,9) -> Prodiamine | T67: =VLOOKUP($R67,Herbicide_Data!$A$1:$Q$61,13) -> 16 | U67: =T67*($H67/43560) -> 2.7548209 | V67: =IF($G67 = ("Preemerge"),"MSM Turf 228-373") -> FALSE | W67: =VLOOKUP($V67,Herbicide_Data!$A$1:$L$17,9) -> #N/A | X67: =VLOOKUP($V67,Herbicide_Data!$A$1:$L$17,12) -> #N/A | Y67: =X67*($H67/43560) -> #N/A | AH67: =IF($G67=("Spring Preemerge (Jan)"),"Surfactant",IF($G67=("Spring Preemerge (Apr)"),"Surfactant","")) | AI67: =VLOOKUP($AH67,Herbicide_Data!$A$1:$Q$61,13) -> #N/A | AJ67: =AI67*($H67/43560) -> #N/A
A68: Max Brian | B68: 45802 | C68: 0.45833333 | D68: =C68+0.0208333 -> 0.47916663 | E68: Matthew Stowers | F68: =IFERROR(VLOOKUP(E68,Data!A$2:B$5,2,TRUE), "") -> 48160 | G68: Fertilize | H68: =IFERROR(VLOOKUP(A68,Customer_Data!$A$1:$P$114,8,TRUE),"") -> 4670 | J68: =IF($G68=("Fall (pre/post emerge)"),"Princep Liquid (100-526)", IF($G68=("Fertilize"),"Harrell's 34-0-5",IF($G68=("Spot Treat"),"Outrider (59639-223)",""))) -> Harrell's 34-0-5 | K68: =(VLOOKUP($J68,Herbicide_Data!$A$1:$L$61,9,TRUE)) -> Nitrogen | L68: =VLOOKUP($J68,Herbicide_Data!$A$1:$L$61,12,TRUE) -> 2.94 | M68: =L68*(H68/43560) -> 0.31519284 | N68: =IF($G68=("Fall (pre/post emerge)"),"Triplet SF (3-Way) 228-312",IF($G68=("Spring Preemerge (Jan)"),"Triplet SF (3-Way) 228-312",IF($G68=("Spring Preemerge (Apr)"),"Triplet SF (3-Way) 228-312",""))) | O68: =VLOOKUP($N68,Herbicide_Data!$A$1:$L$61,9) -> #N/A | P68: =VLOOKUP($N68,Herbicide_Data!$A$1:$P$61,13) -> #N/A | Q68: =P68*($H68/43560) -> #N/A | R68: =IF($G68=("Fall (pre/post emerge)"),"Resolute 4Fl (100-1139)",IF($G68=("Spring Preemerge (Jan)"),"Resolute 4Fl (100-1139)",IF($G68=("Spring Preemerge (Apr)"),"Certinty Turf 59639-226",""))) | S68: =VLOOKUP($R68,Herbicide_Data!$A$1:$L$61,9) -> #N/A | T68: =VLOOKUP($R68,Herbicide_Data!$A$1:$Q$61,13) -> #N/A | U68: =T68*($H68/43560) -> #N/A | V68: =IF($G68 = ("Preemerge"),"MSM Turf 228-373") -> FALSE | W68: =VLOOKUP($V68,Herbicide_Data!$A$1:$L$17,9) -> #N/A | X68: =VLOOKUP($V68,Herbicide_Data!$A$1:$L$17,12) -> #N/A | Y68: =X68*($H68/43560) -> #N/A | AH68: =IF($G68=("Spring Preemerge (Jan)"),"Surfactant",IF($G68=("Spring Preemerge (Apr)"),"Surfactant","")) | AI68: =VLOOKUP($AH68,Herbicide_Data!$A$1:$Q$61,13) -> #N/A | AJ68: =AI68*($H68/43560) -> #N/A
A69: Max Brian | B69: 45948 | C69: =IF(ISBLANK($A69),"",NOW()-TODAY()) -> 0.63285475 | D69: =C69+0.0208333 -> 0.65368805 | E69: Matthew Stowers | F69: =IFERROR(VLOOKUP(E69,Data!A$2:B$5,2,TRUE), "") -> 48160 | G69: Fall (pre/post emerge) | H69: =IFERROR(VLOOKUP(A69,Customer_Data!$A$1:$P$114,8,TRUE),"") -> 4670 | J69: =IF($G69=("Fall (pre/post emerge)"),"Princep Liquid (100-526)", IF($G69=("Fertilize"),"Harrell's 34-0-5",IF($G69=("Spot Treat"),"Outrider (59639-223)",""))) -> Princep Liquid (100-526) | K69: =(VLOOKUP($J69,Herbicide_Data!$A$1:$L$61,9,TRUE)) -> Simazine | L69: =VLOOKUP($J69,Herbicide_Data!$A$1:$L$61,12,TRUE) -> 32 | M69: =L69*(H69/43560) -> 3.4306703 | N69: =IF($G69=("Fall (pre/post emerge)"),"Triplet SF (3-Way) 228-312",IF($G69=("Spring Preemerge (Jan)"),"Triplet SF (3-Way) 228-312",IF($G69=("Spring Preemerge (Apr)"),"Triplet SF (3-Way) 228-312",""))) -> Triplet SF (3-Way) 228-312 | O69: =VLOOKUP($N69,Herbicide_Data!$A$1:$L$61,9) -> 2,4-D, dimethylamine salt; Dicamba, dimethylamine salt;Mecoprop-p (MCPP-p), dimethylamine salt | P69: =VLOOKUP($N69,Herbicide_Data!$A$1:$P$61,13) -> 24 | Q69: =P69*($H69/43560) -> 2.5730028 | R69: =IF($G69=("Fall (pre/post emerge)"),"Resolute 4Fl (100-1139)",IF($G69=("Spring Preemerge (Jan)"),"Resolute 4Fl (100-1139)",IF($G69=("Spring Preemerge (Apr)"),"Certinty Turf 59639-226",""))) -> Resolute 4Fl (100-1139) | S69: =VLOOKUP($R69,Herbicide_Data!$A$1:$L$61,9) -> Prodiamine | T69: =VLOOKUP($R69,Herbicide_Data!$A$1:$Q$61,13) -> 16 | U69: =T69*($H69/43560) -> 1.7153352 | V69: =IF($G69 = ("Preemerge"),"MSM Turf 228-373") -> FALSE | W69: =VLOOKUP($V69,Herbicide_Data!$A$1:$L$17,9) -> #N/A | X69: =VLOOKUP($V69,Herbicide_Data!$A$1:$L$17,12) -> #N/A | Y69: =X69*($H69/43560) -> #N/A | AH69: =IF($G69=("Spring Preemerge (Jan)"),"Surfactant",IF($G69=("Spring Preemerge (Apr)"),"Surfactant","")) | AI69: =VLOOKUP($AH69,Herbicide_Data!$A$1:$Q$61,13) -> #N/A | AJ69: =AI69*($H69/43560) -> #N/A
A70: Brandon Bergold | B70: 45801 | C70: =IF(ISBLANK($A70),"",NOW()-TODAY()) -> 0.63285475 | D70: =C70+0.0208333 -> 0.65368805 | E70: Matthew Stowers | F70: =IFERROR(VLOOKUP(E70,Data!A$2:B$5,2,TRUE), "") -> 48160 | G70: Fertilize | H70: =IFERROR(VLOOKUP(A70,Customer_Data!$A$1:$P$114,8,TRUE),"") -> 5670 | J70: =IF($G70=("Fall (pre/post emerge)"),"Princep Liquid (100-526)", IF($G70=("Fertilize"),"Harrell's 34-0-5",IF($G70=("Spot Treat"),"Outrider (59639-223)",""))) -> Harrell's 34-0-5 | K70: =(VLOOKUP($J70,Herbicide_Data!$A$1:$L$61,9,TRUE)) -> Nitrogen | L70: =VLOOKUP($J70,Herbicide_Data!$A$1:$L$61,12,TRUE) -> 2.94 | M70: =L70*(H70/43560) -> 0.38268595 | N70: =IF($G70=("Fall (pre/post emerge)"),"Triplet SF (3-Way) 228-312",IF($G70=("Spring Preemerge (Jan)"),"Triplet SF (3-Way) 228-312",IF($G70=("Spring Preemerge (Apr)"),"Triplet SF (3-Way) 228-312",""))) | O70: =VLOOKUP($N70,Herbicide_Data!$A$1:$L$61,9) -> #N/A | P70: =VLOOKUP($N70,Herbicide_Data!$A$1:$P$61,13) -> #N/A | Q70: =P70*($H70/43560) -> #N/A | R70: =IF($G70=("Fall (pre/post emerge)"),"Resolute 4Fl (100-1139)",IF($G70=("Spring Preemerge (Jan)"),"Resolute 4Fl (100-1139)",IF($G70=("Spring Preemerge (Apr)"),"Certinty Turf 59639-226",""))) | S70: =VLOOKUP($R70,Herbicide_Data!$A$1:$L$61,9) -> #N/A | T70: =VLOOKUP($R70,Herbicide_Data!$A$1:$Q$61,13) -> #N/A | U70: =T70*($H70/43560) -> #N/A | V70: =IF($G70 = ("Preemerge"),"MSM Turf 228-373") -> FALSE | W70: =VLOOKUP($V70,Herbicide_Data!$A$1:$L$17,9) -> #N/A | X70: =VLOOKUP($V70,Herbicide_Data!$A$1:$L$17,12) -> #N/A | Y70: =X70*($H70/43560) -> #N/A | AH70: =IF($G70=("Spring Preemerge (Jan)"),"Surfactant",IF($G70=("Spring Preemerge (Apr)"),"Surfactant","")) | AI70: =VLOOKUP($AH70,Herbicide_Data!$A$1:$Q$61,13) -> #N/A | AJ70: =AI70*($H70/43560) -> #N/A
A71: Brandon Bergold | B71: 45948 | C71: =IF(ISBLANK($A71),"",NOW()-TODAY()) -> 0.63285475 | D71: =C71+0.0208333 -> 0.65368805 | E71: Matthew Stowers | F71: =IFERROR(VLOOKUP(E71,Data!A$2:B$5,2,TRUE), "") -> 48160 | G71: Fall (pre/post emerge) | H71: =IFERROR(VLOOKUP(A71,Customer_Data!$A$1:$P$114,8,TRUE),"") -> 5670 | J71: =IF($G71=("Fall (pre/post emerge)"),"Princep Liquid (100-526)", IF($G71=("Fertilize"),"Harrell's 34-0-5",IF($G71=("Spot Treat"),"Outrider (59639-223)",""))) -> Princep Liquid (100-526) | K71: =(VLOOKUP($J71,Herbicide_Data!$A$1:$L$61,9,TRUE)) -> Simazine | L71: =VLOOKUP($J71,Herbicide_Data!$A$1:$L$61,12,TRUE) -> 32 | M71: =L71*(H71/43560) -> 4.1652893 | N71: =IF($G71=("Fall (pre/post emerge)"),"Triplet SF (3-Way) 228-312",IF($G71=("Spring Preemerge (Jan)"),"Triplet SF (3-Way) 228-312",IF($G71=("Spring Preemerge (Apr)"),"Triplet SF (3-Way) 228-312",""))) -> Triplet SF (3-Way) 228-312 | O71: =VLOOKUP($N71,Herbicide_Data!$A$1:$L$61,9) -> 2,4-D, dimethylamine salt; Dicamba, dimethylamine salt;Mecoprop-p (MCPP-p), dimethylamine salt | P71: =VLOOKUP($N71,Herbicide_Data!$A$1:$P$61,13) -> 24 | Q71: =P71*($H71/43560) -> 3.1239669 | R71: =IF($G71=("Fall (pre/post emerge)"),"Resolute 4Fl (100-1139)",IF($G71=("Spring Preemerge (Jan)"),"Resolute 4Fl (100-1139)",IF($G71=("Spring Preemerge (Apr)"),"Certinty Turf 59639-226",""))) -> Resolute 4Fl (100-1139) | S71: =VLOOKUP($R71,Herbicide_Data!$A$1:$L$61,9) -> Prodiamine | T71: =VLOOKUP($R71,Herbicide_Data!$A$1:$Q$61,13) -> 16 | U71: =T71*($H71/43560) -> 2.0826446 | V71: =IF($G71 = ("Preemerge"),"MSM Turf 228-373") -> FALSE | W71: =VLOOKUP($V71,Herbicide_Data!$A$1:$L$17,9) -> #N/A | X71: =VLOOKUP($V71,Herbicide_Data!$A$1:$L$17,12) -> #N/A | Y71: =X71*($H71/43560) -> #N/A | AH71: =IF($G71=("Spring Preemerge (Jan)"),"Surfactant",IF($G71=("Spring Preemerge (Apr)"),"Surfactant","")) | AI71: =VLOOKUP($AH71,Herbicide_Data!$A$1:$Q$61,13) -> #N/A | AJ71: =AI71*($H71/43560) -> #N/A
A72: Riley Cooper | B72: 45801 | C72: =IF(ISBLANK($A72),"",NOW()-TODAY()) -> 0.63285475 | D72: =C72+0.0208333 -> 0.65368805 | E72: Matthew Stowers | F72: =IFERROR(VLOOKUP(E72,Data!A$2:B$5,2,TRUE), "") -> 48160 | G72: Fertilize | H72: =IFERROR(VLOOKUP(A72,Customer_Data!$A$1:$P$114,8,TRUE),"") -> 4150 | J72: =IF($G72=("Fall (pre/post emerge)"),"Princep Liquid (100-526)", IF($G72=("Fertilize"),"Harrell's 34-0-5",IF($G72=("Spot Treat"),"Outrider (59639-223)",""))) -> Harrell's 34-0-5 | K72: =(VLOOKUP($J72,Herbicide_Data!$A$1:$L$61,9,TRUE)) -> Nitrogen | L72: =VLOOKUP($J72,Herbicide_Data!$A$1:$L$61,12,TRUE) -> 2.94 | M72: =L72*(H72/43560) -> 0.28009642 | N72: =IF($G72=("Fall (pre/post emerge)"),"Triplet SF (3-Way) 228-312",IF($G72=("Spring Preemerge (Jan)"),"Triplet SF (3-Way) 228-312",IF($G72=("Spring Preemerge (Apr)"),"Triplet SF (3-Way) 228-312",""))) | O72: =VLOOKUP($N72,Herbicide_Data!$A$1:$L$61,9) -> #N/A | P72: =VLOOKUP($N72,Herbicide_Data!$A$1:$P$61,13) -> #N/A | Q72: =P72*($H72/43560) -> #N/A | R72: =IF($G72=("Fall (pre/post emerge)"),"Resolute 4Fl (100-1139)",IF($G72=("Spring Preemerge (Jan)"),"Resolute 4Fl (100-1139)",IF($G72=("Spring Preemerge (Apr)"),"Certinty Turf 59639-226",""))) | S72: =VLOOKUP($R72,Herbicide_Data!$A$1:$L$61,9) -> #N/A | T72: =VLOOKUP($R72,Herbicide_Data!$A$1:$Q$61,13) -> #N/A | U72: =T72*($H72/43560) -> #N/A | V72: =IF($G72 = ("Preemerge"),"MSM Turf 228-373") -> FALSE | W72: =VLOOKUP($V72,Herbicide_Data!$A$1:$L$17,9) -> #N/A | X72: =VLOOKUP($V72,Herbicide_Data!$A$1:$L$17,12) -> #N/A | Y72: =X72*($H72/43560) -> #N/A | AH72: =IF($G72=("Spring Preemerge (Jan)"),"Surfactant",IF($G72=("Spring Preemerge (Apr)"),"Surfactant","")) | AI72: =VLOOKUP($AH72,Herbicide_Data!$A$1:$Q$61,13) -> #N/A | AJ72: =AI72*($H72/43560) -> #N/A
A73: Riley Cooper | B73: 45952 | C73: =IF(ISBLANK($A73),"",NOW()-TODAY()) -> 0.63285475 | D73: =C73+0.0208333 -> 0.65368805 | E73: Matthew Stowers | F73: =IFERROR(VLOOKUP(E73,Data!A$2:B$5,2,TRUE), "") -> 48160 | G73: Fall (pre/post emerge) | H73: =IFERROR(VLOOKUP(A73,Customer_Data!$A$1:$P$114,8,TRUE),"") -> 4150 | J73: =IF($G73=("Fall (pre/post emerge)"),"Princep Liquid (100-526)", IF($G73=("Fertilize"),"Harrell's 34-0-5",IF($G73=("Spot Treat"),"Outrider (59639-223)",""))) -> Princep Liquid (100-526) | K73: =(VLOOKUP($J73,Herbicide_Data!$A$1:$L$61,9,TRUE)) -> Simazine | L73: =VLOOKUP($J73,Herbicide_Data!$A$1:$L$61,12,TRUE) -> 32 | M73: =L73*(H73/43560) -> 3.0486685 | N73: =IF($G73=("Fall (pre/post emerge)"),"Triplet SF (3-Way) 228-312",IF($G73=("Spring Preemerge (Jan)"),"Triplet SF (3-Way) 228-312",IF($G73=("Spring Preemerge (Apr)"),"Triplet SF (3-Way) 228-312",""))) -> Triplet SF (3-Way) 228-312 | O73: =VLOOKUP($N73,Herbicide_Data!$A$1:$L$61,9) -> 2,4-D, dimethylamine salt; Dicamba, dimethylamine salt;Mecoprop-p (MCPP-p), dimethylamine salt | P73: =VLOOKUP($N73,Herbicide_Data!$A$1:$P$61,13) -> 24 | Q73: =P73*($H73/43560) -> 2.2865014 | R73: =IF($G73=("Fall (pre/post emerge)"),"Resolute 4Fl (100-1139)",IF($G73=("Spring Preemerge (Jan)"),"Resolute 4Fl (100-1139)",IF($G73=("Spring Preemerge (Apr)"),"Certinty Turf 59639-226",""))) -> Resolute 4Fl (100-1139) | S73: =VLOOKUP($R73,Herbicide_Data!$A$1:$L$61,9) -> Prodiamine | T73: =VLOOKUP($R73,Herbicide_Data!$A$1:$Q$61,13) -> 16 | U73: =T73*($H73/43560) -> 1.5243343 | V73: =IF($G73 = ("Preemerge"),"MSM Turf 228-373") -> FALSE | W73: =VLOOKUP($V73,Herbicide_Data!$A$1:$L$17,9) -> #N/A | X73: =VLOOKUP($V73,Herbicide_Data!$A$1:$L$17,12) -> #N/A | Y73: =X73*($H73/43560) -> #N/A | AH73: =IF($G73=("Spring Preemerge (Jan)"),"Surfactant",IF($G73=("Spring Preemerge (Apr)"),"Surfactant","")) | AI73: =VLOOKUP($AH73,Herbicide_Data!$A$1:$Q$61,13) -> #N/A | AJ73: =AI73*($H73/43560) -> #N/A
A74: Thomas Wilson | B74: 45801 | C74: =IF(ISBLANK($A74),"",NOW()-TODAY()) -> 0.63285475 | D74: =C74+0.0208333 -> 0.65368805 | E74: Matthew Stowers | F74: =IFERROR(VLOOKUP(E74,Data!A$2:B$5,2,TRUE), "") -> 48160 | G74: Fertilize | H74: =IFERROR(VLOOKUP(A74,Customer_Data!$A$1:$P$114,8,TRUE),"") -> 3875 | J74: =IF($G74=("Fall (pre/post emerge)"),"Princep Liquid (100-526)", IF($G74=("Fertilize"),"Harrell's 34-0-5",IF($G74=("Spot Treat"),"Outrider (59639-223)",""))) -> Harrell's 34-0-5 | K74: =(VLOOKUP($J74,Herbicide_Data!$A$1:$L$61,9,TRUE)) -> Nitrogen | L74: =VLOOKUP($J74,Herbicide_Data!$A$1:$L$61,12,TRUE) -> 2.94 | M74: =L74*(H74/43560) -> 0.26153581 | N74: =IF($G74=("Fall (pre/post emerge)"),"Triplet SF (3-Way) 228-312",IF($G74=("Spring Preemerge (Jan)"),"Triplet SF (3-Way) 228-312",IF($G74=("Spring Preemerge (Apr)"),"Triplet SF (3-Way) 228-312",""))) | O74: =VLOOKUP($N74,Herbicide_Data!$A$1:$L$61,9) -> #N/A | P74: =VLOOKUP($N74,Herbicide_Data!$A$1:$P$61,13) -> #N/A | Q74: =P74*($H74/43560) -> #N/A | R74: =IF($G74=("Fall (pre/post emerge)"),"Resolute 4Fl (100-1139)",IF($G74=("Spring Preemerge (Jan)"),"Resolute 4Fl (100-1139)",IF($G74=("Spring Preemerge (Apr)"),"Certinty Turf 59639-226",""))) | S74: =VLOOKUP($R74,Herbicide_Data!$A$1:$L$61,9) -> #N/A | T74: =VLOOKUP($R74,Herbicide_Data!$A$1:$Q$61,13) -> #N/A | U74: =T74*($H74/43560) -> #N/A | V74: =IF($G74 = ("Preemerge"),"MSM Turf 228-373") -> FALSE | W74: =VLOOKUP($V74,Herbicide_Data!$A$1:$L$17,9) -> #N/A | X74: =VLOOKUP($V74,Herbicide_Data!$A$1:$L$17,12) -> #N/A | Y74: =X74*($H74/43560) -> #N/A | AH74: =IF($G74=("Spring Preemerge (Jan)"),"Surfactant",IF($G74=("Spring Preemerge (Apr)"),"Surfactant","")) | AI74: =VLOOKUP($AH74,Herbicide_Data!$A$1:$Q$61,13) -> #N/A | AJ74: =AI74*($H74/43560) -> #N/A
A75: Thomas Wilson | B75: 45948 | C75: =IF(ISBLANK($A75),"",NOW()-TODAY()) -> 0.63285475 | D75: =C75+0.0208333 -> 0.65368805 | E75: Matthew Stowers | F75: =IFERROR(VLOOKUP(E75,Data!A$2:B$5,2,TRUE), "") -> 48160 | G75: Fall (pre/post emerge) | H75: =IFERROR(VLOOKUP(A75,Customer_Data!$A$1:$P$114,8,TRUE),"") -> 3875 | J75: =IF($G75=("Fall (pre/post emerge)"),"Princep Liquid (100-526)", IF($G75=("Fertilize"),"Harrell's 34-0-5",IF($G75=("Spot Treat"),"Outrider (59639-223)",""))) -> Princep Liquid (100-526) | K75: =(VLOOKUP($J75,Herbicide_Data!$A$1:$L$61,9,TRUE)) -> Simazine | L75: =VLOOKUP($J75,Herbicide_Data!$A$1:$L$61,12,TRUE) -> 32 | M75: =L75*(H75/43560) -> 2.8466483 | N75: =IF($G75=("Fall (pre/post emerge)"),"Triplet SF (3-Way) 228-312",IF($G75=("Spring Preemerge (Jan)"),"Triplet SF (3-Way) 228-312",IF($G75=("Spring Preemerge (Apr)"),"Triplet SF (3-Way) 228-312",""))) -> Triplet SF (3-Way) 228-312 | O75: =VLOOKUP($N75,Herbicide_Data!$A$1:$L$61,9) -> 2,4-D, dimethylamine salt; Dicamba, dimethylamine salt;Mecoprop-p (MCPP-p), dimethylamine salt | P75: =VLOOKUP($N75,Herbicide_Data!$A$1:$P$61,13) -> 24 | Q75: =P75*($H75/43560) -> 2.1349862 | R75: =IF($G75=("Fall (pre/post emerge)"),"Resolute 4Fl (100-1139)",IF($G75=("Spring Preemerge (Jan)"),"Resolute 4Fl (100-1139)",IF($G75=("Spring Preemerge (Apr)"),"Certinty Turf 59639-226",""))) -> Resolute 4Fl (100-1139) | S75: =VLOOKUP($R75,Herbicide_Data!$A$1:$L$61,9) -> Prodiamine | T75: =VLOOKUP($R75,Herbicide_Data!$A$1:$Q$61,13) -> 16 | U75: =T75*($H75/43560) -> 1.4233242 | V75: =IF($G75 = ("Preemerge"),"MSM Turf 228-373") -> FALSE | W75: =VLOOKUP($V75,Herbicide_Data!$A$1:$L$17,9) -> #N/A | X75: =VLOOKUP($V75,Herbicide_Data!$A$1:$L$17,12) -> #N/A | Y75: =X75*($H75/43560) -> #N/A | AH75: =IF($G75=("Spring Preemerge (Jan)"),"Surfactant",IF($G75=("Spring Preemerge (Apr)"),"Surfactant","")) | AI75: =VLOOKUP($AH75,Herbicide_Data!$A$1:$Q$61,13) -> #N/A | AJ75: =AI75*($H75/43560) -> #N/A
A76: Elliot Smith | B76: 45802 | C76: =IF(ISBLANK($A76),"",NOW()-TODAY()) -> 0.63285475 | D76: =C76+0.0208333 -> 0.65368805 | E76: Matthew Stowers | F76: =IFERROR(VLOOKUP(E76,Data!A$2:B$5,2,TRUE), "") -> 48160 | G76: Fertilize | H76: =IFERROR(VLOOKUP(A76,Customer_Data!$A$1:$P$114,8,TRUE),"") -> 13500 | J76: =IF($G76=("Fall (pre/post emerge)"),"Princep Liquid (100-526)", IF($G76=("Fertilize"),"Harrell's 34-0-5",IF($G76=("Spot Treat"),"Outrider (59639-223)",""))) -> Harrell's 34-0-5 | K76: =(VLOOKUP($J76,Herbicide_Data!$A$1:$L$61,9,TRUE)) -> Nitrogen | L76: =VLOOKUP($J76,Herbicide_Data!$A$1:$L$61,12,TRUE) -> 2.94 | M76: =L76*(H76/43560) -> 0.91115702 | N76: =IF($G76=("Fall (pre/post emerge)"),"Triplet SF (3-Way) 228-312",IF($G76=("Spring Preemerge (Jan)"),"Triplet SF (3-Way) 228-312",IF($G76=("Spring Preemerge (Apr)"),"Triplet SF (3-Way) 228-312",""))) | O76: =VLOOKUP($N76,Herbicide_Data!$A$1:$L$61,9) -> #N/A | P76: =VLOOKUP($N76,Herbicide_Data!$A$1:$P$61,13) -> #N/A | Q76: =P76*($H76/43560) -> #N/A | R76: =IF($G76=("Fall (pre/post emerge)"),"Resolute 4Fl (100-1139)",IF($G76=("Spring Preemerge (Jan)"),"Resolute 4Fl (100-1139)",IF($G76=("Spring Preemerge (Apr)"),"Certinty Turf 59639-226",""))) | S76: =VLOOKUP($R76,Herbicide_Data!$A$1:$L$61,9) -> #N/A | T76: =VLOOKUP($R76,Herbicide_Data!$A$1:$Q$61,13) -> #N/A | U76: =T76*($H76/43560) -> #N/A | V76: =IF($G76 = ("Preemerge"),"MSM Turf 228-373") -> FALSE | W76: =VLOOKUP($V76,Herbicide_Data!$A$1:$L$17,9) -> #N/A | X76: =VLOOKUP($V76,Herbicide_Data!$A$1:$L$17,12) -> #N/A | Y76: =X76*($H76/43560) -> #N/A | AH76: =IF($G76=("Spring Preemerge (Jan)"),"Surfactant",IF($G76=("Spring Preemerge (Apr)"),"Surfactant","")) | AI76: =VLOOKUP($AH76,Herbicide_Data!$A$1:$Q$61,13) -> #N/A | AJ76: =AI76*($H76/43560) -> #N/A
A77: Elliot Smith | B77: 45950 | C77: =IF(ISBLANK($A77),"",NOW()-TODAY()) -> 0.63285475 | D77: =C77+0.0208333 -> 0.65368805 | E77: Matthew Stowers | F77: =IFERROR(VLOOKUP(E77,Data!A$2:B$5,2,TRUE), "") -> 48160 | G77: Fall (pre/post emerge) | H77: =IFERROR(VLOOKUP(A77,Customer_Data!$A$1:$P$114,8,TRUE),"") -> 13500 | J77: =IF($G77=("Fall (pre/post emerge)"),"Princep Liquid (100-526)", IF($G77=("Fertilize"),"Harrell's 34-0-5",IF($G77=("Spot Treat"),"Outrider (59639-223)",""))) -> Princep Liquid (100-526) | K77: =(VLOOKUP($J77,Herbicide_Data!$A$1:$L$61,9,TRUE)) -> Simazine | L77: =VLOOKUP($J77,Herbicide_Data!$A$1:$L$61,12,TRUE) -> 32 | M77: =L77*(H77/43560) -> 9.9173554 | N77: =IF($G77=("Fall (pre/post emerge)"),"Triplet SF (3-Way) 228-312",IF($G77=("Spring Preemerge (Jan)"),"Triplet SF (3-Way) 228-312",IF($G77=("Spring Preemerge (Apr)"),"Triplet SF (3-Way) 228-312",""))) -> Triplet SF (3-Way) 228-312 | O77: =VLOOKUP($N77,Herbicide_Data!$A$1:$L$61,9) -> 2,4-D, dimethylamine salt; Dicamba, dimethylamine salt;Mecoprop-p (MCPP-p), dimethylamine salt | P77: =VLOOKUP($N77,Herbicide_Data!$A$1:$P$61,13) -> 24 | Q77: =P77*($H77/43560) -> 7.4380165 | R77: =IF($G77=("Fall (pre/post emerge)"),"Resolute 4Fl (100-1139)",IF($G77=("Spring Preemerge (Jan)"),"Resolute 4Fl (100-1139)",IF($G77=("Spring Preemerge (Apr)"),"Certinty Turf 59639-226",""))) -> Resolute 4Fl (100-1139) | S77: =VLOOKUP($R77,Herbicide_Data!$A$1:$L$61,9) -> Prodiamine | T77: =VLOOKUP($R77,Herbicide_Data!$A$1:$Q$61,13) -> 16 | U77: =T77*($H77/43560) -> 4.9586777 | V77: =IF($G77 = ("Preemerge"),"MSM Turf 228-373") -> FALSE | W77: =VLOOKUP($V77,Herbicide_Data!$A$1:$L$17,9) -> #N/A | X77: =VLOOKUP($V77,Herbicide_Data!$A$1:$L$17,12) -> #N/A | Y77: =X77*($H77/43560) -> #N/A | AH77: =IF($G77=("Spring Preemerge (Jan)"),"Surfactant",IF($G77=("Spring Preemerge (Apr)"),"Surfactant","")) | AI77: =VLOOKUP($AH77,Herbicide_Data!$A$1:$Q$61,13) -> #N/A | AJ77: =AI77*($H77/43560) -> #N/A
A78: Danny Cooper | B78: 45801 | C78: =IF(ISBLANK($A78),"",NOW()-TODAY()) -> 0.63285475 | D78: =C78+0.0208333 -> 0.65368805 | E78: Matthew Stowers | F78: =IFERROR(VLOOKUP(E78,Data!A$2:B$5,2,TRUE), "") -> 48160 | G78: Fertilize | H78: =IFERROR(VLOOKUP(A78,Customer_Data!$A$1:$P$114,8,TRUE),"") -> 7000 | J78: =IF($G78=("Fall (pre/post emerge)"),"Princep Liquid (100-526)", IF($G78=("Fertilize"),"Harrell's 34-0-5",IF($G78=("Spot Treat"),"Outrider (59639-223)",""))) -> Harrell's 34-0-5 | K78: =(VLOOKUP($J78,Herbicide_Data!$A$1:$L$61,9,TRUE)) -> Nitrogen | L78: =VLOOKUP($J78,Herbicide_Data!$A$1:$L$61,12,TRUE) -> 2.94 | M78: =L78*(H78/43560) -> 0.47245179 | N78: =IF($G78=("Fall (pre/post emerge)"),"Triplet SF (3-Way) 228-312",IF($G78=("Spring Preemerge (Jan)"),"Triplet SF (3-Way) 228-312",IF($G78=("Spring Preemerge (Apr)"),"Triplet SF (3-Way) 228-312",""))) | O78: =VLOOKUP($N78,Herbicide_Data!$A$1:$L$61,9) -> #N/A | P78: =VLOOKUP($N78,Herbicide_Data!$A$1:$P$61,13) -> #N/A | Q78: =P78*($H78/43560) -> #N/A | R78: =IF($G78=("Fall (pre/post emerge)"),"Resolute 4Fl (100-1139)",IF($G78=("Spring Preemerge (Jan)"),"Resolute 4Fl (100-1139)",IF($G78=("Spring Preemerge (Apr)"),"Certinty Turf 59639-226",""))) | S78: =VLOOKUP($R78,Herbicide_Data!$A$1:$L$61,9) -> #N/A | T78: =VLOOKUP($R78,Herbicide_Data!$A$1:$Q$61,13) -> #N/A | U78: =T78*($H78/43560) -> #N/A | V78: =IF($G78 = ("Preemerge"),"MSM Turf 228-373") -> FALSE | W78: =VLOOKUP($V78,Herbicide_Data!$A$1:$L$17,9) -> #N/A | X78: =VLOOKUP($V78,Herbicide_Data!$A$1:$L$17,12) -> #N/A | Y78: =X78*($H78/43560) -> #N/A | AH78: =IF($G78=("Spring Preemerge (Jan)"),"Surfactant",IF($G78=("Spring Preemerge (Apr)"),"Surfactant","")) | AI78: =VLOOKUP($AH78,Herbicide_Data!$A$1:$Q$61,13) -> #N/A | AJ78: =AI78*($H78/43560) -> #N/A
A79: Danny Cooper | B79: 45952 | C79: =IF(ISBLANK($A79),"",NOW()-TODAY()) -> 0.63285475 | D79: =C79+0.0208333 -> 0.65368805 | E79: Matthew Stowers | F79: =IFERROR(VLOOKUP(E79,Data!A$2:B$5,2,TRUE), "") -> 48160 | G79: Fall (pre/post emerge) | H79: =IFERROR(VLOOKUP(A79,Customer_Data!$A$1:$P$114,8,TRUE),"") -> 7000 | J79: =IF($G79=("Fall (pre/post emerge)"),"Princep Liquid (100-526)", IF($G79=("Fertilize"),"Harrell's 34-0-5",IF($G79=("Spot Treat"),"Outrider (59639-223)",""))) -> Princep Liquid (100-526) | K79: =(VLOOKUP($J79,Herbicide_Data!$A$1:$L$61,9,TRUE)) -> Simazine | L79: =VLOOKUP($J79,Herbicide_Data!$A$1:$L$61,12,TRUE) -> 32 | M79: =L79*(H79/43560) -> 5.1423324 | N79: =IF($G79=("Fall (pre/post emerge)"),"Triplet SF (3-Way) 228-312",IF($G79=("Spring Preemerge (Jan)"),"Triplet SF (3-Way) 228-312",IF($G79=("Spring Preemerge (Apr)"),"Triplet SF (3-Way) 228-312",""))) -> Triplet SF (3-Way) 228-312 | O79: =VLOOKUP($N79,Herbicide_Data!$A$1:$L$61,9) -> 2,4-D, dimethylamine salt; Dicamba, dimethylamine salt;Mecoprop-p (MCPP-p), dimethylamine salt | P79: =VLOOKUP($N79,Herbicide_Data!$A$1:$P$61,13) -> 24 | Q79: =P79*($H79/43560) -> 3.8567493 | R79: =IF($G79=("Fall (pre/post emerge)"),"Resolute 4Fl (100-1139)",IF($G79=("Spring Preemerge (Jan)"),"Resolute 4Fl (100-1139)",IF($G79=("Spring Preemerge (Apr)"),"Certinty Turf 59639-226",""))) -> Resolute 4Fl (100-1139) | S79: =VLOOKUP($R79,Herbicide_Data!$A$1:$L$61,9) -> Prodiamine | T79: =VLOOKUP($R79,Herbicide_Data!$A$1:$Q$61,13) -> 16 | U79: =T79*($H79/43560) -> 2.5711662 | V79: =IF($G79 = ("Preemerge"),"MSM Turf 228-373") -> FALSE | W79: =VLOOKUP($V79,Herbicide_Data!$A$1:$L$17,9) -> #N/A | X79: =VLOOKUP($V79,Herbicide_Data!$A$1:$L$17,12) -> #N/A | Y79: =X79*($H79/43560) -> #N/A | AH79: =IF($G79=("Spring Preemerge (Jan)"),"Surfactant",IF($G79=("Spring Preemerge (Apr)"),"Surfactant","")) | AI79: =VLOOKUP($AH79,Herbicide_Data!$A$1:$Q$61,13) -> #N/A | AJ79: =AI79*($H79/43560) -> #N/A
A80: Troy Stokes | B80: 45801 | C80: =IF(ISBLANK($A80),"",NOW()-TODAY()) -> 0.63285475 | D80: =C80+0.0208333 -> 0.65368805 | E80: Matthew Stowers | F80: =IFERROR(VLOOKUP(E80,Data!A$2:B$5,2,TRUE), "") -> 48160 | G80: Fertilize | H80: =IFERROR(VLOOKUP(A80,Customer_Data!$A$1:$P$114,8,TRUE),"") -> 9000 | J80: =IF($G80=("Fall (pre/post emerge)"),"Princep Liquid (100-526)", IF($G80=("Fertilize"),"Harrell's 34-0-5",IF($G80=("Spot Treat"),"Outrider (59639-223)",""))) -> Harrell's 34-0-5 | K80: =(VLOOKUP($J80,Herbicide_Data!$A$1:$L$61,9,TRUE)) -> Nitrogen | L80: =VLOOKUP($J80,Herbicide_Data!$A$1:$L$61,12,TRUE) -> 2.94 | M80: =L80*(H80/43560) -> 0.60743802 | N80: =IF($G80=("Fall (pre/post emerge)"),"Triplet SF (3-Way) 228-312",IF($G80=("Spring Preemerge (Jan)"),"Triplet SF (3-Way) 228-312",IF($G80=("Spring Preemerge (Apr)"),"Triplet SF (3-Way) 228-312",""))) | O80: =VLOOKUP($N80,Herbicide_Data!$A$1:$L$61,9) -> #N/A | P80: =VLOOKUP($N80,Herbicide_Data!$A$1:$P$61,13) -> #N/A | Q80: =P80*($H80/43560) -> #N/A | R80: =IF($G80=("Fall (pre/post emerge)"),"Resolute 4Fl (100-1139)",IF($G80=("Spring Preemerge (Jan)"),"Resolute 4Fl (100-1139)",IF($G80=("Spring Preemerge (Apr)"),"Certinty Turf 59639-226",""))) | S80: =VLOOKUP($R80,Herbicide_Data!$A$1:$L$61,9) -> #N/A | T80: =VLOOKUP($R80,Herbicide_Data!$A$1:$Q$61,13) -> #N/A | U80: =T80*($H80/43560) -> #N/A | V80: =IF($G80 = ("Preemerge"),"MSM Turf 228-373") -> FALSE | W80: =VLOOKUP($V80,Herbicide_Data!$A$1:$L$17,9) -> #N/A | X80: =VLOOKUP($V80,Herbicide_Data!$A$1:$L$17,12) -> #N/A | Y80: =X80*($H80/43560) -> #N/A | AH80: =IF($G80=("Spring Preemerge (Jan)"),"Surfactant",IF($G80=("Spring Preemerge (Apr)"),"Surfactant","")) | AI80: =VLOOKUP($AH80,Herbicide_Data!$A$1:$Q$61,13) -> #N/A | AJ80: =AI80*($H80/43560) -> #N/A
... A93: Roe Grubbs | B93: 45950 | C93: =IF(ISBLANK($A93),"",NOW()-TODAY()) -> 0.63285475 | D93: =C93+0.0208333 -> 0.65368805 | E93: Matthew Stowers | F93: =IFERROR(VLOOKUP(E93,Data!A$2:B$5,2,TRUE), "") -> 48160 | G93: Fall (pre/post emerge) | H93: =IFERROR(VLOOKUP(A93,Customer_Data!$A$1:$P$114,8,TRUE),"") -> 5000 | J93: =IF($G93=("Fall (pre/post emerge)"),"Princep Liquid (100-526)", IF($G93=("Fertilize"),"Harrell's 34-0-5",IF($G93=("Spot Treat"),"Outrider (59639-223)",""))) -> Princep Liquid (100-526) | K93: =(VLOOKUP($J93,Herbicide_Data!$A$1:$L$61,9,TRUE)) -> Simazine | L93: =VLOOKUP($J93,Herbicide_Data!$A$1:$L$61,12,TRUE) -> 32 | M93: =L93*(H93/43560) -> 3.6730946 | N93: =IF($G93=("Fall (pre/post emerge)"),"Triplet SF (3-Way) 228-312",IF($G93=("Spring Preemerge (Jan)"),"Triplet SF (3-Way) 228-312",IF($G93=("Spring Preemerge (Apr)"),"Triplet SF (3-Way) 228-312",""))) -> Triplet SF (3-Way) 228-312 | O93: =VLOOKUP($N93,Herbicide_Data!$A$1:$L$61,9) -> 2,4-D, dimethylamine salt; Dicamba, dimethylamine salt;Mecoprop-p (MCPP-p), dimethylamine salt | P93: =VLOOKUP($N93,Herbicide_Data!$A$1:$P$61,13) -> 24 | Q93: =P93*($H93/43560) -> 2.7548209 | R93: =IF($G93=("Fall (pre/post emerge)"),"Resolute 4Fl (100-1139)",IF($G93=("Spring Preemerge (Jan)"),"Resolute 4Fl (100-1139)",IF($G93=("Spring Preemerge (Apr)"),"Certinty Turf 59639-226",""))) -> Resolute 4Fl (100-1139) | S93: =VLOOKUP($R93,Herbicide_Data!$A$1:$L$61,9) -> Prodiamine | T93: =VLOOKUP($R93,Herbicide_Data!$A$1:$Q$61,13) -> 16 | U93: =T93*($H93/43560) -> 1.8365473 | V93: =IF($G93 = ("Preemerge"),"MSM Turf 228-373") -> FALSE | W93: =VLOOKUP($V93,Herbicide_Data!$A$1:$L$17,9) -> #N/A | X93: =VLOOKUP($V93,Herbicide_Data!$A$1:$L$17,12) -> #N/A | Y93: =X93*($H93/43560) -> #N/A | AH93: =IF($G93=("Spring Preemerge (Jan)"),"Surfactant",IF($G93=("Spring Preemerge (Apr)"),"Surfactant","")) | AI93: =VLOOKUP($AH93,Herbicide_Data!$A$1:$Q$61,13) -> #N/A | AJ93: =AI93*($H93/43560) -> #N/A
A94: Carl Easley | B94: 45798 | C94: 0.41666667 | D94: =C94+0.0208333 -> 0.43749997 | E94: Matthew Stowers | F94: =IFERROR(VLOOKUP(E94,Data!A$2:B$5,2,TRUE), "") -> 48160 | G94: Fertilize | H94: =IFERROR(VLOOKUP(A94,Customer_Data!$A$1:$P$114,8,TRUE),"") -> 8000 | J94: =IF($G94=("Fall (pre/post emerge)"),"Princep Liquid (100-526)", IF($G94=("Fertilize"),"Harrell's 34-0-5",IF($G94=("Spot Treat"),"Outrider (59639-223)",""))) -> Harrell's 34-0-5 | K94: =(VLOOKUP($J94,Herbicide_Data!$A$1:$L$61,9,TRUE)) -> Nitrogen | L94: =VLOOKUP($J94,Herbicide_Data!$A$1:$L$61,12,TRUE) -> 2.94 | M94: =L94*(H94/43560) -> 0.5399449 | N94: =IF($G94=("Fall (pre/post emerge)"),"Triplet SF (3-Way) 228-312",IF($G94=("Spring Preemerge (Jan)"),"Triplet SF (3-Way) 228-312",IF($G94=("Spring Preemerge (Apr)"),"Triplet SF (3-Way) 228-312",""))) | O94: =VLOOKUP($N94,Herbicide_Data!$A$1:$L$61,9) -> #N/A | P94: =VLOOKUP($N94,Herbicide_Data!$A$1:$P$61,13) -> #N/A | Q94: =P94*($H94/43560) -> #N/A | R94: =IF($G94=("Fall (pre/post emerge)"),"Resolute 4Fl (100-1139)",IF($G94=("Spring Preemerge (Jan)"),"Resolute 4Fl (100-1139)",IF($G94=("Spring Preemerge (Apr)"),"Certinty Turf 59639-226",""))) | S94: =VLOOKUP($R94,Herbicide_Data!$A$1:$L$61,9) -> #N/A | T94: =VLOOKUP($R94,Herbicide_Data!$A$1:$Q$61,13) -> #N/A | U94: =T94*($H94/43560) -> #N/A | V94: =IF($G94 = ("Preemerge"),"MSM Turf 228-373") -> FALSE | W94: =VLOOKUP($V94,Herbicide_Data!$A$1:$L$17,9) -> #N/A | X94: =VLOOKUP($V94,Herbicide_Data!$A$1:$L$17,12) -> #N/A | Y94: =X94*($H94/43560) -> #N/A | AH94: =IF($G94=("Spring Preemerge (Jan)"),"Surfactant",IF($G94=("Spring Preemerge (Apr)"),"Surfactant","")) | AI94: =VLOOKUP($AH94,Herbicide_Data!$A$1:$Q$61,13) -> #N/A | AJ94: =AI94*($H94/43560) -> #N/A
A95: Sandra Rainer | B95: 45807 | C95: =IF(ISBLANK($A95),"",NOW()-TODAY()) -> 0.63285475 | D95: =C95+0.0208333 -> 0.65368805 | E95: Matthew Stowers | F95: =IFERROR(VLOOKUP(E95,Data!A$2:B$5,2,TRUE), "") -> 48160 | G95: Fertilize | H95: =IFERROR(VLOOKUP(A95,Customer_Data!$A$1:$P$114,8,TRUE),"") -> 14000 | J95: =IF($G95=("Fall (pre/post emerge)"),"Princep Liquid (100-526)", IF($G95=("Fertilize"),"Harrell's 34-0-5",IF($G95=("Spot Treat"),"Outrider (59639-223)",""))) -> Harrell's 34-0-5 | K95: =(VLOOKUP($J95,Herbicide_Data!$A$1:$L$61,9,TRUE)) -> Nitrogen | L95: =VLOOKUP($J95,Herbicide_Data!$A$1:$L$61,12,TRUE) -> 2.94 | M95: =L95*(H95/43560) -> 0.94490358 | N95: =IF($G95=("Fall (pre/post emerge)"),"Triplet SF (3-Way) 228-312",IF($G95=("Spring Preemerge (Jan)"),"Triplet SF (3-Way) 228-312",IF($G95=("Spring Preemerge (Apr)"),"Triplet SF (3-Way) 228-312",""))) | O95: =VLOOKUP($N95,Herbicide_Data!$A$1:$L$61,9) -> #N/A | P95: =VLOOKUP($N95,Herbicide_Data!$A$1:$P$61,13) -> #N/A | Q95: =P95*($H95/43560) -> #N/A | R95: =IF($G95=("Fall (pre/post emerge)"),"Resolute 4Fl (100-1139)",IF($G95=("Spring Preemerge (Jan)"),"Resolute 4Fl (100-1139)",IF($G95=("Spring Preemerge (Apr)"),"Certinty Turf 59639-226",""))) | S95: =VLOOKUP($R95,Herbicide_Data!$A$1:$L$61,9) -> #N/A | T95: =VLOOKUP($R95,Herbicide_Data!$A$1:$Q$61,13) -> #N/A | U95: =T95*($H95/43560) -> #N/A | V95: =IF($G95 = ("Preemerge"),"MSM Turf 228-373") -> FALSE | W95: =VLOOKUP($V95,Herbicide_Data!$A$1:$L$17,9) -> #N/A | X95: =VLOOKUP($V95,Herbicide_Data!$A$1:$L$17,12) -> #N/A | Y95: =X95*($H95/43560) -> #N/A | AH95: =IF($G95=("Spring Preemerge (Jan)"),"Surfactant",IF($G95=("Spring Preemerge (Apr)"),"Surfactant","")) | AI95: =VLOOKUP($AH95,Herbicide_Data!$A$1:$Q$61,13) -> #N/A | AJ95: =AI95*($H95/43560) -> #N/A
A96: Allen Barnes | B96: 45950 | C96: =IF(ISBLANK($A96),"",NOW()-TODAY()) -> 0.63285475 | D96: =C96+0.0208333 -> 0.65368805 | E96: Matthew Stowers | F96: =IFERROR(VLOOKUP(E96,Data!A$2:B$5,2,TRUE), "") -> 48160 | G96: Fall (pre/post emerge) | H96: 6600 | J96: =IF($G96=("Fall (pre/post emerge)"),"Princep Liquid (100-526)", IF($G96=("Fertilize"),"Harrell's 34-0-5",IF($G96=("Spot Treat"),"Outrider (59639-223)",""))) -> Princep Liquid (100-526) | K96: =(VLOOKUP($J96,Herbicide_Data!$A$1:$L$61,9,TRUE)) -> Simazine | L96: =VLOOKUP($J96,Herbicide_Data!$A$1:$L$61,12,TRUE) -> 32 | M96: =L96*(H96/43560) -> 4.8484848 | N96: =IF($G96=("Fall (pre/post emerge)"),"Triplet SF (3-Way) 228-312",IF($G96=("Spring Preemerge (Jan)"),"Triplet SF (3-Way) 228-312",IF($G96=("Spring Preemerge (Apr)"),"Triplet SF (3-Way) 228-312",""))) -> Triplet SF (3-Way) 228-312 | O96: =VLOOKUP($N96,Herbicide_Data!$A$1:$L$61,9) -> 2,4-D, dimethylamine salt; Dicamba, dimethylamine salt;Mecoprop-p (MCPP-p), dimethylamine salt | P96: =VLOOKUP($N96,Herbicide_Data!$A$1:$P$61,13) -> 24 | Q96: =P96*($H96/43560) -> 3.6363636 | R96: =IF($G96=("Fall (pre/post emerge)"),"Resolute 4Fl (100-1139)",IF($G96=("Spring Preemerge (Jan)"),"Resolute 4Fl (100-1139)",IF($G96=("Spring Preemerge (Apr)"),"Certinty Turf 59639-226",""))) -> Resolute 4Fl (100-1139) | S96: =VLOOKUP($R96,Herbicide_Data!$A$1:$L$61,9) -> Prodiamine | T96: =VLOOKUP($R96,Herbicide_Data!$A$1:$Q$61,13) -> 16 | U96: =T96*($H96/43560) -> 2.4242424 | V96: =IF($G96 = ("Preemerge"),"MSM Turf 228-373") -> FALSE | W96: =VLOOKUP($V96,Herbicide_Data!$A$1:$L$17,9) -> #N/A | X96: =VLOOKUP($V96,Herbicide_Data!$A$1:$L$17,12) -> #N/A | Y96: =X96*($H96/43560) -> #N/A | AH96: =IF($G96=("Spring Preemerge (Jan)"),"Surfactant",IF($G96=("Spring Preemerge (Apr)"),"Surfactant","")) | AI96: =VLOOKUP($AH96,Herbicide_Data!$A$1:$Q$61,13) -> #N/A | AJ96: =AI96*($H96/43560) -> #N/A
A97: Gary Jordan | B97: 45952 | C97: =IF(ISBLANK($A97),"",NOW()-TODAY()) -> 0.63285475 | D97: =C97+0.0208333 -> 0.65368805 | E97: Matthew Stowers | F97: =IFERROR(VLOOKUP(E97,Data!A$2:B$5,2,TRUE), "") -> 48160 | G97: Fall (pre/post emerge) | H97: =IFERROR(VLOOKUP(A97,Customer_Data!$A$1:$P$114,8,TRUE),"") -> 8000 | J97: =IF($G97=("Fall (pre/post emerge)"),"Princep Liquid (100-526)", IF($G97=("Fertilize"),"Harrell's 34-0-5",IF($G97=("Spot Treat"),"Outrider (59639-223)",""))) -> Princep Liquid (100-526) | K97: =(VLOOKUP($J97,Herbicide_Data!$A$1:$L$61,9,TRUE)) -> Simazine | L97: =VLOOKUP($J97,Herbicide_Data!$A$1:$L$61,12,TRUE) -> 32 | M97: =L97*(H97/43560) -> 5.8769513 | N97: =IF($G97=("Fall (pre/post emerge)"),"Triplet SF (3-Way) 228-312",IF($G97=("Spring Preemerge (Jan)"),"Triplet SF (3-Way) 228-312",IF($G97=("Spring Preemerge (Apr)"),"Triplet SF (3-Way) 228-312",""))) -> Triplet SF (3-Way) 228-312 | O97: =VLOOKUP($N97,Herbicide_Data!$A$1:$L$61,9) -> 2,4-D, dimethylamine salt; Dicamba, dimethylamine salt;Mecoprop-p (MCPP-p), dimethylamine salt | P97: =VLOOKUP($N97,Herbicide_Data!$A$1:$P$61,13) -> 24 | Q97: =P97*($H97/43560) -> 4.4077135 | R97: =IF($G97=("Fall (pre/post emerge)"),"Resolute 4Fl (100-1139)",IF($G97=("Spring Preemerge (Jan)"),"Resolute 4Fl (100-1139)",IF($G97=("Spring Preemerge (Apr)"),"Certinty Turf 59639-226",""))) -> Resolute 4Fl (100-1139) | S97: =VLOOKUP($R97,Herbicide_Data!$A$1:$L$61,9) -> Prodiamine | T97: =VLOOKUP($R97,Herbicide_Data!$A$1:$Q$61,13) -> 16 | U97: =T97*($H97/43560) -> 2.9384757 | V97: =IF($G97 = ("Preemerge"),"MSM Turf 228-373") -> FALSE | W97: =VLOOKUP($V97,Herbicide_Data!$A$1:$L$17,9) -> #N/A | X97: =VLOOKUP($V97,Herbicide_Data!$A$1:$L$17,12) -> #N/A | Y97: =X97*($H97/43560) -> #N/A | AH97: =IF($G97=("Spring Preemerge (Jan)"),"Surfactant",IF($G97=("Spring Preemerge (Apr)"),"Surfactant","")) | AI97: =VLOOKUP($AH97,Herbicide_Data!$A$1:$Q$61,13) -> #N/A | AJ97: =AI97*($H97/43560) -> #N/A
A98: Luther Holmes | B98: 46074 | C98: 0.45833333 | D98: =C98+0.0208333 -> 0.47916663 | E98: Matthew Stowers | F98: =IFERROR(VLOOKUP(E98,Data!A$2:B$5,2,TRUE), "") -> 48160 | G98: Spring Preemerge (Jan) | H98: =IFERROR(VLOOKUP(A98,Customer_Data!$A$1:$P$114,8,TRUE),"") -> 3687 | J98: =IF($G98=("Fall (pre/post emerge)"),"Princep Liquid (100-526)", IF($G98=("Fertilize"),"Harrell's 34-0-5",IF($G98=("Spot Treat"),"Outrider (59639-223)",""))) | K98: =(VLOOKUP($J98,Herbicide_Data!$A$1:$L$61,9,TRUE)) -> #N/A | L98: =VLOOKUP($J98,Herbicide_Data!$A$1:$L$61,12,TRUE) -> #N/A | M98: =L98*(H98/43560) -> #N/A | N98: =IF($G98=("Fall (pre/post emerge)"),"Triplet SF (3-Way) 228-312",IF($G98=("Spring Preemerge (Jan)"),"Triplet SF (3-Way) 228-312",IF($G98=("Spring Preemerge (Apr)"),"Triplet SF (3-Way) 228-312",""))) -> Triplet SF (3-Way) 228-312 | O98: =VLOOKUP($N98,Herbicide_Data!$A$1:$L$61,9) -> 2,4-D, dimethylamine salt; Dicamba, dimethylamine salt;Mecoprop-p (MCPP-p), dimethylamine salt | P98: =VLOOKUP($N98,Herbicide_Data!$A$1:$P$61,13) -> 24 | Q98: =P98*($H98/43560) -> 2.031405 | R98: =IF($G98=("Fall (pre/post emerge)"),"Resolute 4Fl (100-1139)",IF($G98=("Spring Preemerge (Jan)"),"Resolute 4Fl (100-1139)",IF($G98=("Spring Preemerge (Apr)"),"Certinty Turf 59639-226",""))) -> Resolute 4Fl (100-1139) | S98: =VLOOKUP($R98,Herbicide_Data!$A$1:$L$61,9) -> Prodiamine | T98: =VLOOKUP($R98,Herbicide_Data!$A$1:$Q$61,13) -> 16 | U98: =T98*($H98/43560) -> 1.35427 | V98: =IF($G98 = ("Preemerge"),"MSM Turf 228-373") -> FALSE | W98: =VLOOKUP($V98,Herbicide_Data!$A$1:$L$17,9) -> #N/A | X98: =VLOOKUP($V98,Herbicide_Data!$A$1:$L$17,12) -> #N/A | Y98: =X98*($H98/43560) -> #N/A | AH98: =IF($G98=("Spring Preemerge (Jan)"),"Surfactant",IF($G98=("Spring Preemerge (Apr)"),"Surfactant","")) -> Surfactant | AI98: =VLOOKUP($AH98,Herbicide_Data!$A$1:$Q$61,13) -> 12.8 | AJ98: =AI98*($H98/43560) -> 1.083416
A99: Riley Cooper | B99: 46074 | C99: =IF(ISBLANK($A99),"",NOW()-TODAY()) -> 0.63285475 | D99: =C99+0.0208333 -> 0.65368805 | E99: Matthew Stowers | F99: =IFERROR(VLOOKUP(E99,Data!A$2:B$5,2,TRUE), "") -> 48160 | G99: Spring Preemerge (Jan) | H99: =IFERROR(VLOOKUP(A99,Customer_Data!$A$1:$P$114,8,TRUE),"") -> 4150 | J99: =IF($G99=("Fall (pre/post emerge)"),"Princep Liquid (100-526)", IF($G99=("Fertilize"),"Harrell's 34-0-5",IF($G99=("Spot Treat"),"Outrider (59639-223)",""))) | K99: =(VLOOKUP($J99,Herbicide_Data!$A$1:$L$61,9,TRUE)) -> #N/A | L99: =VLOOKUP($J99,Herbicide_Data!$A$1:$L$61,12,TRUE) -> #N/A | M99: =L99*(H99/43560) -> #N/A | N99: =IF($G99=("Fall (pre/post emerge)"),"Triplet SF (3-Way) 228-312",IF($G99=("Spring Preemerge (Jan)"),"Triplet SF (3-Way) 228-312",IF($G99=("Spring Preemerge (Apr)"),"Triplet SF (3-Way) 228-312",""))) -> Triplet SF (3-Way) 228-312 | O99: =VLOOKUP($N99,Herbicide_Data!$A$1:$L$61,9) -> 2,4-D, dimethylamine salt; Dicamba, dimethylamine salt;Mecoprop-p (MCPP-p), dimethylamine salt | P99: =VLOOKUP($N99,Herbicide_Data!$A$1:$P$61,13) -> 24 | Q99: =P99*($H99/43560) -> 2.2865014 | R99: =IF($G99=("Fall (pre/post emerge)"),"Resolute 4Fl (100-1139)",IF($G99=("Spring Preemerge (Jan)"),"Resolute 4Fl (100-1139)",IF($G99=("Spring Preemerge (Apr)"),"Certinty Turf 59639-226",""))) -> Resolute 4Fl (100-1139) | S99: =VLOOKUP($R99,Herbicide_Data!$A$1:$L$61,9) -> Prodiamine | T99: =VLOOKUP($R99,Herbicide_Data!$A$1:$Q$61,13) -> 16 | U99: =T99*($H99/43560) -> 1.5243343 | V99: =IF($G99 = ("Preemerge"),"MSM Turf 228-373") -> FALSE | W99: =VLOOKUP($V99,Herbicide_Data!$A$1:$L$17,9) -> #N/A | X99: =VLOOKUP($V99,Herbicide_Data!$A$1:$L$17,12) -> #N/A | Y99: =X99*($H99/43560) -> #N/A | AH99: =IF($G99=("Spring Preemerge (Jan)"),"Surfactant",IF($G99=("Spring Preemerge (Apr)"),"Surfactant","")) -> Surfactant | AI99: =VLOOKUP($AH99,Herbicide_Data!$A$1:$Q$61,13) -> 12.8 | AJ99: =AI99*($H99/43560) -> 1.2194674
A100: Thomas Wilson | B100: 46074 | C100: 0.375 | D100: =C100+0.0208333 -> 0.3958333 | E100: Matthew Stowers | F100: =IFERROR(VLOOKUP(E100,Data!A$2:B$5,2,TRUE), "") -> 48160 | G100: Spring Preemerge (Jan) | H100: =IFERROR(VLOOKUP(A100,Customer_Data!$A$1:$P$114,8,TRUE),"") -> 3875 | J100: =IF($G100=("Fall (pre/post emerge)"),"Princep Liquid (100-526)", IF($G100=("Fertilize"),"Harrell's 34-0-5",IF($G100=("Spot Treat"),"Outrider (59639-223)",""))) | K100: =(VLOOKUP($J100,Herbicide_Data!$A$1:$L$61,9,TRUE)) -> #N/A | L100: =VLOOKUP($J100,Herbicide_Data!$A$1:$L$61,12,TRUE) -> #N/A | M100: =L100*(H100/43560) -> #N/A | N100: =IF($G100=("Fall (pre/post emerge)"),"Triplet SF (3-Way) 228-312",IF($G100=("Spring Preemerge (Jan)"),"Triplet SF (3-Way) 228-312",IF($G100=("Spring Preemerge (Apr)"),"Triplet SF (3-Way) 228-312",""))) -> Triplet SF (3-Way) 228-312 | O100: =VLOOKUP($N100,Herbicide_Data!$A$1:$L$61,9) -> 2,4-D, dimethylamine salt; Dicamba, dimethylamine salt;Mecoprop-p (MCPP-p), dimethylamine salt | P100: =VLOOKUP($N100,Herbicide_Data!$A$1:$P$61,13) -> 24 | Q100: =P100*($H100/43560) -> 2.1349862 | R100: =IF($G100=("Fall (pre/post emerge)"),"Resolute 4Fl (100-1139)",IF($G100=("Spring Preemerge (Jan)"),"Resolute 4Fl (100-1139)",IF($G100=("Spring Preemerge (Apr)"),"Certinty Turf 59639-226",""))) -> Resolute 4Fl (100-1139) | S100: =VLOOKUP($R100,Herbicide_Data!$A$1:$L$61,9) -> Prodiamine | T100: =VLOOKUP($R100,Herbicide_Data!$A$1:$Q$61,13) -> 16 | U100: =T100*($H100/43560) -> 1.4233242 | V100: =IF($G100 = ("Preemerge"),"MSM Turf 228-373") -> FALSE | W100: =VLOOKUP($V100,Herbicide_Data!$A$1:$L$17,9) -> #N/A | X100: =VLOOKUP($V100,Herbicide_Data!$A$1:$L$17,12) -> #N/A | Y100: =X100*($H100/43560) -> #N/A | AH100: =IF($G100=("Spring Preemerge (Jan)"),"Surfactant",IF($G100=("Spring Preemerge (Apr)"),"Surfactant","")) -> Surfactant | AI100: =VLOOKUP($AH100,Herbicide_Data!$A$1:$Q$61,13) -> 12.8 | AJ100: =AI100*($H100/43560) -> 1.1386593
A101: Steve Edwards | B101: 46074 | C101: 0.41666667 | D101: =C101+0.0208333 -> 0.43749997 | E101: Matthew Stowers | F101: =IFERROR(VLOOKUP(E101,Data!A$2:B$5,2,TRUE), "") -> 48160 | G101: Spring Preemerge (Jan) | H101: =IFERROR(VLOOKUP(A101,Customer_Data!$A$1:$P$114,8,TRUE),"") -> 9000 | J101: =IF($G101=("Fall (pre/post emerge)"),"Princep Liquid (100-526)", IF($G101=("Fertilize"),"Harrell's 34-0-5",IF($G101=("Spot Treat"),"Outrider (59639-223)",""))) | K101: =(VLOOKUP($J101,Herbicide_Data!$A$1:$L$61,9,TRUE)) -> #N/A | L101: =VLOOKUP($J101,Herbicide_Data!$A$1:$L$61,12,TRUE) -> #N/A | M101: =L101*(H101/43560) -> #N/A | N101: =IF($G101=("Fall (pre/post emerge)"),"Triplet SF (3-Way) 228-312",IF($G101=("Spring Preemerge (Jan)"),"Triplet SF (3-Way) 228-312",IF($G101=("Spring Preemerge (Apr)"),"Triplet SF (3-Way) 228-312",""))) -> Triplet SF (3-Way) 228-312 | O101: =VLOOKUP($N101,Herbicide_Data!$A$1:$L$61,9) -> 2,4-D, dimethylamine salt; Dicamba, dimethylamine salt;Mecoprop-p (MCPP-p), dimethylamine salt | P101: =VLOOKUP($N101,Herbicide_Data!$A$1:$P$61,13) -> 24 | Q101: =P101*($H101/43560) -> 4.9586777 | R101: =IF($G101=("Fall (pre/post emerge)"),"Resolute 4Fl (100-1139)",IF($G101=("Spring Preemerge (Jan)"),"Resolute 4Fl (100-1139)",IF($G101=("Spring Preemerge (Apr)"),"Certinty Turf 59639-226",""))) -> Resolute 4Fl (100-1139) | S101: =VLOOKUP($R101,Herbicide_Data!$A$1:$L$61,9) -> Prodiamine | T101: =VLOOKUP($R101,Herbicide_Data!$A$1:$Q$61,13) -> 16 | U101: =T101*($H101/43560) -> 3.3057851 | V101: =IF($G101 = ("Preemerge"),"MSM Turf 228-373") -> FALSE | W101: =VLOOKUP($V101,Herbicide_Data!$A$1:$L$17,9) -> #N/A | X101: =VLOOKUP($V101,Herbicide_Data!$A$1:$L$17,12) -> #N/A | Y101: =X101*($H101/43560) -> #N/A | AH101: =IF($G101=("Spring Preemerge (Jan)"),"Surfactant",IF($G101=("Spring Preemerge (Apr)"),"Surfactant","")) -> Surfactant | AI101: =VLOOKUP($AH101,Herbicide_Data!$A$1:$Q$61,13) -> 12.8 | AJ101: =AI101*($H101/43560) -> 2.6446281
A102: Browning Bergold | B102: 46074 | C102: 0.5 | D102: =C102+0.0208333 -> 0.5208333 | E102: Matthew Stowers | F102: =IFERROR(VLOOKUP(E102,Data!A$2:B$5,2,TRUE), "") -> 48160 | G102: Spring Preemerge (Jan) | H102: =IFERROR(VLOOKUP(A102,Customer_Data!$A$1:$P$114,8,TRUE),"") -> 6400 | J102: =IF($G102=("Fall (pre/post emerge)"),"Princep Liquid (100-526)", IF($G102=("Fertilize"),"Harrell's 34-0-5",IF($G102=("Spot Treat"),"Outrider (59639-223)",""))) | K102: =(VLOOKUP($J102,Herbicide_Data!$A$1:$L$61,9,TRUE)) -> #N/A | L102: =VLOOKUP($J102,Herbicide_Data!$A$1:$L$61,12,TRUE) -> #N/A | M102: =L102*(H102/43560) -> #N/A | N102: =IF($G102=("Fall (pre/post emerge)"),"Triplet SF (3-Way) 228-312",IF($G102=("Spring Preemerge (Jan)"),"Triplet SF (3-Way) 228-312",IF($G102=("Spring Preemerge (Apr)"),"Triplet SF (3-Way) 228-312",""))) -> Triplet SF (3-Way) 228-312 | O102: =VLOOKUP($N102,Herbicide_Data!$A$1:$L$61,9) -> 2,4-D, dimethylamine salt; Dicamba, dimethylamine salt;Mecoprop-p (MCPP-p), dimethylamine salt | P102: =VLOOKUP($N102,Herbicide_Data!$A$1:$P$61,13) -> 24 | Q102: =P102*($H102/43560) -> 3.5261708 | R102: =IF($G102=("Fall (pre/post emerge)"),"Resolute 4Fl (100-1139)",IF($G102=("Spring Preemerge (Jan)"),"Resolute 4Fl (100-1139)",IF($G102=("Spring Preemerge (Apr)"),"Certinty Turf 59639-226",""))) -> Resolute 4Fl (100-1139) | S102: =VLOOKUP($R102,Herbicide_Data!$A$1:$L$61,9) -> Prodiamine | T102: =VLOOKUP($R102,Herbicide_Data!$A$1:$Q$61,13) -> 16 | U102: =T102*($H102/43560) -> 2.3507805 | V102: =IF($G102 = ("Preemerge"),"MSM Turf 228-373") -> FALSE | W102: =VLOOKUP($V102,Herbicide_Data!$A$1:$L$17,9) -> #N/A | X102: =VLOOKUP($V102,Herbicide_Data!$A$1:$L$17,12) -> #N/A | Y102: =X102*($H102/43560) -> #N/A | AH102: =IF($G102=("Spring Preemerge (Jan)"),"Surfactant",IF($G102=("Spring Preemerge (Apr)"),"Surfactant","")) -> Surfactant | AI102: =VLOOKUP($AH102,Herbicide_Data!$A$1:$Q$61,13) -> 12.8 | AJ102: =AI102*($H102/43560) -> 1.8806244
A103: Dot Stuart | B103: 46081 | C103: =IF(ISBLANK($A103),"",NOW()-TODAY()) -> 0.63285475 | D103: =C103+0.0208333 -> 0.65368805 | E103: Matthew Stowers | F103: =IFERROR(VLOOKUP(E103,Data!A$2:B$5,2,TRUE), "") -> 48160 | G103: Spring Preemerge (Jan) | H103: =IFERROR(VLOOKUP(A103,Customer_Data!$A$1:$P$114,8,TRUE),"") -> 1800 | J103: =IF($G103=("Fall (pre/post emerge)"),"Princep Liquid (100-526)", IF($G103=("Fertilize"),"Harrell's 34-0-5",IF($G103=("Spot Treat"),"Outrider (59639-223)",""))) | K103: =(VLOOKUP($J103,Herbicide_Data!$A$1:$L$61,9,TRUE)) -> #N/A | L103: =VLOOKUP($J103,Herbicide_Data!$A$1:$L$61,12,TRUE) -> #N/A | M103: =L103*(H103/43560) -> #N/A | N103: =IF($G103=("Fall (pre/post emerge)"),"Triplet SF (3-Way) 228-312",IF($G103=("Spring Preemerge (Jan)"),"Triplet SF (3-Way) 228-312",IF($G103=("Spring Preemerge (Apr)"),"Triplet SF (3-Way) 228-312",""))) -> Triplet SF (3-Way) 228-312 | O103: =VLOOKUP($N103,Herbicide_Data!$A$1:$L$61,9) -> 2,4-D, dimethylamine salt; Dicamba, dimethylamine salt;Mecoprop-p (MCPP-p), dimethylamine salt | P103: =VLOOKUP($N103,Herbicide_Data!$A$1:$P$61,13) -> 24 | Q103: =P103*($H103/43560) -> 0.99173554 | R103: =IF($G103=("Fall (pre/post emerge)"),"Resolute 4Fl (100-1139)",IF($G103=("Spring Preemerge (Jan)"),"Resolute 4Fl (100-1139)",IF($G103=("Spring Preemerge (Apr)"),"Certinty Turf 59639-226",""))) -> Resolute 4Fl (100-1139) | S103: =VLOOKUP($R103,Herbicide_Data!$A$1:$L$61,9) -> Prodiamine | T103: =VLOOKUP($R103,Herbicide_Data!$A$1:$Q$61,13) -> 16 | U103: =T103*($H103/43560) -> 0.66115702 | V103: =IF($G103 = ("Preemerge"),"MSM Turf 228-373") -> FALSE | W103: =VLOOKUP($V103,Herbicide_Data!$A$1:$L$17,9) -> #N/A | X103: =VLOOKUP($V103,Herbicide_Data!$A$1:$L$17,12) -> #N/A | Y103: =X103*($H103/43560) -> #N/A | AH103: =IF($G103=("Spring Preemerge (Jan)"),"Surfactant",IF($G103=("Spring Preemerge (Apr)"),"Surfactant","")) -> Surfactant | AI103: =VLOOKUP($AH103,Herbicide_Data!$A$1:$Q$61,13) -> 12.8 | AJ103: =AI103*($H103/43560) -> 0.52892562
A104: Matt Runner | B104: 46081 | C104: 0.4375 | D104: =C104+0.0208333 -> 0.4583333 | E104: Matthew Stowers | F104: =IFERROR(VLOOKUP(E104,Data!A$2:B$5,2,TRUE), "") -> 48160 | G104: Spring Preemerge (Jan) | H104: =IFERROR(VLOOKUP(A104,Customer_Data!$A$1:$P$114,8,TRUE),"") -> 2000 | J104: =IF($G104=("Fall (pre/post emerge)"),"Princep Liquid (100-526)", IF($G104=("Fertilize"),"Harrell's 34-0-5",IF($G104=("Spot Treat"),"Outrider (59639-223)",""))) | K104: =(VLOOKUP($J104,Herbicide_Data!$A$1:$L$61,9,TRUE)) -> #N/A | L104: =VLOOKUP($J104,Herbicide_Data!$A$1:$L$61,12,TRUE) -> #N/A | M104: =L104*(H104/43560) -> #N/A | N104: =IF($G104=("Fall (pre/post emerge)"),"Triplet SF (3-Way) 228-312",IF($G104=("Spring Preemerge (Jan)"),"Triplet SF (3-Way) 228-312",IF($G104=("Spring Preemerge (Apr)"),"Triplet SF (3-Way) 228-312",""))) -> Triplet SF (3-Way) 228-312 | O104: =VLOOKUP($N104,Herbicide_Data!$A$1:$L$61,9) -> 2,4-D, dimethylamine salt; Dicamba, dimethylamine salt;Mecoprop-p (MCPP-p), dimethylamine salt | P104: =VLOOKUP($N104,Herbicide_Data!$A$1:$P$61,13) -> 24 | Q104: =P104*($H104/43560) -> 1.1019284 | R104: =IF($G104=("Fall (pre/post emerge)"),"Resolute 4Fl (100-1139)",IF($G104=("Spring Preemerge (Jan)"),"Resolute 4Fl (100-1139)",IF($G104=("Spring Preemerge (Apr)"),"Certinty Turf 59639-226",""))) -> Resolute 4Fl (100-1139) | S104: =VLOOKUP($R104,Herbicide_Data!$A$1:$L$61,9) -> Prodiamine | T104: =VLOOKUP($R104,Herbicide_Data!$A$1:$Q$61,13) -> 16 | U104: =T104*($H104/43560) -> 0.73461892 | V104: =IF($G104 = ("Preemerge"),"MSM Turf 228-373") -> FALSE | W104: =VLOOKUP($V104,Herbicide_Data!$A$1:$L$17,9) -> #N/A | X104: =VLOOKUP($V104,Herbicide_Data!$A$1:$L$17,12) -> #N/A | Y104: =X104*($H104/43560) -> #N/A | AH104: =IF($G104=("Spring Preemerge (Jan)"),"Surfactant",IF($G104=("Spring Preemerge (Apr)"),"Surfactant","")) -> Surfactant | AI104: =VLOOKUP($AH104,Herbicide_Data!$A$1:$Q$61,13) -> 12.8 | AJ104: =AI104*($H104/43560) -> 0.58769513
A105: Bo Whatley | B105: 46081 | C105: 0.46875 | D105: =C105+0.0208333 -> 0.4895833 | E105: Matthew Stowers | F105: =IFERROR(VLOOKUP(E105,Data!A$2:B$5,2,TRUE), "") -> 48160 | G105: Spring Preemerge (Jan) | H105: =IFERROR(VLOOKUP(A105,Customer_Data!$A$1:$P$114,8,TRUE),"") -> 2750 | J105: =IF($G105=("Fall (pre/post emerge)"),"Princep Liquid (100-526)", IF($G105=("Fertilize"),"Harrell's 34-0-5",IF($G105=("Spot Treat"),"Outrider (59639-223)",""))) | K105: =(VLOOKUP($J105,Herbicide_Data!$A$1:$L$61,9,TRUE)) -> #N/A | L105: =VLOOKUP($J105,Herbicide_Data!$A$1:$L$61,12,TRUE) -> #N/A | M105: =L105*(H105/43560) -> #N/A | N105: =IF($G105=("Fall (pre/post emerge)"),"Triplet SF (3-Way) 228-312",IF($G105=("Spring Preemerge (Jan)"),"Triplet SF (3-Way) 228-312",IF($G105=("Spring Preemerge (Apr)"),"Triplet SF (3-Way) 228-312",""))) -> Triplet SF (3-Way) 228-312 | O105: =VLOOKUP($N105,Herbicide_Data!$A$1:$L$61,9) -> 2,4-D, dimethylamine salt; Dicamba, dimethylamine salt;Mecoprop-p (MCPP-p), dimethylamine salt | P105: =VLOOKUP($N105,Herbicide_Data!$A$1:$P$61,13) -> 24 | Q105: =P105*($H105/43560) -> 1.5151515 | R105: =IF($G105=("Fall (pre/post emerge)"),"Resolute 4Fl (100-1139)",IF($G105=("Spring Preemerge (Jan)"),"Resolute 4Fl (100-1139)",IF($G105=("Spring Preemerge (Apr)"),"Certinty Turf 59639-226",""))) -> Resolute 4Fl (100-1139) | S105: =VLOOKUP($R105,Herbicide_Data!$A$1:$L$61,9) -> Prodiamine | T105: =VLOOKUP($R105,Herbicide_Data!$A$1:$Q$61,13) -> 16 | U105: =T105*($H105/43560) -> 1.010101 | V105: =IF($G105 = ("Preemerge"),"MSM Turf 228-373") -> FALSE | W105: =VLOOKUP($V105,Herbicide_Data!$A$1:$L$17,9) -> #N/A | X105: =VLOOKUP($V105,Herbicide_Data!$A$1:$L$17,12) -> #N/A | Y105: =X105*($H105/43560) -> #N/A | AH105: =IF($G105=("Spring Preemerge (Jan)"),"Surfactant",IF($G105=("Spring Preemerge (Apr)"),"Surfactant","")) -> Surfactant | AI105: =VLOOKUP($AH105,Herbicide_Data!$A$1:$Q$61,13) -> 12.8 | AJ105: =AI105*($H105/43560) -> 0.80808081
A106: Max Brian | B106: 46081 | C106: 0.5 | D106: =C106+0.0208333 -> 0.5208333 | E106: Matthew Stowers | F106: =IFERROR(VLOOKUP(E106,Data!A$2:B$5,2,TRUE), "") -> 48160 | G106: Spring Preemerge (Jan) | H106: =IFERROR(VLOOKUP(A106,Customer_Data!$A$1:$P$114,8,TRUE),"") -> 4670 | J106: =IF($G106=("Fall (pre/post emerge)"),"Princep Liquid (100-526)", IF($G106=("Fertilize"),"Harrell's 34-0-5",IF($G106=("Spot Treat"),"Outrider (59639-223)",""))) | K106: =(VLOOKUP($J106,Herbicide_Data!$A$1:$L$61,9,TRUE)) -> #N/A | L106: =VLOOKUP($J106,Herbicide_Data!$A$1:$L$61,12,TRUE) -> #N/A | M106: =L106*(H106/43560) -> #N/A | N106: =IF($G106=("Fall (pre/post emerge)"),"Triplet SF (3-Way) 228-312",IF($G106=("Spring Preemerge (Jan)"),"Triplet SF (3-Way) 228-312",IF($G106=("Spring Preemerge (Apr)"),"Triplet SF (3-Way) 228-312",""))) -> Triplet SF (3-Way) 228-312 | O106: =VLOOKUP($N106,Herbicide_Data!$A$1:$L$61,9) -> 2,4-D, dimethylamine salt; Dicamba, dimethylamine salt;Mecoprop-p (MCPP-p), dimethylamine salt | P106: =VLOOKUP($N106,Herbicide_Data!$A$1:$P$61,13) -> 24 | Q106: =P106*($H106/43560) -> 2.5730028 | R106: =IF($G106=("Fall (pre/post emerge)"),"Resolute 4Fl (100-1139)",IF($G106=("Spring Preemerge (Jan)"),"Resolute 4Fl (100-1139)",IF($G106=("Spring Preemerge (Apr)"),"Certinty Turf 59639-226",""))) -> Resolute 4Fl (100-1139) | S106: =VLOOKUP($R106,Herbicide_Data!$A$1:$L$61,9) -> Prodiamine | T106: =VLOOKUP($R106,Herbicide_Data!$A$1:$Q$61,13) -> 16 | U106: =T106*($H106/43560) -> 1.7153352 | V106: =IF($G106 = ("Preemerge"),"MSM Turf 228-373") -> FALSE | W106: =VLOOKUP($V106,Herbicide_Data!$A$1:$L$17,9) -> #N/A | X106: =VLOOKUP($V106,Herbicide_Data!$A$1:$L$17,12) -> #N/A | Y106: =X106*($H106/43560) -> #N/A | AH106: =IF($G106=("Spring Preemerge (Jan)"),"Surfactant",IF($G106=("Spring Preemerge (Apr)"),"Surfactant","")) -> Surfactant | AI106: =VLOOKUP($AH106,Herbicide_Data!$A$1:$Q$61,13) -> 12.8 | AJ106: =AI106*($H106/43560) -> 1.3722681
A107: Elliot Smith | B107: 46081 | C107: 0.52083333 | D107: =C107+0.0208333 -> 0.54166663 | E107: Matthew Stowers | F107: =IFERROR(VLOOKUP(E107,Data!A$2:B$5,2,TRUE), "") -> 48160 | G107: Spring Preemerge (Jan) | H107: =IFERROR(VLOOKUP(A107,Customer_Data!$A$1:$P$114,8,TRUE),"") -> 13500 | J107: =IF($G107=("Fall (pre/post emerge)"),"Princep Liquid (100-526)", IF($G107=("Fertilize"),"Harrell's 34-0-5",IF($G107=("Spot Treat"),"Outrider (59639-223)",""))) | K107: =(VLOOKUP($J107,Herbicide_Data!$A$1:$L$61,9,TRUE)) -> #N/A | L107: =VLOOKUP($J107,Herbicide_Data!$A$1:$L$61,12,TRUE) -> #N/A | M107: =L107*(H107/43560) -> #N/A | N107: =IF($G107=("Fall (pre/post emerge)"),"Triplet SF (3-Way) 228-312",IF($G107=("Spring Preemerge (Jan)"),"Triplet SF (3-Way) 228-312",IF($G107=("Spring Preemerge (Apr)"),"Triplet SF (3-Way) 228-312",""))) -> Triplet SF (3-Way) 228-312 | O107: =VLOOKUP($N107,Herbicide_Data!$A$1:$L$61,9) -> 2,4-D, dimethylamine salt; Dicamba, dimethylamine salt;Mecoprop-p (MCPP-p), dimethylamine salt | P107: =VLOOKUP($N107,Herbicide_Data!$A$1:$P$61,13) -> 24 | Q107: =P107*($H107/43560) -> 7.4380165 | R107: =IF($G107=("Fall (pre/post emerge)"),"Resolute 4Fl (100-1139)",IF($G107=("Spring Preemerge (Jan)"),"Resolute 4Fl (100-1139)",IF($G107=("Spring Preemerge (Apr)"),"Certinty Turf 59639-226",""))) -> Resolute 4Fl (100-1139) | S107: =VLOOKUP($R107,Herbicide_Data!$A$1:$L$61,9) -> Prodiamine | T107: =VLOOKUP($R107,Herbicide_Data!$A$1:$Q$61,13) -> 16 | U107: =T107*($H107/43560) -> 4.9586777 | V107: =IF($G107 = ("Preemerge"),"MSM Turf 228-373") -> FALSE | W107: =VLOOKUP($V107,Herbicide_Data!$A$1:$L$17,9) -> #N/A | X107: =VLOOKUP($V107,Herbicide_Data!$A$1:$L$17,12) -> #N/A | Y107: =X107*($H107/43560) -> #N/A | AH107: =IF($G107=("Spring Preemerge (Jan)"),"Surfactant",IF($G107=("Spring Preemerge (Apr)"),"Surfactant","")) -> Surfactant | AI107: =VLOOKUP($AH107,Herbicide_Data!$A$1:$Q$61,13) -> 12.8 | AJ107: =AI107*($H107/43560) -> 3.9669421
A108: Troy Stokes | B108: 46081 | C108: 0.54166667 | D108: =C108+0.0208333 -> 0.56249997 | E108: Matthew Stowers | F108: =IFERROR(VLOOKUP(E108,Data!A$2:B$5,2,TRUE), "") -> 48160 | G108: Spring Preemerge (Jan) | H108: =IFERROR(VLOOKUP(A108,Customer_Data!$A$1:$P$114,8,TRUE),"") -> 9000 | J108: =IF($G108=("Fall (pre/post emerge)"),"Princep Liquid (100-526)", IF($G108=("Fertilize"),"Harrell's 34-0-5",IF($G108=("Spot Treat"),"Outrider (59639-223)",""))) | K108: =(VLOOKUP($J108,Herbicide_Data!$A$1:$L$61,9,TRUE)) -> #N/A | L108: =VLOOKUP($J108,Herbicide_Data!$A$1:$L$61,12,TRUE) -> #N/A | M108: =L108*(H108/43560) -> #N/A | N108: =IF($G108=("Fall (pre/post emerge)"),"Triplet SF (3-Way) 228-312",IF($G108=("Spring Preemerge (Jan)"),"Triplet SF (3-Way) 228-312",IF($G108=("Spring Preemerge (Apr)"),"Triplet SF (3-Way) 228-312",""))) -> Triplet SF (3-Way) 228-312 | O108: =VLOOKUP($N108,Herbicide_Data!$A$1:$L$61,9) -> 2,4-D, dimethylamine salt; Dicamba, dimethylamine salt;Mecoprop-p (MCPP-p), dimethylamine salt | P108: =VLOOKUP($N108,Herbicide_Data!$A$1:$P$61,13) -> 24 | Q108: =P108*($H108/43560) -> 4.9586777 | R108: =IF($G108=("Fall (pre/post emerge)"),"Resolute 4Fl (100-1139)",IF($G108=("Spring Preemerge (Jan)"),"Resolute 4Fl (100-1139)",IF($G108=("Spring Preemerge (Apr)"),"Certinty Turf 59639-226",""))) -> Resolute 4Fl (100-1139) | S108: =VLOOKUP($R108,Herbicide_Data!$A$1:$L$61,9) -> Prodiamine | T108: =VLOOKUP($R108,Herbicide_Data!$A$1:$Q$61,13) -> 16 | U108: =T108*($H108/43560) -> 3.3057851 | V108: =IF($G108 = ("Preemerge"),"MSM Turf 228-373") -> FALSE | W108: =VLOOKUP($V108,Herbicide_Data!$A$1:$L$17,9) -> #N/A | X108: =VLOOKUP($V108,Herbicide_Data!$A$1:$L$17,12) -> #N/A | Y108: =X108*($H108/43560) -> #N/A | AH108: =IF($G108=("Spring Preemerge (Jan)"),"Surfactant",IF($G108=("Spring Preemerge (Apr)"),"Surfactant","")) -> Surfactant | AI108: =VLOOKUP($AH108,Herbicide_Data!$A$1:$Q$61,13) -> 12.8 | AJ108: =AI108*($H108/43560) -> 2.6446281
A109: Gay Grantham | B109: 46081 | C109: 0.5625 | D109: =C109+0.0208333 -> 0.5833333 | E109: Matthew Stowers | F109: =IFERROR(VLOOKUP(E109,Data!A$2:B$5,2,TRUE), "") -> 48160 | G109: Spring Preemerge (Jan) | H109: =IFERROR(VLOOKUP(A109,Customer_Data!$A$1:$P$114,8,TRUE),"") -> 5900 | J109: =IF($G109=("Fall (pre/post emerge)"),"Princep Liquid (100-526)", IF($G109=("Fertilize"),"Harrell's 34-0-5",IF($G109=("Spot Treat"),"Outrider (59639-223)",""))) | K109: =(VLOOKUP($J109,Herbicide_Data!$A$1:$L$61,9,TRUE)) -> #N/A | L109: =VLOOKUP($J109,Herbicide_Data!$A$1:$L$61,12,TRUE) -> #N/A | M109: =L109*(H109/43560) -> #N/A | N109: =IF($G109=("Fall (pre/post emerge)"),"Triplet SF (3-Way) 228-312",IF($G109=("Spring Preemerge (Jan)"),"Triplet SF (3-Way) 228-312",IF($G109=("Spring Preemerge (Apr)"),"Triplet SF (3-Way) 228-312",""))) -> Triplet SF (3-Way) 228-312 | O109: =VLOOKUP($N109,Herbicide_Data!$A$1:$L$61,9) -> 2,4-D, dimethylamine salt; Dicamba, dimethylamine salt;Mecoprop-p (MCPP-p), dimethylamine salt | P109: =VLOOKUP($N109,Herbicide_Data!$A$1:$P$61,13) -> 24 | Q109: =P109*($H109/43560) -> 3.2506887 | R109: =IF($G109=("Fall (pre/post emerge)"),"Resolute 4Fl (100-1139)",IF($G109=("Spring Preemerge (Jan)"),"Resolute 4Fl (100-1139)",IF($G109=("Spring Preemerge (Apr)"),"Certinty Turf 59639-226",""))) -> Resolute 4Fl (100-1139) | S109: =VLOOKUP($R109,Herbicide_Data!$A$1:$L$61,9) -> Prodiamine | T109: =VLOOKUP($R109,Herbicide_Data!$A$1:$Q$61,13) -> 16 | U109: =T109*($H109/43560) -> 2.1671258 | V109: =IF($G109 = ("Preemerge"),"MSM Turf 228-373") -> FALSE | W109: =VLOOKUP($V109,Herbicide_Data!$A$1:$L$17,9) -> #N/A | X109: =VLOOKUP($V109,Herbicide_Data!$A$1:$L$17,12) -> #N/A | Y109: =X109*($H109/43560) -> #N/A | AH109: =IF($G109=("Spring Preemerge (Jan)"),"Surfactant",IF($G109=("Spring Preemerge (Apr)"),"Surfactant","")) -> Surfactant | AI109: =VLOOKUP($AH109,Herbicide_Data!$A$1:$Q$61,13) -> 12.8 | AJ109: =AI109*($H109/43560) -> 1.7337006
A110: Gene Henderson | B110: 46081 | C110: 0.58333333 | D110: =C110+0.0208333 -> 0.60416663 | E110: Matthew Stowers | F110: =IFERROR(VLOOKUP(E110,Data!A$2:B$5,2,TRUE), "") -> 48160 | G110: Spring Preemerge (Jan) | H110: =IFERROR(VLOOKUP(A110,Customer_Data!$A$1:$P$114,8,TRUE),"") -> 11000 | J110: =IF($G110=("Fall (pre/post emerge)"),"Princep Liquid (100-526)", IF($G110=("Fertilize"),"Harrell's 34-0-5",IF($G110=("Spot Treat"),"Outrider (59639-223)",""))) | K110: =(VLOOKUP($J110,Herbicide_Data!$A$1:$L$61,9,TRUE)) -> #N/A | L110: =VLOOKUP($J110,Herbicide_Data!$A$1:$L$61,12,TRUE) -> #N/A | M110: =L110*(H110/43560) -> #N/A | N110: =IF($G110=("Fall (pre/post emerge)"),"Triplet SF (3-Way) 228-312",IF($G110=("Spring Preemerge (Jan)"),"Triplet SF (3-Way) 228-312",IF($G110=("Spring Preemerge (Apr)"),"Triplet SF (3-Way) 228-312",""))) -> Triplet SF (3-Way) 228-312 | O110: =VLOOKUP($N110,Herbicide_Data!$A$1:$L$61,9) -> 2,4-D, dimethylamine salt; Dicamba, dimethylamine salt;Mecoprop-p (MCPP-p), dimethylamine salt | P110: =VLOOKUP($N110,Herbicide_Data!$A$1:$P$61,13) -> 24 | Q110: =P110*($H110/43560) -> 6.0606061 | R110: =IF($G110=("Fall (pre/post emerge)"),"Resolute 4Fl (100-1139)",IF($G110=("Spring Preemerge (Jan)"),"Resolute 4Fl (100-1139)",IF($G110=("Spring Preemerge (Apr)"),"Certinty Turf 59639-226",""))) -> Resolute 4Fl (100-1139) | S110: =VLOOKUP($R110,Herbicide_Data!$A$1:$L$61,9) -> Prodiamine | T110: =VLOOKUP($R110,Herbicide_Data!$A$1:$Q$61,13) -> 16 | U110: =T110*($H110/43560) -> 4.040404 | V110: =IF($G110 = ("Preemerge"),"MSM Turf 228-373") -> FALSE | W110: =VLOOKUP($V110,Herbicide_Data!$A$1:$L$17,9) -> #N/A | X110: =VLOOKUP($V110,Herbicide_Data!$A$1:$L$17,12) -> #N/A | Y110: =X110*($H110/43560) -> #N/A | AH110: =IF($G110=("Spring Preemerge (Jan)"),"Surfactant",IF($G110=("Spring Preemerge (Apr)"),"Surfactant","")) -> Surfactant | AI110: =VLOOKUP($AH110,Herbicide_Data!$A$1:$Q$61,13) -> 12.8 | AJ110: =AI110*($H110/43560) -> 3.2323232
A111: Roe Grubbs | B111: 46081 | C111: 0.60416667 | D111: =C111+0.0208333 -> 0.62499997 | E111: Matthew Stowers | F111: =IFERROR(VLOOKUP(E111,Data!A$2:B$5,2,TRUE), "") -> 48160 | G111: Spring Preemerge (Jan) | H111: =IFERROR(VLOOKUP(A111,Customer_Data!$A$1:$P$114,8,TRUE),"") -> 5000 | J111: =IF($G111=("Fall (pre/post emerge)"),"Princep Liquid (100-526)", IF($G111=("Fertilize"),"Harrell's 34-0-5",IF($G111=("Spot Treat"),"Outrider (59639-223)",""))) | K111: =(VLOOKUP($J111,Herbicide_Data!$A$1:$L$61,9,TRUE)) -> #N/A | L111: =VLOOKUP($J111,Herbicide_Data!$A$1:$L$61,12,TRUE) -> #N/A | M111: =L111*(H111/43560) -> #N/A | N111: =IF($G111=("Fall (pre/post emerge)"),"Triplet SF (3-Way) 228-312",IF($G111=("Spring Preemerge (Jan)"),"Triplet SF (3-Way) 228-312",IF($G111=("Spring Preemerge (Apr)"),"Triplet SF (3-Way) 228-312",""))) -> Triplet SF (3-Way) 228-312 | O111: =VLOOKUP($N111,Herbicide_Data!$A$1:$L$61,9) -> 2,4-D, dimethylamine salt; Dicamba, dimethylamine salt;Mecoprop-p (MCPP-p), dimethylamine salt | P111: =VLOOKUP($N111,Herbicide_Data!$A$1:$P$61,13) -> 24 | Q111: =P111*($H111/43560) -> 2.7548209 | R111: =IF($G111=("Fall (pre/post emerge)"),"Resolute 4Fl (100-1139)",IF($G111=("Spring Preemerge (Jan)"),"Resolute 4Fl (100-1139)",IF($G111=("Spring Preemerge (Apr)"),"Certinty Turf 59639-226",""))) -> Resolute 4Fl (100-1139) | S111: =VLOOKUP($R111,Herbicide_Data!$A$1:$L$61,9) -> Prodiamine | T111: =VLOOKUP($R111,Herbicide_Data!$A$1:$Q$61,13) -> 16 | U111: =T111*($H111/43560) -> 1.8365473 | V111: =IF($G111 = ("Preemerge"),"MSM Turf 228-373") -> FALSE | W111: =VLOOKUP($V111,Herbicide_Data!$A$1:$L$17,9) -> #N/A | X111: =VLOOKUP($V111,Herbicide_Data!$A$1:$L$17,12) -> #N/A | Y111: =X111*($H111/43560) -> #N/A | AH111: =IF($G111=("Spring Preemerge (Jan)"),"Surfactant",IF($G111=("Spring Preemerge (Apr)"),"Surfactant","")) -> Surfactant | AI111: =VLOOKUP($AH111,Herbicide_Data!$A$1:$Q$61,13) -> 12.8 | AJ111: =AI111*($H111/43560) -> 1.4692378
A112: Allen Barnes | B112: 46081 | C112: 0.625 | D112: =C112+0.0208333 -> 0.6458333 | E112: Matthew Stowers | F112: =IFERROR(VLOOKUP(E112,Data!A$2:B$5,2,TRUE), "") -> 48160 | G112: Spring Preemerge (Jan) | H112: =IFERROR(VLOOKUP(A112,Customer_Data!$A$1:$P$114,8,TRUE),"") -> 0 | J112: =IF($G112=("Fall (pre/post emerge)"),"Princep Liquid (100-526)", IF($G112=("Fertilize"),"Harrell's 34-0-5",IF($G112=("Spot Treat"),"Outrider (59639-223)",""))) | K112: =(VLOOKUP($J112,Herbicide_Data!$A$1:$L$61,9,TRUE)) -> #N/A | L112: =VLOOKUP($J112,Herbicide_Data!$A$1:$L$61,12,TRUE) -> #N/A | M112: =L112*(H112/43560) -> #N/A | N112: =IF($G112=("Fall (pre/post emerge)"),"Triplet SF (3-Way) 228-312",IF($G112=("Spring Preemerge (Jan)"),"Triplet SF (3-Way) 228-312",IF($G112=("Spring Preemerge (Apr)"),"Triplet SF (3-Way) 228-312",""))) -> Triplet SF (3-Way) 228-312 | O112: =VLOOKUP($N112,Herbicide_Data!$A$1:$L$61,9) -> 2,4-D, dimethylamine salt; Dicamba, dimethylamine salt;Mecoprop-p (MCPP-p), dimethylamine salt | P112: =VLOOKUP($N112,Herbicide_Data!$A$1:$P$61,13) -> 24 | Q112: =P112*($H112/43560) -> 0 | R112: =IF($G112=("Fall (pre/post emerge)"),"Resolute 4Fl (100-1139)",IF($G112=("Spring Preemerge (Jan)"),"Resolute 4Fl (100-1139)",IF($G112=("Spring Preemerge (Apr)"),"Certinty Turf 59639-226",""))) -> Resolute 4Fl (100-1139) | S112: =VLOOKUP($R112,Herbicide_Data!$A$1:$L$61,9) -> Prodiamine | T112: =VLOOKUP($R112,Herbicide_Data!$A$1:$Q$61,13) -> 16 | U112: =T112*($H112/43560) -> 0 | V112: =IF($G112 = ("Preemerge"),"MSM Turf 228-373") -> FALSE | W112: =VLOOKUP($V112,Herbicide_Data!$A$1:$L$17,9) -> #N/A | X112: =VLOOKUP($V112,Herbicide_Data!$A$1:$L$17,12) -> #N/A | Y112: =X112*($H112/43560) -> #N/A | AH112: =IF($G112=("Spring Preemerge (Jan)"),"Surfactant",IF($G112=("Spring Preemerge (Apr)"),"Surfactant","")) -> Surfactant | AI112: =VLOOKUP($AH112,Herbicide_Data!$A$1:$Q$61,13) -> 12.8 | AJ112: =AI112*($H112/43560) -> 0
...

Sheet Application Report
A1: Customer Name | B1: Customer Street | C1: Customer City | D1: Customer State | E1: Customer Zip | F1: Application Date | G1: Applicator | H1: ID number | I1: Treatment Type | J1: Size of Area Treated | L1: Brand Name 1 & EPA Number | M1: Active Ingredients | N1: Rate per Acre | O1: Total Amount Applied (Oz) | P1: Brand Name 2 | Q1: Active Ingredients | R1: Rate per Acre | S1: Total Amount Applied (Oz) | T1: Brand Name 3 | U1: Active Ingredients | V1: Rate per Acre | W1: Total Amount Applied (Oz) | X1: Brand Name 4 | Y1: Active Ingredients | Z1: Rate per Acre | AA1: Total Amount Applied (Oz) | AB1: Brand Name 5 | AC1: Active Ingredients | AD1: Rate per Acre | AE1: Total Amount Applied (Oz)
A2: =Applications!A3 -> Dot Stuart | B2: =VLOOKUP($A2,Customer_Data!$A$1:$R$161,3,TRUE) -> 414 Providence Drive | C2: =VLOOKUP($A2,Customer_Data!$A$1:$R$161,4,TRUE) -> Brandon | D2: =VLOOKUP($A2,Customer_Data!$A$1:$R$161,5,TRUE) -> MS | E2: =VLOOKUP($A2,Customer_Data!$A$1:$R$161,6,TRUE) -> 39042 | F2: =Applications!B3 -> 45591 | G2: =Applications!E3 -> Matthew Stowers | H2: =Applications!F3 -> 48160 | I2: =Applications!G3 -> Fall (pre/post emerge) | J2: =Applications!H3 -> 1800 | L2: =Applications!J3 -> Princep Liquid (100-526) | M2: =Applications!K3 -> Simazine | N2: =Applications!L3 -> 32 | O2: =Applications!M3 -> 1.322314 | P2: =Applications!N3 -> Triplet SF (3-Way) 228-312 | Q2: =Applications!O3 -> 2,4-D, dimethylamine salt; Dicamba, dimethylamine salt;Mecoprop-p (MCPP-p), dimethylamine salt | R2: =Applications!P3 -> 24 | S2: =Applications!Q3 -> 0.99173554 | ... AE2: =Applications!AC3 -> 0
A3: =Applications!A4 -> Matt Runner | B3: =VLOOKUP($A3,Customer_Data!$A$1:$R$161,3,TRUE) -> 528 Acadian Ct. | C3: =VLOOKUP($A3,Customer_Data!$A$1:$R$161,4,TRUE) -> Brandon | D3: =VLOOKUP($A3,Customer_Data!$A$1:$R$161,5,TRUE) -> MS | E3: =VLOOKUP($A3,Customer_Data!$A$1:$R$161,6,TRUE) -> 39042 | F3: =Applications!B4 -> 45591 | G3: =Applications!E4 -> Matthew Stowers | H3: =Applications!F4 -> 48160 | I3: =Applications!G4 -> Fall (pre/post emerge) | J3: =Applications!H4 -> 2000 | L3: =Applications!J4 -> Princep Liquid (100-526) | M3: =Applications!K4 -> Simazine | N3: =Applications!L4 -> 32 | O3: =Applications!M4 -> 1.4692378 | P3: =Applications!N4 -> Triplet SF (3-Way) 228-312 | Q3: =Applications!O4 -> 2,4-D, dimethylamine salt; Dicamba, dimethylamine salt;Mecoprop-p (MCPP-p), dimethylamine salt | R3: =Applications!P4 -> 24 | S3: =Applications!Q4 -> 1.1019284 | ... AE3: =Applications!AC4 -> 0
A4: =Applications!A5 -> Luther Stowers | B4: =VLOOKUP($A4,Customer_Data!$A$1:$R$161,3,TRUE) -> 325 North Brandon Blvd. | C4: =VLOOKUP($A4,Customer_Data!$A$1:$R$161,4,TRUE) -> Brandon | D4: =VLOOKUP($A4,Customer_Data!$A$1:$R$161,5,TRUE) -> MS | E4: =VLOOKUP($A4,Customer_Data!$A$1:$R$161,6,TRUE) -> 39042 | F4: =Applications!B5 -> 45591 | G4: =Applications!E5 -> Luther Stowers | H4: =Applications!F5 -> 48182 | I4: =Applications!G5 -> Fall (pre/post emerge) | J4: =Applications!H5 -> 5361 | L4: =Applications!J5 -> Princep Liquid (100-526) | M4: =Applications!K5 -> Simazine | N4: =Applications!L5 -> 32 | O4: =Applications!M5 -> 3.938292 | P4: =Applications!N5 -> Triplet SF (3-Way) 228-312 | Q4: =Applications!O5 -> 2,4-D, dimethylamine salt; Dicamba, dimethylamine salt;Mecoprop-p (MCPP-p), dimethylamine salt | R4: =Applications!P5 -> 24 | S4: =Applications!Q5 -> 2.953719 | ... AE4: =Applications!AC5 -> 0
A5: =Applications!A6 -> Bobby Fatheree | B5: =VLOOKUP($A5,Customer_Data!$A$1:$R$161,3,TRUE) -> 283 Rockbridge Drive | C5: =VLOOKUP($A5,Customer_Data!$A$1:$R$161,4,TRUE) -> Madison | D5: =VLOOKUP($A5,Customer_Data!$A$1:$R$161,5,TRUE) -> MS | E5: =VLOOKUP($A5,Customer_Data!$A$1:$R$161,6,TRUE) -> 39110 | F5: =Applications!B6 -> 45592 | G5: =Applications!E6 -> Matthew Stowers | H5: =Applications!F6 -> 48160 | I5: =Applications!G6 -> Fall (pre/post emerge) | J5: =Applications!H6 -> 8850 | L5: =Applications!J6 -> Princep Liquid (100-526) | M5: =Applications!K6 -> Simazine | N5: =Applications!L6 -> 32 | O5: =Applications!M6 -> 6.5013774 | P5: =Applications!N6 -> Triplet SF (3-Way) 228-312 | Q5: =Applications!O6 -> 2,4-D, dimethylamine salt; Dicamba, dimethylamine salt;Mecoprop-p (MCPP-p), dimethylamine salt | R5: =Applications!P6 -> 24 | S5: =Applications!Q6 -> 4.8760331 | ... AE5: =Applications!AC6 -> 0
A6: =Applications!A7 -> Asa Barnes | B6: =VLOOKUP($A6,Customer_Data!$A$1:$R$161,3,TRUE) -> 314 Buttonwood Lane | C6: =VLOOKUP($A6,Customer_Data!$A$1:$R$161,4,TRUE) -> Canton | D6: =VLOOKUP($A6,Customer_Data!$A$1:$R$161,5,TRUE) -> MS | E6: =VLOOKUP($A6,Customer_Data!$A$1:$R$161,6,TRUE) -> 39046 | F6: =Applications!B7 -> 45592 | G6: =Applications!E7 -> Matthew Stowers | H6: =Applications!F7 -> 48160 | I6: =Applications!G7 -> Fall (pre/post emerge) | J6: =Applications!H7 -> 6575 | L6: =Applications!J7 -> Princep Liquid (100-526) | M6: =Applications!K7 -> Simazine | N6: =Applications!L7 -> 32 | O6: =Applications!M7 -> 4.8301194 | P6: =Applications!N7 -> Triplet SF (3-Way) 228-312 | Q6: =Applications!O7 -> 2,4-D, dimethylamine salt; Dicamba, dimethylamine salt;Mecoprop-p (MCPP-p), dimethylamine salt | R6: =Applications!P7 -> 24 | S6: =Applications!Q7 -> 3.6225895 | ... AE6: =Applications!AC7 -> 0
A7: =Applications!A8 -> David Fatheree | B7: =VLOOKUP($A7,Customer_Data!$A$1:$R$161,3,TRUE) -> 706 Ivywood Court | C7: =VLOOKUP($A7,Customer_Data!$A$1:$R$161,4,TRUE) -> Madison | D7: =VLOOKUP($A7,Customer_Data!$A$1:$R$161,5,TRUE) -> MS | E7: =VLOOKUP($A7,Customer_Data!$A$1:$R$161,6,TRUE) -> 39110 | F7: =Applications!B8 -> 45592 | G7: =Applications!E8 -> Matthew Stowers | H7: =Applications!F8 -> 48160 | I7: =Applications!G8 -> Fall (pre/post emerge) | J7: =Applications!H8 -> 8910 | L7: =Applications!J8 -> Princep Liquid (100-526) | M7: =Applications!K8 -> Simazine | N7: =Applications!L8 -> 32 | O7: =Applications!M8 -> 6.5454545 | P7: =Applications!N8 -> Triplet SF (3-Way) 228-312 | Q7: =Applications!O8 -> 2,4-D, dimethylamine salt; Dicamba, dimethylamine salt;Mecoprop-p (MCPP-p), dimethylamine salt | R7: =Applications!P8 -> 24 | S7: =Applications!Q8 -> 4.9090909 | ... AE7: =Applications!AC8 -> 0
A8: =Applications!A9 -> Matt Stowers | B8: =VLOOKUP($A8,Customer_Data!$A$1:$R$161,3,TRUE) -> 519 Oak Park Circle | C8: =VLOOKUP($A8,Customer_Data!$A$1:$R$161,4,TRUE) -> Pearl | D8: =VLOOKUP($A8,Customer_Data!$A$1:$R$161,5,TRUE) -> MS | E8: =VLOOKUP($A8,Customer_Data!$A$1:$R$161,6,TRUE) -> 39208 | F8: =Applications!B9 -> 45592 | G8: =Applications!E9 -> Matthew Stowers | H8: =Applications!F9 -> 48160 | I8: =Applications!G9 -> Fall (pre/post emerge) | J8: =Applications!H9 -> 6568 | L8: =Applications!J9 -> Princep Liquid (100-526) | M8: =Applications!K9 -> Simazine | N8: =Applications!L9 -> 32 | O8: =Applications!M9 -> 4.824977 | P8: =Applications!N9 -> Triplet SF (3-Way) 228-312 | Q8: =Applications!O9 -> 2,4-D, dimethylamine salt; Dicamba, dimethylamine salt;Mecoprop-p (MCPP-p), dimethylamine salt | R8: =Applications!P9 -> 24 | S8: =Applications!Q9 -> 3.6187328 | ... AE8: =Applications!AC9 -> 0
A9: =Applications!A10 -> Luther Holmes | B9: =VLOOKUP($A9,Customer_Data!$A$1:$R$161,3,TRUE) -> 5481 Kaywood Drive | C9: =VLOOKUP($A9,Customer_Data!$A$1:$R$161,4,TRUE) -> Jackson | D9: =VLOOKUP($A9,Customer_Data!$A$1:$R$161,5,TRUE) -> MS | E9: =VLOOKUP($A9,Customer_Data!$A$1:$R$161,6,TRUE) -> 39211 | F9: =Applications!B10 -> 45604 | G9: =Applications!E10 -> Luther Stowers | H9: =Applications!F10 -> 48182 | I9: =Applications!G10 -> Fall (pre/post emerge) | J9: =Applications!H10 -> 3687 | L9: =Applications!J10 -> Princep Liquid (100-526) | M9: =Applications!K10 -> Simazine | N9: =Applications!L10 -> 32 | O9: =Applications!M10 -> 2.7085399 | P9: =Applications!N10 -> Triplet SF (3-Way) 228-312 | Q9: =Applications!O10 -> 2,4-D, dimethylamine salt; Dicamba, dimethylamine salt;Mecoprop-p (MCPP-p), dimethylamine salt | R9: =Applications!P10 -> 24 | S9: =Applications!Q10 -> 2.031405 | ... AE9: =Applications!AC10 -> 0
A10: =Applications!A11 -> David Fatheree | B10: =VLOOKUP($A10,Customer_Data!$A$1:$R$161,3,TRUE) -> 706 Ivywood Court | C10: =VLOOKUP($A10,Customer_Data!$A$1:$R$161,4,TRUE) -> Madison | D10: =VLOOKUP($A10,Customer_Data!$A$1:$R$161,5,TRUE) -> MS | E10: =VLOOKUP($A10,Customer_Data!$A$1:$R$161,6,TRUE) -> 39110 | F10: =Applications!B11 -> 45710 | G10: =Applications!E11 -> Matthew Stowers | H10: =Applications!F11 -> 48160 | I10: =Applications!G11 -> Spring Preemerge (Jan) | J10: =Applications!H11 -> 8910 | L10: =Applications!J11 | M10: =Applications!K11 -> #N/A | N10: =Applications!L11 -> #N/A | O10: =Applications!M11 -> #N/A | P10: =Applications!N11 -> Triplet SF (3-Way) 228-312 | Q10: =Applications!O11 -> 2,4-D, dimethylamine salt; Dicamba, dimethylamine salt;Mecoprop-p (MCPP-p), dimethylamine salt | R10: =Applications!P11 -> 24 | S10: =Applications!Q11 -> 4.9090909 | ... AE10: =Applications!AC11 -> 0
A11: =Applications!A12 -> Riley Cooper | B11: =VLOOKUP($A11,Customer_Data!$A$1:$R$161,3,TRUE) -> 227 Westfield Road | C11: =VLOOKUP($A11,Customer_Data!$A$1:$R$161,4,TRUE) -> Ridgeland | D11: =VLOOKUP($A11,Customer_Data!$A$1:$R$161,5,TRUE) -> MS | E11: =VLOOKUP($A11,Customer_Data!$A$1:$R$161,6,TRUE) -> 39157 | F11: =Applications!B12 -> 45710 | G11: =Applications!E12 -> Matthew Stowers | H11: =Applications!F12 -> 48160 | I11: =Applications!G12 -> Spring Preemerge (Jan) | J11: =Applications!H12 -> 4150 | L11: =Applications!J12 | M11: =Applications!K12 -> #N/A | N11: =Applications!L12 -> #N/A | O11: =Applications!M12 -> #N/A | P11: =Applications!N12 -> Triplet SF (3-Way) 228-312 | Q11: =Applications!O12 -> 2,4-D, dimethylamine salt; Dicamba, dimethylamine salt;Mecoprop-p (MCPP-p), dimethylamine salt | R11: =Applications!P12 -> 24 | S11: =Applications!Q12 -> 2.2865014 | ... AE11: =Applications!AC12 -> 0
A12: =Applications!A13 -> Thomas Wilson | B12: =VLOOKUP($A12,Customer_Data!$A$1:$R$161,3,TRUE) -> 213 Westfield Road | C12: =VLOOKUP($A12,Customer_Data!$A$1:$R$161,4,TRUE) -> Ridgeland | D12: =VLOOKUP($A12,Customer_Data!$A$1:$R$161,5,TRUE) -> MS | E12: =VLOOKUP($A12,Customer_Data!$A$1:$R$161,6,TRUE) -> 39157 | F12: =Applications!B13 -> 45710 | G12: =Applications!E13 -> Matthew Stowers | H12: =Applications!F13 -> 48160 | I12: =Applications!G13 -> Spring Preemerge (Jan) | J12: =Applications!H13 -> 3875 | L12: =Applications!J13 | M12: =Applications!K13 -> #N/A | N12: =Applications!L13 -> #N/A | O12: =Applications!M13 -> #N/A | P12: =Applications!N13 -> Triplet SF (3-Way) 228-312 | Q12: =Applications!O13 -> 2,4-D, dimethylamine salt; Dicamba, dimethylamine salt;Mecoprop-p (MCPP-p), dimethylamine salt | R12: =Applications!P13 -> 24 | S12: =Applications!Q13 -> 2.1349862 | ... AE12: =Applications!AC13 -> 0
A13: =Applications!A14 -> Max Miller | B13: =VLOOKUP($A13,Customer_Data!$A$1:$R$161,3,TRUE) -> 1021 Cumberland Dr. | C13: =VLOOKUP($A13,Customer_Data!$A$1:$R$161,4,TRUE) -> Brandon | D13: =VLOOKUP($A13,Customer_Data!$A$1:$R$161,5,TRUE) -> MS | E13: =VLOOKUP($A13,Customer_Data!$A$1:$R$161,6,TRUE) -> 39047 | F13: =Applications!B14 -> 45710 | G13: =Applications!E14 -> Matthew Stowers | H13: =Applications!F14 -> 48160 | I13: =Applications!G14 -> Spring Preemerge (Jan) | J13: =Applications!H14 -> 3100 | L13: =Applications!J14 | M13: =Applications!K14 -> #N/A | N13: =Applications!L14 -> #N/A | O13: =Applications!M14 -> #N/A | P13: =Applications!N14 -> Triplet SF (3-Way) 228-312 | Q13: =Applications!O14 -> 2,4-D, dimethylamine salt; Dicamba, dimethylamine salt;Mecoprop-p (MCPP-p), dimethylamine salt | R13: =Applications!P14 -> 24 | S13: =Applications!Q14 -> 1.707989 | ... AE13: =Applications!AC14 -> 0
... A49: =Applications!A50 -> Luther Stowers | B49: =VLOOKUP($A49,Customer_Data!$A$1:$R$161,3,TRUE) -> 325 North Brandon Blvd. | C49: =VLOOKUP($A49,Customer_Data!$A$1:$R$161,4,TRUE) -> Brandon | D49: =VLOOKUP($A49,Customer_Data!$A$1:$R$161,5,TRUE) -> MS | E49: =VLOOKUP($A49,Customer_Data!$A$1:$R$161,6,TRUE) -> 39042 | F49: =Applications!B50 -> 45781 | G49: =Applications!E50 -> Luther Stowers | H49: =Applications!F50 -> 48182 | I49: =Applications!G50 -> Spring Preemerge (Apr) | J49: =Applications!H50 -> 5361 | L49: =Applications!J50 | M49: =Applications!K50 -> #N/A | N49: =Applications!L50 -> #N/A | O49: =Applications!M50 -> #N/A | P49: =Applications!N50 -> Triplet SF (3-Way) 228-312 | Q49: =Applications!O50 -> 2,4-D, dimethylamine salt; Dicamba, dimethylamine salt;Mecoprop-p (MCPP-p), dimethylamine salt | R49: =Applications!P50 -> 24 | S49: =Applications!Q50 -> 2.953719 | ... AE49: =Applications!AC50 -> 0
A50: =Applications!A94 -> Carl Easley | B50: =VLOOKUP($A50,Customer_Data!$A$1:$R$161,3,TRUE) -> 631 Big Valley Loop | C50: =VLOOKUP($A50,Customer_Data!$A$1:$R$161,4,TRUE) -> Flowood | D50: =VLOOKUP($A50,Customer_Data!$A$1:$R$161,5,TRUE) -> MS | E50: =VLOOKUP($A50,Customer_Data!$A$1:$R$161,6,TRUE) -> 39047 | F50: =Applications!B94 -> 45798 | G50: =Applications!E94 -> Matthew Stowers | H50: =Applications!F94 -> 48160 | I50: =Applications!G94 -> Fertilize | J50: =Applications!H94 -> 8000 | L50: =Applications!J94 -> Harrell's 34-0-5 | M50: =Applications!K94 -> Nitrogen | N50: =Applications!L94 -> 2.94 | O50: =Applications!M94 -> 0.5399449 | P50: =Applications!N94 | Q50: =Applications!O94 -> #N/A | R50: =Applications!P94 -> #N/A | S50: =Applications!Q94 -> #N/A | ... AE50: =Applications!AC94 -> 0
